Workbook
Name Reporting_Month: Dashboard!$C$4
Name Truck_Filter: Dashboard!$F$4
Name Gross_Fee_Month: Dashboard!$B$8
Name Cash_Profit_Month: Dashboard!$L$8
Name Margin_Month: Dashboard!$B$12
Name Crew_To_Pay: Dashboard!$H$12
Name Loan_Balance: Dashboard!$J$12
Name Unpaid_Invoices: Dashboard!$L$12

Sheet Dashboard
A1: 🚚 J&Z TRUCKING · COMMAND CENTER
A2: Live figures from every trip, every receipt and every loan. Change the two filters below — the whole page follows.
B3: GO TO ▸ | C3: P&L | D3: Trucks | E3: Loans | F3: Destinations | G3: Crew pay | H3: Trips log | I3: Expenses | J3: Payroll | K3: Setup | L3: Read me
B4: MONTH | C4: 46296 | D4: ◀ change | E4: TRUCK | F4: All | G4: all units | H4: ="vs previous month ▸ fee "&IF(N(Calc!$B$40)=0,"n/a",IF(Calc!$B$7>=Calc!$B$40,"+","")&ROUND((Calc!$B$7/Calc!$B$40-1)*100,1)&"%")&" trips "&IF(N(Calc!$B$41)=0,"n/a",IF(Calc!$B$10>=Calc!$B$41,"+","")&(Calc!$B$10-Calc!$B$41))&" tons "&IF(N(Calc!$B$42)=0,"n/a",IF(Calc!$B$11>=Calc!$B$42,"+","")&ROUND((Calc!$B$11/Calc!$B$42-1)*100,1)&"%")&" (pick a truck to see that unit alone)"
B7: GROSS HAULING FEE | D7: NET HAULING FEE | F7: CREW COST | H7: TRIP NET PROFIT | J7: OPERATING PROFIT | L7: CASH PROFIT AFTER LOANS
B8: =Calc!$B$7 | D8: =Calc!$Q$9 | F8: =Calc!$B$15 | H8: =Calc!$Q$19 | J8: =Calc!$Q$22 | L8: =Calc!$Q$24
B9: total fee invoiced this month | D9: after the 2% withholding tax | F9: driver + helper share + allowance | H9: after fuel, toll & crew | J9: after repairs, rent & overhead | L9: what is really left in your pocket
B11: PROFIT MARGIN | D11: TRIPS DELIVERED | F11: TONS HAULED | H11: STILL TO PAY CREW | J11: LOAN BALANCE | L11: UNPAID INVOICES
B12: =Calc!$Q$25 | D12: =Calc!$B$10 | F12: =Calc!$B$11 | H12: =Calc!$B$30 | J12: =Calc!$B$99 | L12: =Calc!$B$31
B13: cash profit ÷ gross fee | D13: this month | F13: total weight moved | H13: unsettled balance this month | J13: principal still owed, all lenders | L13: customer fees not yet collected
B47: PROFIT & LOSS · selected month
B48: LINE ITEM | D48: AMOUNT | E48: % OF FEE | F48: HOW IT IS BUILT
B49: Gross hauling fee | D49: =Calc!$Q$7 | E49: =IF(Calc!$Q$7=0,"",D49/Calc!$Q$7) | F49: tons × rate × (1 + fuel surcharge)
B50: Withholding tax (2%) | D50: =Calc!$Q$8 | E50: =IF(Calc!$Q$7=0,"",D50/Calc!$Q$7) | F50: 2% withheld by the client
B51: Net hauling fee | D51: =Calc!$Q$9 | E51: =IF(Calc!$Q$7=0,"",D51/Calc!$Q$7) | F51: the base for the crew shares
B52: Driver share | D52: =Calc!$Q$10 | E52: =IF(Calc!$Q$7=0,"",D52/Calc!$Q$7) | F52: driver share of net fee
B53: Helper share | D53: =Calc!$Q$11 | E53: =IF(Calc!$Q$7=0,"",D53/Calc!$Q$7) | F53: helper share of net fee
B54: Driver allowance | D54: =Calc!$Q$12 | E54: =IF(Calc!$Q$7=0,"",D54/Calc!$Q$7) | F54: cash given per trip
B55: Reimbursable expenses | D55: =Calc!$Q$13 | E55: =IF(Calc!$Q$7=0,"",D55/Calc!$Q$7) | F55: driver receipts to pay back
B56: Gross profit | D56: =Calc!$Q$14 | E56: =IF(Calc!$Q$7=0,"",D56/Calc!$Q$7) | F56: after crew and reimbursables
B57: Fuel | D57: =Calc!$Q$15 | E57: =IF(Calc!$Q$7=0,"",D57/Calc!$Q$7) | F57: diesel logged per trip
B58: Toll & parking | D58: =Calc!$Q$16 | E58: =IF(Calc!$Q$7=0,"",D58/Calc!$Q$7) | F58: expressway + parking
B59: Other trip costs | D59: =Calc!$Q$17 | E59: =IF(Calc!$Q$7=0,"",D59/Calc!$Q$7) | F59: weighing, grease, tips
B60: Total trip cost | D60: =Calc!$Q$18 | E60: =IF(Calc!$Q$7=0,"",D60/Calc!$Q$7)
B61: Trip net profit | D61: =Calc!$Q$19 | E61: =IF(Calc!$Q$7=0,"",D61/Calc!$Q$7) | F61: before truck running costs
B62: Vehicle running costs (repairs, tires…) | D62: =Calc!$Q$20 | E62: =IF(Calc!$Q$7=0,"",D62/Calc!$Q$7) | F62: repairs, tires, insurance, LTO, wash
B63: Overhead (rent, office, salaries…) | D63: =Calc!$Q$21 | E63: =IF(Calc!$Q$7=0,"",D63/Calc!$Q$7) | F63: rent, office salary, utilities, fees
B64: Operating profit | D64: =Calc!$Q$22 | E64: =IF(Calc!$Q$7=0,"",D64/Calc!$Q$7) | F64: the operating result
B65: Loan amortisation paid | D65: =Calc!$Q$23 | E65: =IF(Calc!$Q$7=0,"",D65/Calc!$Q$7) | F65: principal + interest to all lenders
B66: Cash profit after loans | D66: =Calc!$Q$24 | E66: =IF(Calc!$Q$7=0,"",D66/Calc!$Q$7) | F66: money actually left with you
B67: Margin on hauling fee | D67: =Calc!$Q$25 | F67: cash profit ÷ gross fee
B68: Memo: advances & payouts (not a cost) | D68: =Calc!$Q$26 | E68: =IF(Calc!$Q$7=0,"",D68/Calc!$Q$7) | F68: advances are a transfer, not a cost
B70: TRUCK PERFORMANCE · selected month | H70: LOAN BOOK · all lenders, self-updating
B71: TRUCK | C71: TRIPS | D71: TONS | E71: GROSS FEE | F71: TRIP PROFIT | G71: MARGIN | H71: LENDER · TRUCK | J71: AMORT. | K71: BALANCE | L71: MONTHS LEFT | M71: PAID %
B72: =Calc!$Q$32 | C72: =Calc!$R$32 | D72: =Calc!$S$32 | E72: =Calc!$T$32 | F72: =Calc!$U$32 | G72: =Calc!$V$32 | H72: =IF(Setup!$A133="","",Setup!$A133&" · "&Setup!$B133) | J72: =Setup!$E133 | K72: =Setup!$K133 | L72: =Setup!$J133 | M72: =Setup!$M133
B73: =Calc!$Q$33 | C73: =Calc!$R$33 | D73: =Calc!$S$33 | E73: =Calc!$T$33 | F73: =Calc!$U$33 | G73: =Calc!$V$33 | H73: =IF(Setup!$A134="","",Setup!$A134&" · "&Setup!$B134) | J73: =Setup!$E134 | K73: =Setup!$K134 | L73: =Setup!$J134 | M73: =Setup!$M134
B74: =Calc!$Q$34 | C74: =Calc!$R$34 | D74: =Calc!$S$34 | E74: =Calc!$T$34 | F74: =Calc!$U$34 | G74: =Calc!$V$34 | H74: =IF(Setup!$A135="","",Setup!$A135&" · "&Setup!$B135) | J74: =Setup!$E135 | K74: =Setup!$K135 | L74: =Setup!$J135 | M74: =Setup!$M135
B75: =Calc!$Q$35 | C75: =Calc!$R$35 | D75: =Calc!$S$35 | E75: =Calc!$T$35 | F75: =Calc!$U$35 | G75: =Calc!$V$35 | H75: =IF(Setup!$A136="","",Setup!$A136&" · "&Setup!$B136) | J75: =Setup!$E136 | K75: =Setup!$K136 | L75: =Setup!$J136 | M75: =Setup!$M136
B76: =Calc!$Q$36 | C76: =Calc!$R$36 | D76: =Calc!$S$36 | E76: =Calc!$T$36 | F76: =Calc!$U$36 | G76: =Calc!$V$36 | H76: =IF(Setup!$A137="","",Setup!$A137&" · "&Setup!$B137) | J76: =Setup!$E137 | K76: =Setup!$K137 | L76: =Setup!$J137 | M76: =Setup!$M137
B77: =Calc!$Q$37 | C77: =Calc!$R$37 | D77: =Calc!$S$37 | E77: =Calc!$T$37 | F77: =Calc!$U$37 | G77: =Calc!$V$37 | H77: =IF(Setup!$A138="","",Setup!$A138&" · "&Setup!$B138) | J77: =Setup!$E138 | K77: =Setup!$K138 | L77: =Setup!$J138 | M77: =Setup!$M138
B78: =Calc!$Q$38 | C78: =Calc!$R$38 | D78: =Calc!$S$38 | E78: =Calc!$T$38 | F78: =Calc!$U$38 | G78: =Calc!$V$38 | H78: TOTAL | J78: =SUM(J72:J77) | K78: =SUM(K72:K77) | L78: =SUM(L72:L77) | M78: =IF(SUM(Setup!$C$133:$C$138)=0,0,1-K78/SUM(Setup!$C$133:$C$138))
B79: =Calc!$Q$39 | C79: =Calc!$R$39 | D79: =Calc!$S$39 | E79: =Calc!$T$39 | F79: =Calc!$U$39 | G79: =Calc!$V$39
B80: =Calc!$Q$40 | C80: =Calc!$R$40 | D80: =Calc!$S$40 | E80: =Calc!$T$40 | F80: =Calc!$U$40 | G80: =Calc!$V$40
B81: =Calc!$Q$41 | C81: =Calc!$R$41 | D81: =Calc!$S$41 | E81: =Calc!$T$41 | F81: =Calc!$U$41 | G81: =Calc!$V$41
B82: TOTAL | C82: =SUM(C72:C81) | D82: =SUM(D72:D81) | E82: =SUM(E72:E81) | F82: =SUM(F72:F81) | G82: =SUM(G72:G81)
B84: TOP DESTINATIONS · selected month | H84: WHERE THE MONEY WENT · booked expenses
B85: DESTINATION | C85: TRIPS | D85: TONS | E85: GROSS FEE | F85: TRIP PROFIT | G85: MARGIN | H85: COST GROUP | K85: AMOUNT | L85: SHARE | M85: COUNTED IN PROFIT?
B86: =Calc!$J$51 | C86: =IF(Calc!$J$51="","",Calc!$K$51) | D86: =IF(Calc!$J$51="","",Calc!$L$51) | E86: =IF(Calc!$J$51="","",Calc!$M$51) | F86: =IF(Calc!$J$51="","",Calc!$N$51) | G86: =IF(Calc!$J$51="","",Calc!$O$51) | H86: Vehicle | K86: =Calc!$B$91 | L86: =IF(Calc!$B$97=0,"",K86/Calc!$B$97) | M86: yes — running cost
B87: =Calc!$J$52 | C87: =IF(Calc!$J$52="","",Calc!$K$52) | D87: =IF(Calc!$J$52="","",Calc!$L$52) | E87: =IF(Calc!$J$52="","",Calc!$M$52) | F87: =IF(Calc!$J$52="","",Calc!$N$52) | G87: =IF(Calc!$J$52="","",Calc!$O$52) | H87: Financing | K87: =Calc!$B$92 | L87: =IF(Calc!$B$97=0,"",K87/Calc!$B$97) | M87: yes — after operating profit
B88: =Calc!$J$53 | C88: =IF(Calc!$J$53="","",Calc!$K$53) | D88: =IF(Calc!$J$53="","",Calc!$L$53) | E88: =IF(Calc!$J$53="","",Calc!$M$53) | F88: =IF(Calc!$J$53="","",Calc!$N$53) | G88: =IF(Calc!$J$53="","",Calc!$O$53) | H88: Transfer | K88: =Calc!$B$93 | L88: =IF(Calc!$B$97=0,"",K88/Calc!$B$97) | M88: no — advances
B89: =Calc!$J$54 | C89: =IF(Calc!$J$54="","",Calc!$K$54) | D89: =IF(Calc!$J$54="","",Calc!$L$54) | E89: =IF(Calc!$J$54="","",Calc!$M$54) | F89: =IF(Calc!$J$54="","",Calc!$N$54) | G89: =IF(Calc!$J$54="","",Calc!$O$54) | H89: Overhead | K89: =Calc!$B$94 | L89: =IF(Calc!$B$97=0,"",K89/Calc!$B$97) | M89: yes — overhead
B90: =Calc!$J$55 | C90: =IF(Calc!$J$55="","",Calc!$K$55) | D90: =IF(Calc!$J$55="","",Calc!$L$55) | E90: =IF(Calc!$J$55="","",Calc!$M$55) | F90: =IF(Calc!$J$55="","",Calc!$N$55) | G90: =IF(Calc!$J$55="","",Calc!$O$55) | H90: Other | K90: =Calc!$B$95 | L90: =IF(Calc!$B$97=0,"",K90/Calc!$B$97) | M90: no — owner / capital
B91: =Calc!$J$56 | C91: =IF(Calc!$J$56="","",Calc!$K$56) | D91: =IF(Calc!$J$56="","",Calc!$L$56) | E91: =IF(Calc!$J$56="","",Calc!$M$56) | F91: =IF(Calc!$J$56="","",Calc!$N$56) | G91: =IF(Calc!$J$56="","",Calc!$O$56) | H91: TOTAL BOOKED | K91: =Calc!$B$97 | L91: 1
B92: =Calc!$J$57 | C92: =IF(Calc!$J$57="","",Calc!$K$57) | D92: =IF(Calc!$J$57="","",Calc!$L$57) | E92: =IF(Calc!$J$57="","",Calc!$M$57) | F92: =IF(Calc!$J$57="","",Calc!$N$57) | G92: =IF(Calc!$J$57="","",Calc!$O$57) | H92: Only Vehicle / Overhead / Financing reach the P&L. Advances, payouts, owner's draw and asset buys are excluded.
B93: =Calc!$J$58 | C93: =IF(Calc!$J$58="","",Calc!$K$58) | D93: =IF(Calc!$J$58="","",Calc!$L$58) | E93: =IF(Calc!$J$58="","",Calc!$M$58) | F93: =IF(Calc!$J$58="","",Calc!$N$58) | G93: =IF(Calc!$J$58="","",Calc!$O$58)
B94: =Calc!$J$59 | C94: =IF(Calc!$J$59="","",Calc!$K$59) | D94: =IF(Calc!$J$59="","",Calc!$L$59) | E94: =IF(Calc!$J$59="","",Calc!$M$59) | F94: =IF(Calc!$J$59="","",Calc!$N$59) | G94: =IF(Calc!$J$59="","",Calc!$O$59)
B95: =Calc!$J$60 | C95: =IF(Calc!$J$60="","",Calc!$K$60) | D95: =IF(Calc!$J$60="","",Calc!$L$60) | E95: =IF(Calc!$J$60="","",Calc!$M$60) | F95: =IF(Calc!$J$60="","",Calc!$N$60) | G95: =IF(Calc!$J$60="","",Calc!$O$60)
B96: Full list (20 destinations) is on the Calc sheet — add new lanes in Setup §8.
B99: CREW SETTLEMENT · selected month (auto — mirrors the Payroll sheet)
B100: CREW NAME | C100: ROLE | D100: TRIPS | E100: GROSS FEE HANDLED | F100: SHARE | G100: ALLOWANCE + REIMB. | H100: CASH ADVANCE | I100: PAYOUT RELEASED | J100: BALANCE | K100: STATUS
B101: =Calc!$A$75 | C101: =Calc!$B$75 | D101: =IF(Calc!$A$75="","",Calc!$C$75) | E101: =IF(Calc!$A$75="","",Calc!$D$75) | F101: =IF(Calc!$A$75="","",Calc!$E$75) | G101: =IF(Calc!$A$75="","",Calc!$F$75+Calc!$G$75) | H101: =IF(Calc!$A$75="","",Calc!$H$75) | I101: =IF(Calc!$A$75="","",Calc!$I$75) | J101: =IF(Calc!$A$75="","",Calc!$J$75) | K101: =IF(B101="","",IF(AND(Calc!$E$75=0,Calc!$H$75=0,Calc!$I$75=0),"",IF(J101>0.5,"TO PAY",IF(J101<-0.5,"OWES ADVANCE","SETTLED"))))
B102: =Calc!$A$76 | C102: =Calc!$B$76 | D102: =IF(Calc!$A$76="","",Calc!$C$76) | E102: =IF(Calc!$A$76="","",Calc!$D$76) | F102: =IF(Calc!$A$76="","",Calc!$E$76) | G102: =IF(Calc!$A$76="","",Calc!$F$76+Calc!$G$76) | H102: =IF(Calc!$A$76="","",Calc!$H$76) | I102: =IF(Calc!$A$76="","",Calc!$I$76) | J102: =IF(Calc!$A$76="","",Calc!$J$76) | K102: =IF(B102="","",IF(AND(Calc!$E$76=0,Calc!$H$76=0,Calc!$I$76=0),"",IF(J102>0.5,"TO PAY",IF(J102<-0.5,"OWES ADVANCE","SETTLED"))))
B103: =Calc!$A$77 | C103: =Calc!$B$77 | D103: =IF(Calc!$A$77="","",Calc!$C$77) | E103: =IF(Calc!$A$77="","",Calc!$D$77) | F103: =IF(Calc!$A$77="","",Calc!$E$77) | G103: =IF(Calc!$A$77="","",Calc!$F$77+Calc!$G$77) | H103: =IF(Calc!$A$77="","",Calc!$H$77) | I103: =IF(Calc!$A$77="","",Calc!$I$77) | J103: =IF(Calc!$A$77="","",Calc!$J$77) | K103: =IF(B103="","",IF(AND(Calc!$E$77=0,Calc!$H$77=0,Calc!$I$77=0),"",IF(J103>0.5,"TO PAY",IF(J103<-0.5,"OWES ADVANCE","SETTLED"))))
B104: =Calc!$A$78 | C104: =Calc!$B$78 | D104: =IF(Calc!$A$78="","",Calc!$C$78) | E104: =IF(Calc!$A$78="","",Calc!$D$78) | F104: =IF(Calc!$A$78="","",Calc!$E$78) | G104: =IF(Calc!$A$78="","",Calc!$F$78+Calc!$G$78) | H104: =IF(Calc!$A$78="","",Calc!$H$78) | I104: =IF(Calc!$A$78="","",Calc!$I$78) | J104: =IF(Calc!$A$78="","",Calc!$J$78) | K104: =IF(B104="","",IF(AND(Calc!$E$78=0,Calc!$H$78=0,Calc!$I$78=0),"",IF(J104>0.5,"TO PAY",IF(J104<-0.5,"OWES ADVANCE","SETTLED"))))
B105: =Calc!$A$79 | C105: =Calc!$B$79 | D105: =IF(Calc!$A$79="","",Calc!$C$79) | E105: =IF(Calc!$A$79="","",Calc!$D$79) | F105: =IF(Calc!$A$79="","",Calc!$E$79) | G105: =IF(Calc!$A$79="","",Calc!$F$79+Calc!$G$79) | H105: =IF(Calc!$A$79="","",Calc!$H$79) | I105: =IF(Calc!$A$79="","",Calc!$I$79) | J105: =IF(Calc!$A$79="","",Calc!$J$79) | K105: =IF(B105="","",IF(AND(Calc!$E$79=0,Calc!$H$79=0,Calc!$I$79=0),"",IF(J105>0.5,"TO PAY",IF(J105<-0.5,"OWES ADVANCE","SETTLED"))))
B106: =Calc!$A$80 | C106: =Calc!$B$80 | D106: =IF(Calc!$A$80="","",Calc!$C$80) | E106: =IF(Calc!$A$80="","",Calc!$D$80) | F106: =IF(Calc!$A$80="","",Calc!$E$80) | G106: =IF(Calc!$A$80="","",Calc!$F$80+Calc!$G$80) | H106: =IF(Calc!$A$80="","",Calc!$H$80) | I106: =IF(Calc!$A$80="","",Calc!$I$80) | J106: =IF(Calc!$A$80="","",Calc!$J$80) | K106: =IF(B106="","",IF(AND(Calc!$E$80=0,Calc!$H$80=0,Calc!$I$80=0),"",IF(J106>0.5,"TO PAY",IF(J106<-0.5,"OWES ADVANCE","SETTLED"))))
B107: =Calc!$A$81 | C107: =Calc!$B$81 | D107: =IF(Calc!$A$81="","",Calc!$C$81) | E107: =IF(Calc!$A$81="","",Calc!$D$81) | F107: =IF(Calc!$A$81="","",Calc!$E$81) | G107: =IF(Calc!$A$81="","",Calc!$F$81+Calc!$G$81) | H107: =IF(Calc!$A$81="","",Calc!$H$81) | I107: =IF(Calc!$A$81="","",Calc!$I$81) | J107: =IF(Calc!$A$81="","",Calc!$J$81) | K107: =IF(B107="","",IF(AND(Calc!$E$81=0,Calc!$H$81=0,Calc!$I$81=0),"",IF(J107>0.5,"TO PAY",IF(J107<-0.5,"OWES ADVANCE","SETTLED"))))
B108: =Calc!$A$82 | C108: =Calc!$B$82 | D108: =IF(Calc!$A$82="","",Calc!$C$82) | E108: =IF(Calc!$A$82="","",Calc!$D$82) | F108: =IF(Calc!$A$82="","",Calc!$E$82) | G108: =IF(Calc!$A$82="","",Calc!$F$82+Calc!$G$82) | H108: =IF(Calc!$A$82="","",Calc!$H$82) | I108: =IF(Calc!$A$82="","",Calc!$I$82) | J108: =IF(Calc!$A$82="","",Calc!$J$82) | K108: =IF(B108="","",IF(AND(Calc!$E$82=0,Calc!$H$82=0,Calc!$I$82=0),"",IF(J108>0.5,"TO PAY",IF(J108<-0.5,"OWES ADVANCE","SETTLED"))))
B109: =Calc!$A$83 | C109: =Calc!$B$83 | D109: =IF(Calc!$A$83="","",Calc!$C$83) | E109: =IF(Calc!$A$83="","",Calc!$D$83) | F109: =IF(Calc!$A$83="","",Calc!$E$83) | G109: =IF(Calc!$A$83="","",Calc!$F$83+Calc!$G$83) | H109: =IF(Calc!$A$83="","",Calc!$H$83) | I109: =IF(Calc!$A$83="","",Calc!$I$83) | J109: =IF(Calc!$A$83="","",Calc!$J$83) | K109: =IF(B109="","",IF(AND(Calc!$E$83=0,Calc!$H$83=0,Calc!$I$83=0),"",IF(J109>0.5,"TO PAY",IF(J109<-0.5,"OWES ADVANCE","SETTLED"))))
B110: =Calc!$A$84 | C110: =Calc!$B$84 | D110: =IF(Calc!$A$84="","",Calc!$C$84) | E110: =IF(Calc!$A$84="","",Calc!$D$84) | F110: =IF(Calc!$A$84="","",Calc!$E$84) | G110: =IF(Calc!$A$84="","",Calc!$F$84+Calc!$G$84) | H110: =IF(Calc!$A$84="","",Calc!$H$84) | I110: =IF(Calc!$A$84="","",Calc!$I$84) | J110: =IF(Calc!$A$84="","",Calc!$J$84) | K110: =IF(B110="","",IF(AND(Calc!$E$84=0,Calc!$H$84=0,Calc!$I$84=0),"",IF(J110>0.5,"TO PAY",IF(J110<-0.5,"OWES ADVANCE","SETTLED"))))
B111: =Calc!$A$85 | C111: =Calc!$B$85 | D111: =IF(Calc!$A$85="","",Calc!$C$85) | E111: =IF(Calc!$A$85="","",Calc!$D$85) | F111: =IF(Calc!$A$85="","",Calc!$E$85) | G111: =IF(Calc!$A$85="","",Calc!$F$85+Calc!$G$85) | H111: =IF(Calc!$A$85="","",Calc!$H$85) | I111: =IF(Calc!$A$85="","",Calc!$I$85) | J111: =IF(Calc!$A$85="","",Calc!$J$85) | K111: =IF(B111="","",IF(AND(Calc!$E$85=0,Calc!$H$85=0,Calc!$I$85=0),"",IF(J111>0.5,"TO PAY",IF(J111<-0.5,"OWES ADVANCE","SETTLED"))))
B112: =Calc!$A$86 | C112: =Calc!$B$86 | D112: =IF(Calc!$A$86="","",Calc!$C$86) | E112: =IF(Calc!$A$86="","",Calc!$D$86) | F112: =IF(Calc!$A$86="","",Calc!$E$86) | G112: =IF(Calc!$A$86="","",Calc!$F$86+Calc!$G$86) | H112: =IF(Calc!$A$86="","",Calc!$H$86) | I112: =IF(Calc!$A$86="","",Calc!$I$86) | J112: =IF(Calc!$A$86="","",Calc!$J$86) | K112: =IF(B112="","",IF(AND(Calc!$E$86=0,Calc!$H$86=0,Calc!$I$86=0),"",IF(J112>0.5,"TO PAY",IF(J112<-0.5,"OWES ADVANCE","SETTLED"))))
B113: TOTAL | D113: =SUM(D101:D112) | E113: =SUM(E101:E112) | F113: =SUM(F101:F112) | G113: =SUM(G101:G112) | H113: =SUM(H101:H112) | I113: =SUM(I101:I112) | J113: =SUM(J101:J112)
B115: Every number above is a live formula. Nothing on this page is typed by hand — only the two filters at the top.

Sheet Trips
A1: 🚚 TRIPS — one row per delivery (this is the only sheet you fill in daily)
A2: Type only in the WHITE columns. Grey columns calculate themselves. Leave the fuel surcharge blank to use the 18% default — leave allowance blank to use the default.
A3: ALL-TIME TOTALS → | B3: =COUNT(5:1004)&" trips logged" | H3: =SUM(H5:H1004) | K3: =SUM(K5:K1004) | L3: =SUM(L5:L1004) | M3: =SUM(M5:M1004) | N3: =SUM(N5:N1004) | O3: =SUM(O5:O1004) | P3: =SUM(P5:P1004) | Q3: =SUM(Q5:Q1004) | R3: =SUM(R5:R1004) | ... V3: =SUM(V5:V1004)
A4: DATE | B4: INVOICE / DR NO. | C4: TRUCK | D4: DRIVER | E4: HELPER | F4: SOURCE | G4: DESTINATION | H4: TONS | I4: RATE / TON | J4: FUEL SURCH. % | K4: GROSS FEE | L4: 2% TAX | M4: NET FEE | N4: DRIVER PAY | O4: HELPER PAY | P4: ALLOWANCE | Q4: REIMBURSABLE | R4: FUEL COST | S4: TOLL + PARKING | T4: OTHER TRIP COST | U4: DIRECT COST | V4: TRIP NET PROFIT | W4: BILLING | X4: REMARKS
A5: 46235 | B5: DR-1001 | C5: TRUCK 1 | D5: R. Dela Cruz | E5: J. Santos | F5: BATAAN | G5: TARLAC | H5: 17 | I5: =IF($G5="","",IF($F5="",IFERROR(INDEX(Setup!$C$21:$C$60,MATCH("|"&UPPER(TRIM($G5)),Setup!$Q$21:$Q$60,0)),"NO RATE"),IFERROR(INDEX(Setup!$C$21:$C$60,MATCH(UPPER(TRIM($F5))&"|"&UPPER(TRIM($G5)),Setup!$P$21:$P$60,0)),IFERROR(INDEX(Setup!$C$21:$C$60,MATCH(UPPER(TRIM($G5))&"|"&UPPER(TRIM($F5)),Setup!$P$21:$P$60,0)),"NO RATE")))) | K5: =IF(OR($G5="",$H5="",NOT(ISNUMBER($I5))),"",ROUND($H5*$I5*(1+IF($J5="",Setup!$B$16,$J5)),2)) | L5: =IF($K5="","",ROUND($K5*Setup!$B$13,2)) | M5: =IF($K5="","",$K5-$L5) | N5: =IF(OR($M5="",$D5=""),"",ROUND($M5*IFERROR(IF(VLOOKUP($D5,Setup!$A$76:$C$87,3,FALSE)="",Setup!$B$14,VLOOKUP($D5,Setup!$A$76:$C$87,3,FALSE)),Setup!$B$14),2)) | O5: =IF(OR($M5="",$E5=""),"",ROUND($M5*IFERROR(IF(VLOOKUP($E5,Setup!$A$76:$C$87,3,FALSE)="",Setup!$B$15,VLOOKUP($E5,Setup!$A$76:$C$87,3,FALSE)),Setup!$B$15),2)) | P5: 500 | Q5: 450 | R5: 5600 | S5: 620 | T5: 0 | U5: =IF($K5="","",SUM($R5:$T5)) | V5: =IF($K5="","",$M5-(N($N5)+N($O5)+IF($P5="",Setup!$B$17,$P5)+N($Q5))-N($U5)) | W5: Paid | Z5: =IF($A5="","",DATE(YEAR($A5),MONTH($A5),1))
A6: 46237 | B6: DR-1002 | C6: TRUCK 1 | D6: M. Reyes | E6: A. Bautista | F6: BATAAN | G6: BMPP | H6: 20 | I6: =IF($G6="","",IF($F6="",IFERROR(INDEX(Setup!$C$21:$C$60,MATCH("|"&UPPER(TRIM($G6)),Setup!$Q$21:$Q$60,0)),"NO RATE"),IFERROR(INDEX(Setup!$C$21:$C$60,MATCH(UPPER(TRIM($F6))&"|"&UPPER(TRIM($G6)),Setup!$P$21:$P$60,0)),IFERROR(INDEX(Setup!$C$21:$C$60,MATCH(UPPER(TRIM($G6))&"|"&UPPER(TRIM($F6)),Setup!$P$21:$P$60,0)),"NO RATE")))) | K6: =IF(OR($G6="",$H6="",NOT(ISNUMBER($I6))),"",ROUND($H6*$I6*(1+IF($J6="",Setup!$B$16,$J6)),2)) | L6: =IF($K6="","",ROUND($K6*Setup!$B$13,2)) | M6: =IF($K6="","",$K6-$L6) | N6: =IF(OR($M6="",$D6=""),"",ROUND($M6*IFERROR(IF(VLOOKUP($D6,Setup!$A$76:$C$87,3,FALSE)="",Setup!$B$14,VLOOKUP($D6,Setup!$A$76:$C$87,3,FALSE)),Setup!$B$14),2)) | O6: =IF(OR($M6="",$E6=""),"",ROUND($M6*IFERROR(IF(VLOOKUP($E6,Setup!$A$76:$C$87,3,FALSE)="",Setup!$B$15,VLOOKUP($E6,Setup!$A$76:$C$87,3,FALSE)),Setup!$B$15),2)) | P6: 500 | Q6: 0 | R6: 8300 | S6: 560 | T6: 0 | U6: =IF($K6="","",SUM($R6:$T6)) | V6: =IF($K6="","",$M6-(N($N6)+N($O6)+IF($P6="",Setup!$B$17,$P6)+N($Q6))-N($U6)) | W6: Paid | Z6: =IF($A6="","",DATE(YEAR($A6),MONTH($A6),1))
A7: 46239 | B7: DR-1003 | C7: TRUCK 1 | D7: R. Dela Cruz | E7: J. Santos | F7: ORION | G7: BMPP | H7: 23 | I7: =IF($G7="","",IF($F7="",IFERROR(INDEX(Setup!$C$21:$C$60,MATCH("|"&UPPER(TRIM($G7)),Setup!$Q$21:$Q$60,0)),"NO RATE"),IFERROR(INDEX(Setup!$C$21:$C$60,MATCH(UPPER(TRIM($F7))&"|"&UPPER(TRIM($G7)),Setup!$P$21:$P$60,0)),IFERROR(INDEX(Setup!$C$21:$C$60,MATCH(UPPER(TRIM($G7))&"|"&UPPER(TRIM($F7)),Setup!$P$21:$P$60,0)),"NO RATE")))) | K7: =IF(OR($G7="",$H7="",NOT(ISNUMBER($I7))),"",ROUND($H7*$I7*(1+IF($J7="",Setup!$B$16,$J7)),2)) | L7: =IF($K7="","",ROUND($K7*Setup!$B$13,2)) | M7: =IF($K7="","",$K7-$L7) | N7: =IF(OR($M7="",$D7=""),"",ROUND($M7*IFERROR(IF(VLOOKUP($D7,Setup!$A$76:$C$87,3,FALSE)="",Setup!$B$14,VLOOKUP($D7,Setup!$A$76:$C$87,3,FALSE)),Setup!$B$14),2)) | O7: =IF(OR($M7="",$E7=""),"",ROUND($M7*IFERROR(IF(VLOOKUP($E7,Setup!$A$76:$C$87,3,FALSE)="",Setup!$B$15,VLOOKUP($E7,Setup!$A$76:$C$87,3,FALSE)),Setup!$B$15),2)) | P7: 500 | Q7: 0 | R7: 9800 | S7: 540 | T7: 0 | U7: =IF($K7="","",SUM($R7:$T7)) | V7: =IF($K7="","",$M7-(N($N7)+N($O7)+IF($P7="",Setup!$B$17,$P7)+N($Q7))-N($U7)) | W7: Paid | Z7: =IF($A7="","",DATE(YEAR($A7),MONTH($A7),1))
A8: 46241 | B8: DR-1004 | C8: TRUCK 1 | D8: M. Reyes | E8: A. Bautista | F8: MABINI, BATANGAS | G8: BMPP | H8: 19 | I8: =IF($G8="","",IF($F8="",IFERROR(INDEX(Setup!$C$21:$C$60,MATCH("|"&UPPER(TRIM($G8)),Setup!$Q$21:$Q$60,0)),"NO RATE"),IFERROR(INDEX(Setup!$C$21:$C$60,MATCH(UPPER(TRIM($F8))&"|"&UPPER(TRIM($G8)),Setup!$P$21:$P$60,0)),IFERROR(INDEX(Setup!$C$21:$C$60,MATCH(UPPER(TRIM($G8))&"|"&UPPER(TRIM($F8)),Setup!$P$21:$P$60,0)),"NO RATE")))) | K8: =IF(OR($G8="",$H8="",NOT(ISNUMBER($I8))),"",ROUND($H8*$I8*(1+IF($J8="",Setup!$B$16,$J8)),2)) | L8: =IF($K8="","",ROUND($K8*Setup!$B$13,2)) | M8: =IF($K8="","",$K8-$L8) | N8: =IF(OR($M8="",$D8=""),"",ROUND($M8*IFERROR(IF(VLOOKUP($D8,Setup!$A$76:$C$87,3,FALSE)="",Setup!$B$14,VLOOKUP($D8,Setup!$A$76:$C$87,3,FALSE)),Setup!$B$14),2)) | O8: =IF(OR($M8="",$E8=""),"",ROUND($M8*IFERROR(IF(VLOOKUP($E8,Setup!$A$76:$C$87,3,FALSE)="",Setup!$B$15,VLOOKUP($E8,Setup!$A$76:$C$87,3,FALSE)),Setup!$B$15),2)) | P8: 500 | Q8: 0 | R8: 11100 | S8: 980 | T8: 0 | U8: =IF($K8="","",SUM($R8:$T8)) | V8: =IF($K8="","",$M8-(N($N8)+N($O8)+IF($P8="",Setup!$B$17,$P8)+N($Q8))-N($U8)) | W8: Paid | Z8: =IF($A8="","",DATE(YEAR($A8),MONTH($A8),1))
A9: 46243 | B9: DR-1005 | C9: TRUCK 1 | D9: R. Dela Cruz | E9: J. Santos | F9: BATAAN | G9: ISABELA | H9: 18 | I9: =IF($G9="","",IF($F9="",IFERROR(INDEX(Setup!$C$21:$C$60,MATCH("|"&UPPER(TRIM($G9)),Setup!$Q$21:$Q$60,0)),"NO RATE"),IFERROR(INDEX(Setup!$C$21:$C$60,MATCH(UPPER(TRIM($F9))&"|"&UPPER(TRIM($G9)),Setup!$P$21:$P$60,0)),IFERROR(INDEX(Setup!$C$21:$C$60,MATCH(UPPER(TRIM($G9))&"|"&UPPER(TRIM($F9)),Setup!$P$21:$P$60,0)),"NO RATE")))) | K9: =IF(OR($G9="",$H9="",NOT(ISNUMBER($I9))),"",ROUND($H9*$I9*(1+IF($J9="",Setup!$B$16,$J9)),2)) | L9: =IF($K9="","",ROUND($K9*Setup!$B$13,2)) | M9: =IF($K9="","",$K9-$L9) | N9: =IF(OR($M9="",$D9=""),"",ROUND($M9*IFERROR(IF(VLOOKUP($D9,Setup!$A$76:$C$87,3,FALSE)="",Setup!$B$14,VLOOKUP($D9,Setup!$A$76:$C$87,3,FALSE)),Setup!$B$14),2)) | O9: =IF(OR($M9="",$E9=""),"",ROUND($M9*IFERROR(IF(VLOOKUP($E9,Setup!$A$76:$C$87,3,FALSE)="",Setup!$B$15,VLOOKUP($E9,Setup!$A$76:$C$87,3,FALSE)),Setup!$B$15),2)) | P9: 500 | Q9: 0 | R9: 16500 | S9: 1250 | T9: 0 | U9: =IF($K9="","",SUM($R9:$T9)) | V9: =IF($K9="","",$M9-(N($N9)+N($O9)+IF($P9="",Setup!$B$17,$P9)+N($Q9))-N($U9)) | W9: Paid | X9: long haul — diesel receipt attached | Z9: =IF($A9="","",DATE(YEAR($A9),MONTH($A9),1))
A10: 46245 | B10: DR-1006 | C10: TRUCK 1 | D10: M. Reyes | E10: A. Bautista | F10: ORION | G10: TARLAC | H10: 21 | I10: =IF($G10="","",IF($F10="",IFERROR(INDEX(Setup!$C$21:$C$60,MATCH("|"&UPPER(TRIM($G10)),Setup!$Q$21:$Q$60,0)),"NO RATE"),IFERROR(INDEX(Setup!$C$21:$C$60,MATCH(UPPER(TRIM($F10))&"|"&UPPER(TRIM($G10)),Setup!$P$21:$P$60,0)),IFERROR(INDEX(Setup!$C$21:$C$60,MATCH(UPPER(TRIM($G10))&"|"&UPPER(TRIM($F10)),Setup!$P$21:$P$60,0)),"NO RATE")))) | K10: =IF(OR($G10="",$H10="",NOT(ISNUMBER($I10))),"",ROUND($H10*$I10*(1+IF($J10="",Setup!$B$16,$J10)),2)) | L10: =IF($K10="","",ROUND($K10*Setup!$B$13,2)) | M10: =IF($K10="","",$K10-$L10) | N10: =IF(OR($M10="",$D10=""),"",ROUND($M10*IFERROR(IF(VLOOKUP($D10,Setup!$A$76:$C$87,3,FALSE)="",Setup!$B$14,VLOOKUP($D10,Setup!$A$76:$C$87,3,FALSE)),Setup!$B$14),2)) | O10: =IF(OR($M10="",$E10=""),"",ROUND($M10*IFERROR(IF(VLOOKUP($E10,Setup!$A$76:$C$87,3,FALSE)="",Setup!$B$15,VLOOKUP($E10,Setup!$A$76:$C$87,3,FALSE)),Setup!$B$15),2)) | P10: 500 | Q10: 450 | R10: 7200 | S10: 610 | T10: 0 | U10: =IF($K10="","",SUM($R10:$T10)) | V10: =IF($K10="","",$M10-(N($N10)+N($O10)+IF($P10="",Setup!$B$17,$P10)+N($Q10))-N($U10)) | W10: Paid | Z10: =IF($A10="","",DATE(YEAR($A10),MONTH($A10),1))
A11: 46247 | B11: DR-1007 | C11: TRUCK 1 | D11: R. Dela Cruz | E11: J. Santos | F11: MABINI, BATANGAS | G11: TARLAC | H11: 17 | I11: =IF($G11="","",IF($F11="",IFERROR(INDEX(Setup!$C$21:$C$60,MATCH("|"&UPPER(TRIM($G11)),Setup!$Q$21:$Q$60,0)),"NO RATE"),IFERROR(INDEX(Setup!$C$21:$C$60,MATCH(UPPER(TRIM($F11))&"|"&UPPER(TRIM($G11)),Setup!$P$21:$P$60,0)),IFERROR(INDEX(Setup!$C$21:$C$60,MATCH(UPPER(TRIM($G11))&"|"&UPPER(TRIM($F11)),Setup!$P$21:$P$60,0)),"NO RATE")))) | K11: =IF(OR($G11="",$H11="",NOT(ISNUMBER($I11))),"",ROUND($H11*$I11*(1+IF($J11="",Setup!$B$16,$J11)),2)) | L11: =IF($K11="","",ROUND($K11*Setup!$B$13,2)) | M11: =IF($K11="","",$K11-$L11) | N11: =IF(OR($M11="",$D11=""),"",ROUND($M11*IFERROR(IF(VLOOKUP($D11,Setup!$A$76:$C$87,3,FALSE)="",Setup!$B$14,VLOOKUP($D11,Setup!$A$76:$C$87,3,FALSE)),Setup!$B$14),2)) | O11: =IF(OR($M11="",$E11=""),"",ROUND($M11*IFERROR(IF(VLOOKUP($E11,Setup!$A$76:$C$87,3,FALSE)="",Setup!$B$15,VLOOKUP($E11,Setup!$A$76:$C$87,3,FALSE)),Setup!$B$15),2)) | P11: 500 | Q11: 0 | R11: 8900 | S11: 900 | T11: 0 | U11: =IF($K11="","",SUM($R11:$T11)) | V11: =IF($K11="","",$M11-(N($N11)+N($O11)+IF($P11="",Setup!$B$17,$P11)+N($Q11))-N($U11)) | W11: Paid | Z11: =IF($A11="","",DATE(YEAR($A11),MONTH($A11),1))
A12: 46249 | B12: DR-1008 | C12: TRUCK 1 | D12: M. Reyes | E12: A. Bautista | F12: BATAAN | G12: ARMOR | H12: 20 | I12: =IF($G12="","",IF($F12="",IFERROR(INDEX(Setup!$C$21:$C$60,MATCH("|"&UPPER(TRIM($G12)),Setup!$Q$21:$Q$60,0)),"NO RATE"),IFERROR(INDEX(Setup!$C$21:$C$60,MATCH(UPPER(TRIM($F12))&"|"&UPPER(TRIM($G12)),Setup!$P$21:$P$60,0)),IFERROR(INDEX(Setup!$C$21:$C$60,MATCH(UPPER(TRIM($G12))&"|"&UPPER(TRIM($F12)),Setup!$P$21:$P$60,0)),"NO RATE")))) | K12: =IF(OR($G12="",$H12="",NOT(ISNUMBER($I12))),"",ROUND($H12*$I12*(1+IF($J12="",Setup!$B$16,$J12)),2)) | L12: =IF($K12="","",ROUND($K12*Setup!$B$13,2)) | M12: =IF($K12="","",$K12-$L12) | N12: =IF(OR($M12="",$D12=""),"",ROUND($M12*IFERROR(IF(VLOOKUP($D12,Setup!$A$76:$C$87,3,FALSE)="",Setup!$B$14,VLOOKUP($D12,Setup!$A$76:$C$87,3,FALSE)),Setup!$B$14),2)) | O12: =IF(OR($M12="",$E12=""),"",ROUND($M12*IFERROR(IF(VLOOKUP($E12,Setup!$A$76:$C$87,3,FALSE)="",Setup!$B$15,VLOOKUP($E12,Setup!$A$76:$C$87,3,FALSE)),Setup!$B$15),2)) | P12: 500 | Q12: 0 | R12: 7900 | S12: 520 | T12: 0 | U12: =IF($K12="","",SUM($R12:$T12)) | V12: =IF($K12="","",$M12-(N($N12)+N($O12)+IF($P12="",Setup!$B$17,$P12)+N($Q12))-N($U12)) | W12: Paid | Z12: =IF($A12="","",DATE(YEAR($A12),MONTH($A12),1))
A13: 46251 | B13: DR-1009 | C13: TRUCK 1 | D13: R. Dela Cruz | E13: J. Santos | F13: ORION | G13: BULACAN | H13: 23 | I13: =IF($G13="","",IF($F13="",IFERROR(INDEX(Setup!$C$21:$C$60,MATCH("|"&UPPER(TRIM($G13)),Setup!$Q$21:$Q$60,0)),"NO RATE"),IFERROR(INDEX(Setup!$C$21:$C$60,MATCH(UPPER(TRIM($F13))&"|"&UPPER(TRIM($G13)),Setup!$P$21:$P$60,0)),IFERROR(INDEX(Setup!$C$21:$C$60,MATCH(UPPER(TRIM($G13))&"|"&UPPER(TRIM($F13)),Setup!$P$21:$P$60,0)),"NO RATE")))) | K13: =IF(OR($G13="",$H13="",NOT(ISNUMBER($I13))),"",ROUND($H13*$I13*(1+IF($J13="",Setup!$B$16,$J13)),2)) | L13: =IF($K13="","",ROUND($K13*Setup!$B$13,2)) | M13: =IF($K13="","",$K13-$L13) | N13: =IF(OR($M13="",$D13=""),"",ROUND($M13*IFERROR(IF(VLOOKUP($D13,Setup!$A$76:$C$87,3,FALSE)="",Setup!$B$14,VLOOKUP($D13,Setup!$A$76:$C$87,3,FALSE)),Setup!$B$14),2)) | O13: =IF(OR($M13="",$E13=""),"",ROUND($M13*IFERROR(IF(VLOOKUP($E13,Setup!$A$76:$C$87,3,FALSE)="",Setup!$B$15,VLOOKUP($E13,Setup!$A$76:$C$87,3,FALSE)),Setup!$B$15),2)) | P13: 500 | Q13: 0 | R13: 7700 | S13: 590 | T13: 0 | U13: =IF($K13="","",SUM($R13:$T13)) | V13: =IF($K13="","",$M13-(N($N13)+N($O13)+IF($P13="",Setup!$B$17,$P13)+N($Q13))-N($U13)) | W13: Paid | Z13: =IF($A13="","",DATE(YEAR($A13),MONTH($A13),1))
A14: 46253 | B14: DR-1010 | C14: TRUCK 1 | D14: M. Reyes | E14: A. Bautista | F14: MABINI, BATANGAS | G14: MONCADA | H14: 17 | I14: =IF($G14="","",IF($F14="",IFERROR(INDEX(Setup!$C$21:$C$60,MATCH("|"&UPPER(TRIM($G14)),Setup!$Q$21:$Q$60,0)),"NO RATE"),IFERROR(INDEX(Setup!$C$21:$C$60,MATCH(UPPER(TRIM($F14))&"|"&UPPER(TRIM($G14)),Setup!$P$21:$P$60,0)),IFERROR(INDEX(Setup!$C$21:$C$60,MATCH(UPPER(TRIM($G14))&"|"&UPPER(TRIM($F14)),Setup!$P$21:$P$60,0)),"NO RATE")))) | K14: =IF(OR($G14="",$H14="",NOT(ISNUMBER($I14))),"",ROUND($H14*$I14*(1+IF($J14="",Setup!$B$16,$J14)),2)) | L14: =IF($K14="","",ROUND($K14*Setup!$B$13,2)) | M14: =IF($K14="","",$K14-$L14) | N14: =IF(OR($M14="",$D14=""),"",ROUND($M14*IFERROR(IF(VLOOKUP($D14,Setup!$A$76:$C$87,3,FALSE)="",Setup!$B$14,VLOOKUP($D14,Setup!$A$76:$C$87,3,FALSE)),Setup!$B$14),2)) | O14: =IF(OR($M14="",$E14=""),"",ROUND($M14*IFERROR(IF(VLOOKUP($E14,Setup!$A$76:$C$87,3,FALSE)="",Setup!$B$15,VLOOKUP($E14,Setup!$A$76:$C$87,3,FALSE)),Setup!$B$15),2)) | P14: 500 | Q14: 0 | R14: 6600 | S14: 430 | T14: 0 | U14: =IF($K14="","",SUM($R14:$T14)) | V14: =IF($K14="","",$M14-(N($N14)+N($O14)+IF($P14="",Setup!$B$17,$P14)+N($Q14))-N($U14)) | W14: Paid | X14: helper not available, driver solo | Z14: =IF($A14="","",DATE(YEAR($A14),MONTH($A14),1))
A15: 46255 | B15: DR-1011 | C15: TRUCK 1 | D15: R. Dela Cruz | E15: J. Santos | F15: BATAAN | G15: BULACAN | H15: 20 | I15: =IF($G15="","",IF($F15="",IFERROR(INDEX(Setup!$C$21:$C$60,MATCH("|"&UPPER(TRIM($G15)),Setup!$Q$21:$Q$60,0)),"NO RATE"),IFERROR(INDEX(Setup!$C$21:$C$60,MATCH(UPPER(TRIM($F15))&"|"&UPPER(TRIM($G15)),Setup!$P$21:$P$60,0)),IFERROR(INDEX(Setup!$C$21:$C$60,MATCH(UPPER(TRIM($G15))&"|"&UPPER(TRIM($F15)),Setup!$P$21:$P$60,0)),"NO RATE")))) | K15: =IF(OR($G15="",$H15="",NOT(ISNUMBER($I15))),"",ROUND($H15*$I15*(1+IF($J15="",Setup!$B$16,$J15)),2)) | L15: =IF($K15="","",ROUND($K15*Setup!$B$13,2)) | M15: =IF($K15="","",$K15-$L15) | N15: =IF(OR($M15="",$D15=""),"",ROUND($M15*IFERROR(IF(VLOOKUP($D15,Setup!$A$76:$C$87,3,FALSE)="",Setup!$B$14,VLOOKUP($D15,Setup!$A$76:$C$87,3,FALSE)),Setup!$B$14),2)) | O15: =IF(OR($M15="",$E15=""),"",ROUND($M15*IFERROR(IF(VLOOKUP($E15,Setup!$A$76:$C$87,3,FALSE)="",Setup!$B$15,VLOOKUP($E15,Setup!$A$76:$C$87,3,FALSE)),Setup!$B$15),2)) | P15: 500 | Q15: 450 | R15: 7600 | S15: 480 | T15: 0 | U15: =IF($K15="","",SUM($R15:$T15)) | V15: =IF($K15="","",$M15-(N($N15)+N($O15)+IF($P15="",Setup!$B$17,$P15)+N($Q15))-N($U15)) | W15: Paid | Z15: =IF($A15="","",DATE(YEAR($A15),MONTH($A15),1))
A16: 46257 | B16: DR-1012 | C16: TRUCK 1 | D16: M. Reyes | E16: A. Bautista | F16: ORION | G16: ROSALES | H16: 21 | I16: =IF($G16="","",IF($F16="",IFERROR(INDEX(Setup!$C$21:$C$60,MATCH("|"&UPPER(TRIM($G16)),Setup!$Q$21:$Q$60,0)),"NO RATE"),IFERROR(INDEX(Setup!$C$21:$C$60,MATCH(UPPER(TRIM($F16))&"|"&UPPER(TRIM($G16)),Setup!$P$21:$P$60,0)),IFERROR(INDEX(Setup!$C$21:$C$60,MATCH(UPPER(TRIM($G16))&"|"&UPPER(TRIM($F16)),Setup!$P$21:$P$60,0)),"NO RATE")))) | K16: =IF(OR($G16="",$H16="",NOT(ISNUMBER($I16))),"",ROUND($H16*$I16*(1+IF($J16="",Setup!$B$16,$J16)),2)) | L16: =IF($K16="","",ROUND($K16*Setup!$B$13,2)) | M16: =IF($K16="","",$K16-$L16) | N16: =IF(OR($M16="",$D16=""),"",ROUND($M16*IFERROR(IF(VLOOKUP($D16,Setup!$A$76:$C$87,3,FALSE)="",Setup!$B$14,VLOOKUP($D16,Setup!$A$76:$C$87,3,FALSE)),Setup!$B$14),2)) | O16: =IF(OR($M16="",$E16=""),"",ROUND($M16*IFERROR(IF(VLOOKUP($E16,Setup!$A$76:$C$87,3,FALSE)="",Setup!$B$15,VLOOKUP($E16,Setup!$A$76:$C$87,3,FALSE)),Setup!$B$15),2)) | P16: 500 | Q16: 0 | R16: 7800 | S16: 700 | T16: 0 | U16: =IF($K16="","",SUM($R16:$T16)) | V16: =IF($K16="","",$M16-(N($N16)+N($O16)+IF($P16="",Setup!$B$17,$P16)+N($Q16))-N($U16)) | W16: Paid | Z16: =IF($A16="","",DATE(YEAR($A16),MONTH($A16),1))
A17: 46259 | B17: DR-1013 | C17: TRUCK 1 | D17: R. Dela Cruz | E17: J. Santos | F17: MABINI, BATANGAS | G17: BATAAN | H17: 17 | I17: =IF($G17="","",IF($F17="",IFERROR(INDEX(Setup!$C$21:$C$60,MATCH("|"&UPPER(TRIM($G17)),Setup!$Q$21:$Q$60,0)),"NO RATE"),IFERROR(INDEX(Setup!$C$21:$C$60,MATCH(UPPER(TRIM($F17))&"|"&UPPER(TRIM($G17)),Setup!$P$21:$P$60,0)),IFERROR(INDEX(Setup!$C$21:$C$60,MATCH(UPPER(TRIM($G17))&"|"&UPPER(TRIM($F17)),Setup!$P$21:$P$60,0)),"NO RATE")))) | K17: =IF(OR($G17="",$H17="",NOT(ISNUMBER($I17))),"",ROUND($H17*$I17*(1+IF($J17="",Setup!$B$16,$J17)),2)) | L17: =IF($K17="","",ROUND($K17*Setup!$B$13,2)) | M17: =IF($K17="","",$K17-$L17) | N17: =IF(OR($M17="",$D17=""),"",ROUND($M17*IFERROR(IF(VLOOKUP($D17,Setup!$A$76:$C$87,3,FALSE)="",Setup!$B$14,VLOOKUP($D17,Setup!$A$76:$C$87,3,FALSE)),Setup!$B$14),2)) | O17: =IF(OR($M17="",$E17=""),"",ROUND($M17*IFERROR(IF(VLOOKUP($E17,Setup!$A$76:$C$87,3,FALSE)="",Setup!$B$15,VLOOKUP($E17,Setup!$A$76:$C$87,3,FALSE)),Setup!$B$15),2)) | P17: 500 | Q17: 0 | R17: 10000 | S17: 880 | T17: 0 | U17: =IF($K17="","",SUM($R17:$T17)) | V17: =IF($K17="","",$M17-(N($N17)+N($O17)+IF($P17="",Setup!$B$17,$P17)+N($Q17))-N($U17)) | W17: Paid | Z17: =IF($A17="","",DATE(YEAR($A17),MONTH($A17),1))
A18: 46261 | B18: DR-1014 | C18: TRUCK 1 | D18: M. Reyes | E18: A. Bautista | F18: BATAAN | G18: BMEG BATAAN | H18: 20 | I18: =IF($G18="","",IF($F18="",IFERROR(INDEX(Setup!$C$21:$C$60,MATCH("|"&UPPER(TRIM($G18)),Setup!$Q$21:$Q$60,0)),"NO RATE"),IFERROR(INDEX(Setup!$C$21:$C$60,MATCH(UPPER(TRIM($F18))&"|"&UPPER(TRIM($G18)),Setup!$P$21:$P$60,0)),IFERROR(INDEX(Setup!$C$21:$C$60,MATCH(UPPER(TRIM($G18))&"|"&UPPER(TRIM($F18)),Setup!$P$21:$P$60,0)),"NO RATE")))) | K18: =IF(OR($G18="",$H18="",NOT(ISNUMBER($I18))),"",ROUND($H18*$I18*(1+IF($J18="",Setup!$B$16,$J18)),2)) | L18: =IF($K18="","",ROUND($K18*Setup!$B$13,2)) | M18: =IF($K18="","",$K18-$L18) | N18: =IF(OR($M18="",$D18=""),"",ROUND($M18*IFERROR(IF(VLOOKUP($D18,Setup!$A$76:$C$87,3,FALSE)="",Setup!$B$14,VLOOKUP($D18,Setup!$A$76:$C$87,3,FALSE)),Setup!$B$14),2)) | O18: =IF(OR($M18="",$E18=""),"",ROUND($M18*IFERROR(IF(VLOOKUP($E18,Setup!$A$76:$C$87,3,FALSE)="",Setup!$B$15,VLOOKUP($E18,Setup!$A$76:$C$87,3,FALSE)),Setup!$B$15),2)) | P18: 400 | Q18: 0 | R18: 900 | S18: 120 | T18: 0 | U18: =IF($K18="","",SUM($R18:$T18)) | V18: =IF($K18="","",$M18-(N($N18)+N($O18)+IF($P18="",Setup!$B$17,$P18)+N($Q18))-N($U18)) | W18: Paid | Z18: =IF($A18="","",DATE(YEAR($A18),MONTH($A18),1))
A19: 46266 | B19: DR-1015 | C19: TRUCK 1 | D19: M. Reyes | E19: A. Bautista | F19: BATAAN | G19: TARLAC | H19: 18 | I19: =IF($G19="","",IF($F19="",IFERROR(INDEX(Setup!$C$21:$C$60,MATCH("|"&UPPER(TRIM($G19)),Setup!$Q$21:$Q$60,0)),"NO RATE"),IFERROR(INDEX(Setup!$C$21:$C$60,MATCH(UPPER(TRIM($F19))&"|"&UPPER(TRIM($G19)),Setup!$P$21:$P$60,0)),IFERROR(INDEX(Setup!$C$21:$C$60,MATCH(UPPER(TRIM($G19))&"|"&UPPER(TRIM($F19)),Setup!$P$21:$P$60,0)),"NO RATE")))) | K19: =IF(OR($G19="",$H19="",NOT(ISNUMBER($I19))),"",ROUND($H19*$I19*(1+IF($J19="",Setup!$B$16,$J19)),2)) | L19: =IF($K19="","",ROUND($K19*Setup!$B$13,2)) | M19: =IF($K19="","",$K19-$L19) | N19: =IF(OR($M19="",$D19=""),"",ROUND($M19*IFERROR(IF(VLOOKUP($D19,Setup!$A$76:$C$87,3,FALSE)="",Setup!$B$14,VLOOKUP($D19,Setup!$A$76:$C$87,3,FALSE)),Setup!$B$14),2)) | O19: =IF(OR($M19="",$E19=""),"",ROUND($M19*IFERROR(IF(VLOOKUP($E19,Setup!$A$76:$C$87,3,FALSE)="",Setup!$B$15,VLOOKUP($E19,Setup!$A$76:$C$87,3,FALSE)),Setup!$B$15),2)) | P19: 500 | Q19: 0 | R19: 6400 | S19: 620 | T19: 0 | U19: =IF($K19="","",SUM($R19:$T19)) | V19: =IF($K19="","",$M19-(N($N19)+N($O19)+IF($P19="",Setup!$B$17,$P19)+N($Q19))-N($U19)) | W19: Paid | Z19: =IF($A19="","",DATE(YEAR($A19),MONTH($A19),1))
A20: 46267 | B20: DR-1016 | C20: TRUCK 1 | D20: R. Dela Cruz | E20: J. Santos | F20: BATAAN | G20: BMPP | H20: 21 | I20: =IF($G20="","",IF($F20="",IFERROR(INDEX(Setup!$C$21:$C$60,MATCH("|"&UPPER(TRIM($G20)),Setup!$Q$21:$Q$60,0)),"NO RATE"),IFERROR(INDEX(Setup!$C$21:$C$60,MATCH(UPPER(TRIM($F20))&"|"&UPPER(TRIM($G20)),Setup!$P$21:$P$60,0)),IFERROR(INDEX(Setup!$C$21:$C$60,MATCH(UPPER(TRIM($G20))&"|"&UPPER(TRIM($F20)),Setup!$P$21:$P$60,0)),"NO RATE")))) | K20: =IF(OR($G20="",$H20="",NOT(ISNUMBER($I20))),"",ROUND($H20*$I20*(1+IF($J20="",Setup!$B$16,$J20)),2)) | L20: =IF($K20="","",ROUND($K20*Setup!$B$13,2)) | M20: =IF($K20="","",$K20-$L20) | N20: =IF(OR($M20="",$D20=""),"",ROUND($M20*IFERROR(IF(VLOOKUP($D20,Setup!$A$76:$C$87,3,FALSE)="",Setup!$B$14,VLOOKUP($D20,Setup!$A$76:$C$87,3,FALSE)),Setup!$B$14),2)) | O20: =IF(OR($M20="",$E20=""),"",ROUND($M20*IFERROR(IF(VLOOKUP($E20,Setup!$A$76:$C$87,3,FALSE)="",Setup!$B$15,VLOOKUP($E20,Setup!$A$76:$C$87,3,FALSE)),Setup!$B$15),2)) | P20: 500 | Q20: 0 | R20: 9400 | S20: 560 | T20: 0 | U20: =IF($K20="","",SUM($R20:$T20)) | V20: =IF($K20="","",$M20-(N($N20)+N($O20)+IF($P20="",Setup!$B$17,$P20)+N($Q20))-N($U20)) | W20: Paid | Z20: =IF($A20="","",DATE(YEAR($A20),MONTH($A20),1))
A21: 46269 | B21: DR-1017 | C21: TRUCK 1 | D21: M. Reyes | E21: A. Bautista | F21: ORION | G21: BMPP | H21: 21 | I21: =IF($G21="","",IF($F21="",IFERROR(INDEX(Setup!$C$21:$C$60,MATCH("|"&UPPER(TRIM($G21)),Setup!$Q$21:$Q$60,0)),"NO RATE"),IFERROR(INDEX(Setup!$C$21:$C$60,MATCH(UPPER(TRIM($F21))&"|"&UPPER(TRIM($G21)),Setup!$P$21:$P$60,0)),IFERROR(INDEX(Setup!$C$21:$C$60,MATCH(UPPER(TRIM($G21))&"|"&UPPER(TRIM($F21)),Setup!$P$21:$P$60,0)),"NO RATE")))) | K21: =IF(OR($G21="",$H21="",NOT(ISNUMBER($I21))),"",ROUND($H21*$I21*(1+IF($J21="",Setup!$B$16,$J21)),2)) | L21: =IF($K21="","",ROUND($K21*Setup!$B$13,2)) | M21: =IF($K21="","",$K21-$L21) | N21: =IF(OR($M21="",$D21=""),"",ROUND($M21*IFERROR(IF(VLOOKUP($D21,Setup!$A$76:$C$87,3,FALSE)="",Setup!$B$14,VLOOKUP($D21,Setup!$A$76:$C$87,3,FALSE)),Setup!$B$14),2)) | O21: =IF(OR($M21="",$E21=""),"",ROUND($M21*IFERROR(IF(VLOOKUP($E21,Setup!$A$76:$C$87,3,FALSE)="",Setup!$B$15,VLOOKUP($E21,Setup!$A$76:$C$87,3,FALSE)),Setup!$B$15),2)) | P21: 500 | Q21: 0 | R21: 7600 | S21: 540 | T21: 0 | U21: =IF($K21="","",SUM($R21:$T21)) | V21: =IF($K21="","",$M21-(N($N21)+N($O21)+IF($P21="",Setup!$B$17,$P21)+N($Q21))-N($U21)) | W21: Paid | Z21: =IF($A21="","",DATE(YEAR($A21),MONTH($A21),1))
A22: 46271 | B22: DR-1018 | C22: TRUCK 1 | D22: R. Dela Cruz | E22: J. Santos | F22: MABINI, BATANGAS | G22: BMPP | H22: 20 | I22: =IF($G22="","",IF($F22="",IFERROR(INDEX(Setup!$C$21:$C$60,MATCH("|"&UPPER(TRIM($G22)),Setup!$Q$21:$Q$60,0)),"NO RATE"),IFERROR(INDEX(Setup!$C$21:$C$60,MATCH(UPPER(TRIM($F22))&"|"&UPPER(TRIM($G22)),Setup!$P$21:$P$60,0)),IFERROR(INDEX(Setup!$C$21:$C$60,MATCH(UPPER(TRIM($G22))&"|"&UPPER(TRIM($F22)),Setup!$P$21:$P$60,0)),"NO RATE")))) | K22: =IF(OR($G22="",$H22="",NOT(ISNUMBER($I22))),"",ROUND($H22*$I22*(1+IF($J22="",Setup!$B$16,$J22)),2)) | L22: =IF($K22="","",ROUND($K22*Setup!$B$13,2)) | M22: =IF($K22="","",$K22-$L22) | N22: =IF(OR($M22="",$D22=""),"",ROUND($M22*IFERROR(IF(VLOOKUP($D22,Setup!$A$76:$C$87,3,FALSE)="",Setup!$B$14,VLOOKUP($D22,Setup!$A$76:$C$87,3,FALSE)),Setup!$B$14),2)) | O22: =IF(OR($M22="",$E22=""),"",ROUND($M22*IFERROR(IF(VLOOKUP($E22,Setup!$A$76:$C$87,3,FALSE)="",Setup!$B$15,VLOOKUP($E22,Setup!$A$76:$C$87,3,FALSE)),Setup!$B$15),2)) | P22: 500 | Q22: 0 | R22: 12700 | S22: 980 | T22: 0 | U22: =IF($K22="","",SUM($R22:$T22)) | V22: =IF($K22="","",$M22-(N($N22)+N($O22)+IF($P22="",Setup!$B$17,$P22)+N($Q22))-N($U22)) | W22: Paid | Z22: =IF($A22="","",DATE(YEAR($A22),MONTH($A22),1))
A23: 46273 | B23: DR-1019 | C23: TRUCK 1 | D23: M. Reyes | E23: A. Bautista | F23: BATAAN | G23: ISABELA | H23: 19 | I23: =IF($G23="","",IF($F23="",IFERROR(INDEX(Setup!$C$21:$C$60,MATCH("|"&UPPER(TRIM($G23)),Setup!$Q$21:$Q$60,0)),"NO RATE"),IFERROR(INDEX(Setup!$C$21:$C$60,MATCH(UPPER(TRIM($F23))&"|"&UPPER(TRIM($G23)),Setup!$P$21:$P$60,0)),IFERROR(INDEX(Setup!$C$21:$C$60,MATCH(UPPER(TRIM($G23))&"|"&UPPER(TRIM($F23)),Setup!$P$21:$P$60,0)),"NO RATE")))) | K23: =IF(OR($G23="",$H23="",NOT(ISNUMBER($I23))),"",ROUND($H23*$I23*(1+IF($J23="",Setup!$B$16,$J23)),2)) | L23: =IF($K23="","",ROUND($K23*Setup!$B$13,2)) | M23: =IF($K23="","",$K23-$L23) | N23: =IF(OR($M23="",$D23=""),"",ROUND($M23*IFERROR(IF(VLOOKUP($D23,Setup!$A$76:$C$87,3,FALSE)="",Setup!$B$14,VLOOKUP($D23,Setup!$A$76:$C$87,3,FALSE)),Setup!$B$14),2)) | O23: =IF(OR($M23="",$E23=""),"",ROUND($M23*IFERROR(IF(VLOOKUP($E23,Setup!$A$76:$C$87,3,FALSE)="",Setup!$B$15,VLOOKUP($E23,Setup!$A$76:$C$87,3,FALSE)),Setup!$B$15),2)) | P23: 500 | Q23: 450 | R23: 18800 | S23: 1250 | T23: 0 | U23: =IF($K23="","",SUM($R23:$T23)) | V23: =IF($K23="","",$M23-(N($N23)+N($O23)+IF($P23="",Setup!$B$17,$P23)+N($Q23))-N($U23)) | W23: Paid | X23: long haul — diesel receipt attached | Z23: =IF($A23="","",DATE(YEAR($A23),MONTH($A23),1))
A24: 46274 | B24: DR-1020 | C24: TRUCK 1 | D24: R. Dela Cruz | E24: J. Santos | F24: ORION | G24: TARLAC | H24: 19 | I24: =IF($G24="","",IF($F24="",IFERROR(INDEX(Setup!$C$21:$C$60,MATCH("|"&UPPER(TRIM($G24)),Setup!$Q$21:$Q$60,0)),"NO RATE"),IFERROR(INDEX(Setup!$C$21:$C$60,MATCH(UPPER(TRIM($F24))&"|"&UPPER(TRIM($G24)),Setup!$P$21:$P$60,0)),IFERROR(INDEX(Setup!$C$21:$C$60,MATCH(UPPER(TRIM($G24))&"|"&UPPER(TRIM($F24)),Setup!$P$21:$P$60,0)),"NO RATE")))) | K24: =IF(OR($G24="",$H24="",NOT(ISNUMBER($I24))),"",ROUND($H24*$I24*(1+IF($J24="",Setup!$B$16,$J24)),2)) | L24: =IF($K24="","",ROUND($K24*Setup!$B$13,2)) | M24: =IF($K24="","",$K24-$L24) | N24: =IF(OR($M24="",$D24=""),"",ROUND($M24*IFERROR(IF(VLOOKUP($D24,Setup!$A$76:$C$87,3,FALSE)="",Setup!$B$14,VLOOKUP($D24,Setup!$A$76:$C$87,3,FALSE)),Setup!$B$14),2)) | O24: =IF(OR($M24="",$E24=""),"",ROUND($M24*IFERROR(IF(VLOOKUP($E24,Setup!$A$76:$C$87,3,FALSE)="",Setup!$B$15,VLOOKUP($E24,Setup!$A$76:$C$87,3,FALSE)),Setup!$B$15),2)) | P24: 500 | Q24: 0 | R24: 5600 | S24: 610 | T24: 0 | U24: =IF($K24="","",SUM($R24:$T24)) | V24: =IF($K24="","",$M24-(N($N24)+N($O24)+IF($P24="",Setup!$B$17,$P24)+N($Q24))-N($U24)) | W24: Paid | Z24: =IF($A24="","",DATE(YEAR($A24),MONTH($A24),1))
A25: 46276 | B25: DR-1021 | C25: TRUCK 1 | D25: M. Reyes | E25: A. Bautista | F25: MABINI, BATANGAS | G25: TARLAC | H25: 18 | I25: =IF($G25="","",IF($F25="",IFERROR(INDEX(Setup!$C$21:$C$60,MATCH("|"&UPPER(TRIM($G25)),Setup!$Q$21:$Q$60,0)),"NO RATE"),IFERROR(INDEX(Setup!$C$21:$C$60,MATCH(UPPER(TRIM($F25))&"|"&UPPER(TRIM($G25)),Setup!$P$21:$P$60,0)),IFERROR(INDEX(Setup!$C$21:$C$60,MATCH(UPPER(TRIM($G25))&"|"&UPPER(TRIM($F25)),Setup!$P$21:$P$60,0)),"NO RATE")))) | K25: =IF(OR($G25="",$H25="",NOT(ISNUMBER($I25))),"",ROUND($H25*$I25*(1+IF($J25="",Setup!$B$16,$J25)),2)) | L25: =IF($K25="","",ROUND($K25*Setup!$B$13,2)) | M25: =IF($K25="","",$K25-$L25) | N25: =IF(OR($M25="",$D25=""),"",ROUND($M25*IFERROR(IF(VLOOKUP($D25,Setup!$A$76:$C$87,3,FALSE)="",Setup!$B$14,VLOOKUP($D25,Setup!$A$76:$C$87,3,FALSE)),Setup!$B$14),2)) | O25: =IF(OR($M25="",$E25=""),"",ROUND($M25*IFERROR(IF(VLOOKUP($E25,Setup!$A$76:$C$87,3,FALSE)="",Setup!$B$15,VLOOKUP($E25,Setup!$A$76:$C$87,3,FALSE)),Setup!$B$15),2)) | P25: 500 | Q25: 0 | R25: 10200 | S25: 900 | T25: 0 | U25: =IF($K25="","",SUM($R25:$T25)) | V25: =IF($K25="","",$M25-(N($N25)+N($O25)+IF($P25="",Setup!$B$17,$P25)+N($Q25))-N($U25)) | W25: Paid | Z25: =IF($A25="","",DATE(YEAR($A25),MONTH($A25),1))
A26: 46278 | B26: DR-1022 | C26: TRUCK 1 | D26: R. Dela Cruz | E26: J. Santos | F26: BATAAN | G26: ARMOR | H26: 21 | I26: =IF($G26="","",IF($F26="",IFERROR(INDEX(Setup!$C$21:$C$60,MATCH("|"&UPPER(TRIM($G26)),Setup!$Q$21:$Q$60,0)),"NO RATE"),IFERROR(INDEX(Setup!$C$21:$C$60,MATCH(UPPER(TRIM($F26))&"|"&UPPER(TRIM($G26)),Setup!$P$21:$P$60,0)),IFERROR(INDEX(Setup!$C$21:$C$60,MATCH(UPPER(TRIM($G26))&"|"&UPPER(TRIM($F26)),Setup!$P$21:$P$60,0)),"NO RATE")))) | K26: =IF(OR($G26="",$H26="",NOT(ISNUMBER($I26))),"",ROUND($H26*$I26*(1+IF($J26="",Setup!$B$16,$J26)),2)) | L26: =IF($K26="","",ROUND($K26*Setup!$B$13,2)) | M26: =IF($K26="","",$K26-$L26) | N26: =IF(OR($M26="",$D26=""),"",ROUND($M26*IFERROR(IF(VLOOKUP($D26,Setup!$A$76:$C$87,3,FALSE)="",Setup!$B$14,VLOOKUP($D26,Setup!$A$76:$C$87,3,FALSE)),Setup!$B$14),2)) | O26: =IF(OR($M26="",$E26=""),"",ROUND($M26*IFERROR(IF(VLOOKUP($E26,Setup!$A$76:$C$87,3,FALSE)="",Setup!$B$15,VLOOKUP($E26,Setup!$A$76:$C$87,3,FALSE)),Setup!$B$15),2)) | P26: 500 | Q26: 0 | R26: 8900 | S26: 520 | T26: 0 | U26: =IF($K26="","",SUM($R26:$T26)) | V26: =IF($K26="","",$M26-(N($N26)+N($O26)+IF($P26="",Setup!$B$17,$P26)+N($Q26))-N($U26)) | W26: Paid | Z26: =IF($A26="","",DATE(YEAR($A26),MONTH($A26),1))
A27: 46280 | B27: DR-1023 | C27: TRUCK 1 | D27: M. Reyes | E27: A. Bautista | F27: ORION | G27: BULACAN | H27: 21 | I27: =IF($G27="","",IF($F27="",IFERROR(INDEX(Setup!$C$21:$C$60,MATCH("|"&UPPER(TRIM($G27)),Setup!$Q$21:$Q$60,0)),"NO RATE"),IFERROR(INDEX(Setup!$C$21:$C$60,MATCH(UPPER(TRIM($F27))&"|"&UPPER(TRIM($G27)),Setup!$P$21:$P$60,0)),IFERROR(INDEX(Setup!$C$21:$C$60,MATCH(UPPER(TRIM($G27))&"|"&UPPER(TRIM($F27)),Setup!$P$21:$P$60,0)),"NO RATE")))) | K27: =IF(OR($G27="",$H27="",NOT(ISNUMBER($I27))),"",ROUND($H27*$I27*(1+IF($J27="",Setup!$B$16,$J27)),2)) | L27: =IF($K27="","",ROUND($K27*Setup!$B$13,2)) | M27: =IF($K27="","",$K27-$L27) | N27: =IF(OR($M27="",$D27=""),"",ROUND($M27*IFERROR(IF(VLOOKUP($D27,Setup!$A$76:$C$87,3,FALSE)="",Setup!$B$14,VLOOKUP($D27,Setup!$A$76:$C$87,3,FALSE)),Setup!$B$14),2)) | O27: =IF(OR($M27="",$E27=""),"",ROUND($M27*IFERROR(IF(VLOOKUP($E27,Setup!$A$76:$C$87,3,FALSE)="",Setup!$B$15,VLOOKUP($E27,Setup!$A$76:$C$87,3,FALSE)),Setup!$B$15),2)) | P27: 500 | Q27: 0 | R27: 6000 | S27: 590 | T27: 0 | U27: =IF($K27="","",SUM($R27:$T27)) | V27: =IF($K27="","",$M27-(N($N27)+N($O27)+IF($P27="",Setup!$B$17,$P27)+N($Q27))-N($U27)) | W27: Paid | Z27: =IF($A27="","",DATE(YEAR($A27),MONTH($A27),1))
A28: 46281 | B28: DR-1024 | C28: TRUCK 1 | D28: R. Dela Cruz | E28: J. Santos | F28: MABINI, BATANGAS | G28: MONCADA | H28: 18 | I28: =IF($G28="","",IF($F28="",IFERROR(INDEX(Setup!$C$21:$C$60,MATCH("|"&UPPER(TRIM($G28)),Setup!$Q$21:$Q$60,0)),"NO RATE"),IFERROR(INDEX(Setup!$C$21:$C$60,MATCH(UPPER(TRIM($F28))&"|"&UPPER(TRIM($G28)),Setup!$P$21:$P$60,0)),IFERROR(INDEX(Setup!$C$21:$C$60,MATCH(UPPER(TRIM($G28))&"|"&UPPER(TRIM($F28)),Setup!$P$21:$P$60,0)),"NO RATE")))) | K28: =IF(OR($G28="",$H28="",NOT(ISNUMBER($I28))),"",ROUND($H28*$I28*(1+IF($J28="",Setup!$B$16,$J28)),2)) | L28: =IF($K28="","",ROUND($K28*Setup!$B$13,2)) | M28: =IF($K28="","",$K28-$L28) | N28: =IF(OR($M28="",$D28=""),"",ROUND($M28*IFERROR(IF(VLOOKUP($D28,Setup!$A$76:$C$87,3,FALSE)="",Setup!$B$14,VLOOKUP($D28,Setup!$A$76:$C$87,3,FALSE)),Setup!$B$14),2)) | O28: =IF(OR($M28="",$E28=""),"",ROUND($M28*IFERROR(IF(VLOOKUP($E28,Setup!$A$76:$C$87,3,FALSE)="",Setup!$B$15,VLOOKUP($E28,Setup!$A$76:$C$87,3,FALSE)),Setup!$B$15),2)) | P28: 500 | Q28: 450 | R28: 7700 | S28: 430 | T28: 0 | U28: =IF($K28="","",SUM($R28:$T28)) | V28: =IF($K28="","",$M28-(N($N28)+N($O28)+IF($P28="",Setup!$B$17,$P28)+N($Q28))-N($U28)) | W28: Paid | X28: helper not available, driver solo | Z28: =IF($A28="","",DATE(YEAR($A28),MONTH($A28),1))
A29: 46283 | B29: DR-1025 | C29: TRUCK 1 | D29: M. Reyes | E29: A. Bautista | F29: BATAAN | G29: BULACAN | H29: 21 | I29: =IF($G29="","",IF($F29="",IFERROR(INDEX(Setup!$C$21:$C$60,MATCH("|"&UPPER(TRIM($G29)),Setup!$Q$21:$Q$60,0)),"NO RATE"),IFERROR(INDEX(Setup!$C$21:$C$60,MATCH(UPPER(TRIM($F29))&"|"&UPPER(TRIM($G29)),Setup!$P$21:$P$60,0)),IFERROR(INDEX(Setup!$C$21:$C$60,MATCH(UPPER(TRIM($G29))&"|"&UPPER(TRIM($F29)),Setup!$P$21:$P$60,0)),"NO RATE")))) | K29: =IF(OR($G29="",$H29="",NOT(ISNUMBER($I29))),"",ROUND($H29*$I29*(1+IF($J29="",Setup!$B$16,$J29)),2)) | L29: =IF($K29="","",ROUND($K29*Setup!$B$13,2)) | M29: =IF($K29="","",$K29-$L29) | N29: =IF(OR($M29="",$D29=""),"",ROUND($M29*IFERROR(IF(VLOOKUP($D29,Setup!$A$76:$C$87,3,FALSE)="",Setup!$B$14,VLOOKUP($D29,Setup!$A$76:$C$87,3,FALSE)),Setup!$B$14),2)) | O29: =IF(OR($M29="",$E29=""),"",ROUND($M29*IFERROR(IF(VLOOKUP($E29,Setup!$A$76:$C$87,3,FALSE)="",Setup!$B$15,VLOOKUP($E29,Setup!$A$76:$C$87,3,FALSE)),Setup!$B$15),2)) | P29: 500 | Q29: 0 | R29: 8600 | S29: 480 | T29: 0 | U29: =IF($K29="","",SUM($R29:$T29)) | V29: =IF($K29="","",$M29-(N($N29)+N($O29)+IF($P29="",Setup!$B$17,$P29)+N($Q29))-N($U29)) | W29: Paid | Z29: =IF($A29="","",DATE(YEAR($A29),MONTH($A29),1))
A30: 46285 | B30: DR-1026 | C30: TRUCK 1 | D30: R. Dela Cruz | E30: J. Santos | F30: ORION | G30: ROSALES | H30: 19 | I30: =IF($G30="","",IF($F30="",IFERROR(INDEX(Setup!$C$21:$C$60,MATCH("|"&UPPER(TRIM($G30)),Setup!$Q$21:$Q$60,0)),"NO RATE"),IFERROR(INDEX(Setup!$C$21:$C$60,MATCH(UPPER(TRIM($F30))&"|"&UPPER(TRIM($G30)),Setup!$P$21:$P$60,0)),IFERROR(INDEX(Setup!$C$21:$C$60,MATCH(UPPER(TRIM($G30))&"|"&UPPER(TRIM($F30)),Setup!$P$21:$P$60,0)),"NO RATE")))) | K30: =IF(OR($G30="",$H30="",NOT(ISNUMBER($I30))),"",ROUND($H30*$I30*(1+IF($J30="",Setup!$B$16,$J30)),2)) | L30: =IF($K30="","",ROUND($K30*Setup!$B$13,2)) | M30: =IF($K30="","",$K30-$L30) | N30: =IF(OR($M30="",$D30=""),"",ROUND($M30*IFERROR(IF(VLOOKUP($D30,Setup!$A$76:$C$87,3,FALSE)="",Setup!$B$14,VLOOKUP($D30,Setup!$A$76:$C$87,3,FALSE)),Setup!$B$14),2)) | O30: =IF(OR($M30="",$E30=""),"",ROUND($M30*IFERROR(IF(VLOOKUP($E30,Setup!$A$76:$C$87,3,FALSE)="",Setup!$B$15,VLOOKUP($E30,Setup!$A$76:$C$87,3,FALSE)),Setup!$B$15),2)) | P30: 500 | Q30: 0 | R30: 6000 | S30: 700 | T30: 0 | U30: =IF($K30="","",SUM($R30:$T30)) | V30: =IF($K30="","",$M30-(N($N30)+N($O30)+IF($P30="",Setup!$B$17,$P30)+N($Q30))-N($U30)) | W30: Paid | Z30: =IF($A30="","",DATE(YEAR($A30),MONTH($A30),1))
A31: 46287 | B31: DR-1027 | C31: TRUCK 1 | D31: M. Reyes | E31: A. Bautista | F31: MABINI, BATANGAS | G31: BATAAN | H31: 18 | I31: =IF($G31="","",IF($F31="",IFERROR(INDEX(Setup!$C$21:$C$60,MATCH("|"&UPPER(TRIM($G31)),Setup!$Q$21:$Q$60,0)),"NO RATE"),IFERROR(INDEX(Setup!$C$21:$C$60,MATCH(UPPER(TRIM($F31))&"|"&UPPER(TRIM($G31)),Setup!$P$21:$P$60,0)),IFERROR(INDEX(Setup!$C$21:$C$60,MATCH(UPPER(TRIM($G31))&"|"&UPPER(TRIM($F31)),Setup!$P$21:$P$60,0)),"NO RATE")))) | K31: =IF(OR($G31="",$H31="",NOT(ISNUMBER($I31))),"",ROUND($H31*$I31*(1+IF($J31="",Setup!$B$16,$J31)),2)) | L31: =IF($K31="","",ROUND($K31*Setup!$B$13,2)) | M31: =IF($K31="","",$K31-$L31) | N31: =IF(OR($M31="",$D31=""),"",ROUND($M31*IFERROR(IF(VLOOKUP($D31,Setup!$A$76:$C$87,3,FALSE)="",Setup!$B$14,VLOOKUP($D31,Setup!$A$76:$C$87,3,FALSE)),Setup!$B$14),2)) | O31: =IF(OR($M31="",$E31=""),"",ROUND($M31*IFERROR(IF(VLOOKUP($E31,Setup!$A$76:$C$87,3,FALSE)="",Setup!$B$15,VLOOKUP($E31,Setup!$A$76:$C$87,3,FALSE)),Setup!$B$15),2)) | P31: 500 | Q31: 0 | R31: 11500 | S31: 880 | T31: 0 | U31: =IF($K31="","",SUM($R31:$T31)) | V31: =IF($K31="","",$M31-(N($N31)+N($O31)+IF($P31="",Setup!$B$17,$P31)+N($Q31))-N($U31)) | W31: Paid | Z31: =IF($A31="","",DATE(YEAR($A31),MONTH($A31),1))
A32: 46288 | B32: DR-1028 | C32: TRUCK 1 | D32: R. Dela Cruz | E32: J. Santos | F32: BATAAN | G32: BMEG BATAAN | H32: 21 | I32: =IF($G32="","",IF($F32="",IFERROR(INDEX(Setup!$C$21:$C$60,MATCH("|"&UPPER(TRIM($G32)),Setup!$Q$21:$Q$60,0)),"NO RATE"),IFERROR(INDEX(Setup!$C$21:$C$60,MATCH(UPPER(TRIM($F32))&"|"&UPPER(TRIM($G32)),Setup!$P$21:$P$60,0)),IFERROR(INDEX(Setup!$C$21:$C$60,MATCH(UPPER(TRIM($G32))&"|"&UPPER(TRIM($F32)),Setup!$P$21:$P$60,0)),"NO RATE")))) | K32: =IF(OR($G32="",$H32="",NOT(ISNUMBER($I32))),"",ROUND($H32*$I32*(1+IF($J32="",Setup!$B$16,$J32)),2)) | L32: =IF($K32="","",ROUND($K32*Setup!$B$13,2)) | M32: =IF($K32="","",$K32-$L32) | N32: =IF(OR($M32="",$D32=""),"",ROUND($M32*IFERROR(IF(VLOOKUP($D32,Setup!$A$76:$C$87,3,FALSE)="",Setup!$B$14,VLOOKUP($D32,Setup!$A$76:$C$87,3,FALSE)),Setup!$B$14),2)) | O32: =IF(OR($M32="",$E32=""),"",ROUND($M32*IFERROR(IF(VLOOKUP($E32,Setup!$A$76:$C$87,3,FALSE)="",Setup!$B$15,VLOOKUP($E32,Setup!$A$76:$C$87,3,FALSE)),Setup!$B$15),2)) | P32: 400 | Q32: 0 | R32: 1000 | S32: 120 | T32: 0 | U32: =IF($K32="","",SUM($R32:$T32)) | V32: =IF($K32="","",$M32-(N($N32)+N($O32)+IF($P32="",Setup!$B$17,$P32)+N($Q32))-N($U32)) | W32: Paid | Z32: =IF($A32="","",DATE(YEAR($A32),MONTH($A32),1))
A33: 46290 | B33: DR-1029 | C33: TRUCK 1 | D33: M. Reyes | E33: A. Bautista | F33: BATAAN | G33: TARLAC | H33: 17 | I33: =IF($G33="","",IF($F33="",IFERROR(INDEX(Setup!$C$21:$C$60,MATCH("|"&UPPER(TRIM($G33)),Setup!$Q$21:$Q$60,0)),"NO RATE"),IFERROR(INDEX(Setup!$C$21:$C$60,MATCH(UPPER(TRIM($F33))&"|"&UPPER(TRIM($G33)),Setup!$P$21:$P$60,0)),IFERROR(INDEX(Setup!$C$21:$C$60,MATCH(UPPER(TRIM($G33))&"|"&UPPER(TRIM($F33)),Setup!$P$21:$P$60,0)),"NO RATE")))) | K33: =IF(OR($G33="",$H33="",NOT(ISNUMBER($I33))),"",ROUND($H33*$I33*(1+IF($J33="",Setup!$B$16,$J33)),2)) | L33: =IF($K33="","",ROUND($K33*Setup!$B$13,2)) | M33: =IF($K33="","",$K33-$L33) | N33: =IF(OR($M33="",$D33=""),"",ROUND($M33*IFERROR(IF(VLOOKUP($D33,Setup!$A$76:$C$87,3,FALSE)="",Setup!$B$14,VLOOKUP($D33,Setup!$A$76:$C$87,3,FALSE)),Setup!$B$14),2)) | O33: =IF(OR($M33="",$E33=""),"",ROUND($M33*IFERROR(IF(VLOOKUP($E33,Setup!$A$76:$C$87,3,FALSE)="",Setup!$B$15,VLOOKUP($E33,Setup!$A$76:$C$87,3,FALSE)),Setup!$B$15),2)) | P33: 500 | Q33: 450 | R33: 5600 | S33: 620 | T33: 0 | U33: =IF($K33="","",SUM($R33:$T33)) | V33: =IF($K33="","",$M33-(N($N33)+N($O33)+IF($P33="",Setup!$B$17,$P33)+N($Q33))-N($U33)) | W33: Partial | Z33: =IF($A33="","",DATE(YEAR($A33),MONTH($A33),1))
A34: 46292 | B34: DR-1030 | C34: TRUCK 1 | D34: R. Dela Cruz | E34: J. Santos | F34: BATAAN | G34: BMPP | H34: 20 | I34: =IF($G34="","",IF($F34="",IFERROR(INDEX(Setup!$C$21:$C$60,MATCH("|"&UPPER(TRIM($G34)),Setup!$Q$21:$Q$60,0)),"NO RATE"),IFERROR(INDEX(Setup!$C$21:$C$60,MATCH(UPPER(TRIM($F34))&"|"&UPPER(TRIM($G34)),Setup!$P$21:$P$60,0)),IFERROR(INDEX(Setup!$C$21:$C$60,MATCH(UPPER(TRIM($G34))&"|"&UPPER(TRIM($F34)),Setup!$P$21:$P$60,0)),"NO RATE")))) | K34: =IF(OR($G34="",$H34="",NOT(ISNUMBER($I34))),"",ROUND($H34*$I34*(1+IF($J34="",Setup!$B$16,$J34)),2)) | L34: =IF($K34="","",ROUND($K34*Setup!$B$13,2)) | M34: =IF($K34="","",$K34-$L34) | N34: =IF(OR($M34="",$D34=""),"",ROUND($M34*IFERROR(IF(VLOOKUP($D34,Setup!$A$76:$C$87,3,FALSE)="",Setup!$B$14,VLOOKUP($D34,Setup!$A$76:$C$87,3,FALSE)),Setup!$B$14),2)) | O34: =IF(OR($M34="",$E34=""),"",ROUND($M34*IFERROR(IF(VLOOKUP($E34,Setup!$A$76:$C$87,3,FALSE)="",Setup!$B$15,VLOOKUP($E34,Setup!$A$76:$C$87,3,FALSE)),Setup!$B$15),2)) | P34: 500 | Q34: 0 | R34: 8300 | S34: 560 | T34: 0 | U34: =IF($K34="","",SUM($R34:$T34)) | V34: =IF($K34="","",$M34-(N($N34)+N($O34)+IF($P34="",Setup!$B$17,$P34)+N($Q34))-N($U34)) | W34: Partial | Z34: =IF($A34="","",DATE(YEAR($A34),MONTH($A34),1))
A35: 46296 | B35: DR-1031 | C35: TRUCK 1 | D35: R. Dela Cruz | E35: J. Santos | F35: BATAAN | G35: TARLAC | H35: 19 | I35: =IF($G35="","",IF($F35="",IFERROR(INDEX(Setup!$C$21:$C$60,MATCH("|"&UPPER(TRIM($G35)),Setup!$Q$21:$Q$60,0)),"NO RATE"),IFERROR(INDEX(Setup!$C$21:$C$60,MATCH(UPPER(TRIM($F35))&"|"&UPPER(TRIM($G35)),Setup!$P$21:$P$60,0)),IFERROR(INDEX(Setup!$C$21:$C$60,MATCH(UPPER(TRIM($G35))&"|"&UPPER(TRIM($F35)),Setup!$P$21:$P$60,0)),"NO RATE")))) | K35: =IF(OR($G35="",$H35="",NOT(ISNUMBER($I35))),"",ROUND($H35*$I35*(1+IF($J35="",Setup!$B$16,$J35)),2)) | L35: =IF($K35="","",ROUND($K35*Setup!$B$13,2)) | M35: =IF($K35="","",$K35-$L35) | N35: =IF(OR($M35="",$D35=""),"",ROUND($M35*IFERROR(IF(VLOOKUP($D35,Setup!$A$76:$C$87,3,FALSE)="",Setup!$B$14,VLOOKUP($D35,Setup!$A$76:$C$87,3,FALSE)),Setup!$B$14),2)) | O35: =IF(OR($M35="",$E35=""),"",ROUND($M35*IFERROR(IF(VLOOKUP($E35,Setup!$A$76:$C$87,3,FALSE)="",Setup!$B$15,VLOOKUP($E35,Setup!$A$76:$C$87,3,FALSE)),Setup!$B$15),2)) | P35: 500 | Q35: 0 | R35: 7400 | S35: 620 | T35: 0 | U35: =IF($K35="","",SUM($R35:$T35)) | V35: =IF($K35="","",$M35-(N($N35)+N($O35)+IF($P35="",Setup!$B$17,$P35)+N($Q35))-N($U35)) | W35: Paid | Z35: =IF($A35="","",DATE(YEAR($A35),MONTH($A35),1))
A36: 46297 | B36: DR-1032 | C36: TRUCK 1 | D36: M. Reyes | E36: A. Bautista | F36: BATAAN | G36: BMPP | H36: 19 | I36: =IF($G36="","",IF($F36="",IFERROR(INDEX(Setup!$C$21:$C$60,MATCH("|"&UPPER(TRIM($G36)),Setup!$Q$21:$Q$60,0)),"NO RATE"),IFERROR(INDEX(Setup!$C$21:$C$60,MATCH(UPPER(TRIM($F36))&"|"&UPPER(TRIM($G36)),Setup!$P$21:$P$60,0)),IFERROR(INDEX(Setup!$C$21:$C$60,MATCH(UPPER(TRIM($G36))&"|"&UPPER(TRIM($F36)),Setup!$P$21:$P$60,0)),"NO RATE")))) | K36: =IF(OR($G36="",$H36="",NOT(ISNUMBER($I36))),"",ROUND($H36*$I36*(1+IF($J36="",Setup!$B$16,$J36)),2)) | L36: =IF($K36="","",ROUND($K36*Setup!$B$13,2)) | M36: =IF($K36="","",$K36-$L36) | N36: =IF(OR($M36="",$D36=""),"",ROUND($M36*IFERROR(IF(VLOOKUP($D36,Setup!$A$76:$C$87,3,FALSE)="",Setup!$B$14,VLOOKUP($D36,Setup!$A$76:$C$87,3,FALSE)),Setup!$B$14),2)) | O36: =IF(OR($M36="",$E36=""),"",ROUND($M36*IFERROR(IF(VLOOKUP($E36,Setup!$A$76:$C$87,3,FALSE)="",Setup!$B$15,VLOOKUP($E36,Setup!$A$76:$C$87,3,FALSE)),Setup!$B$15),2)) | P36: 500 | Q36: 0 | R36: 7200 | S36: 560 | T36: 0 | U36: =IF($K36="","",SUM($R36:$T36)) | V36: =IF($K36="","",$M36-(N($N36)+N($O36)+IF($P36="",Setup!$B$17,$P36)+N($Q36))-N($U36)) | W36: Paid | Z36: =IF($A36="","",DATE(YEAR($A36),MONTH($A36),1))
A37: 46299 | B37: DR-1033 | C37: TRUCK 1 | D37: R. Dela Cruz | E37: J. Santos | F37: ORION | G37: BMPP | H37: 22 | I37: =IF($G37="","",IF($F37="",IFERROR(INDEX(Setup!$C$21:$C$60,MATCH("|"&UPPER(TRIM($G37)),Setup!$Q$21:$Q$60,0)),"NO RATE"),IFERROR(INDEX(Setup!$C$21:$C$60,MATCH(UPPER(TRIM($F37))&"|"&UPPER(TRIM($G37)),Setup!$P$21:$P$60,0)),IFERROR(INDEX(Setup!$C$21:$C$60,MATCH(UPPER(TRIM($G37))&"|"&UPPER(TRIM($F37)),Setup!$P$21:$P$60,0)),"NO RATE")))) | K37: =IF(OR($G37="",$H37="",NOT(ISNUMBER($I37))),"",ROUND($H37*$I37*(1+IF($J37="",Setup!$B$16,$J37)),2)) | L37: =IF($K37="","",ROUND($K37*Setup!$B$13,2)) | M37: =IF($K37="","",$K37-$L37) | N37: =IF(OR($M37="",$D37=""),"",ROUND($M37*IFERROR(IF(VLOOKUP($D37,Setup!$A$76:$C$87,3,FALSE)="",Setup!$B$14,VLOOKUP($D37,Setup!$A$76:$C$87,3,FALSE)),Setup!$B$14),2)) | O37: =IF(OR($M37="",$E37=""),"",ROUND($M37*IFERROR(IF(VLOOKUP($E37,Setup!$A$76:$C$87,3,FALSE)="",Setup!$B$15,VLOOKUP($E37,Setup!$A$76:$C$87,3,FALSE)),Setup!$B$15),2)) | P37: 500 | Q37: 0 | R37: 8600 | S37: 540 | T37: 0 | U37: =IF($K37="","",SUM($R37:$T37)) | V37: =IF($K37="","",$M37-(N($N37)+N($O37)+IF($P37="",Setup!$B$17,$P37)+N($Q37))-N($U37)) | W37: Paid | Z37: =IF($A37="","",DATE(YEAR($A37),MONTH($A37),1))
A38: 46301 | B38: DR-1034 | C38: TRUCK 1 | D38: M. Reyes | E38: A. Bautista | F38: MABINI, BATANGAS | G38: BMPP | H38: 21 | I38: =IF($G38="","",IF($F38="",IFERROR(INDEX(Setup!$C$21:$C$60,MATCH("|"&UPPER(TRIM($G38)),Setup!$Q$21:$Q$60,0)),"NO RATE"),IFERROR(INDEX(Setup!$C$21:$C$60,MATCH(UPPER(TRIM($F38))&"|"&UPPER(TRIM($G38)),Setup!$P$21:$P$60,0)),IFERROR(INDEX(Setup!$C$21:$C$60,MATCH(UPPER(TRIM($G38))&"|"&UPPER(TRIM($F38)),Setup!$P$21:$P$60,0)),"NO RATE")))) | K38: =IF(OR($G38="",$H38="",NOT(ISNUMBER($I38))),"",ROUND($H38*$I38*(1+IF($J38="",Setup!$B$16,$J38)),2)) | L38: =IF($K38="","",ROUND($K38*Setup!$B$13,2)) | M38: =IF($K38="","",$K38-$L38) | N38: =IF(OR($M38="",$D38=""),"",ROUND($M38*IFERROR(IF(VLOOKUP($D38,Setup!$A$76:$C$87,3,FALSE)="",Setup!$B$14,VLOOKUP($D38,Setup!$A$76:$C$87,3,FALSE)),Setup!$B$14),2)) | O38: =IF(OR($M38="",$E38=""),"",ROUND($M38*IFERROR(IF(VLOOKUP($E38,Setup!$A$76:$C$87,3,FALSE)="",Setup!$B$15,VLOOKUP($E38,Setup!$A$76:$C$87,3,FALSE)),Setup!$B$15),2)) | P38: 500 | Q38: 450 | R38: 14400 | S38: 980 | T38: 0 | U38: =IF($K38="","",SUM($R38:$T38)) | V38: =IF($K38="","",$M38-(N($N38)+N($O38)+IF($P38="",Setup!$B$17,$P38)+N($Q38))-N($U38)) | W38: Paid | Z38: =IF($A38="","",DATE(YEAR($A38),MONTH($A38),1))
A39: 46303 | B39: DR-1035 | C39: TRUCK 1 | D39: R. Dela Cruz | E39: J. Santos | F39: BATAAN | G39: ISABELA | H39: 17 | I39: =IF($G39="","",IF($F39="",IFERROR(INDEX(Setup!$C$21:$C$60,MATCH("|"&UPPER(TRIM($G39)),Setup!$Q$21:$Q$60,0)),"NO RATE"),IFERROR(INDEX(Setup!$C$21:$C$60,MATCH(UPPER(TRIM($F39))&"|"&UPPER(TRIM($G39)),Setup!$P$21:$P$60,0)),IFERROR(INDEX(Setup!$C$21:$C$60,MATCH(UPPER(TRIM($G39))&"|"&UPPER(TRIM($F39)),Setup!$P$21:$P$60,0)),"NO RATE")))) | K39: =IF(OR($G39="",$H39="",NOT(ISNUMBER($I39))),"",ROUND($H39*$I39*(1+IF($J39="",Setup!$B$16,$J39)),2)) | L39: =IF($K39="","",ROUND($K39*Setup!$B$13,2)) | M39: =IF($K39="","",$K39-$L39) | N39: =IF(OR($M39="",$D39=""),"",ROUND($M39*IFERROR(IF(VLOOKUP($D39,Setup!$A$76:$C$87,3,FALSE)="",Setup!$B$14,VLOOKUP($D39,Setup!$A$76:$C$87,3,FALSE)),Setup!$B$14),2)) | O39: =IF(OR($M39="",$E39=""),"",ROUND($M39*IFERROR(IF(VLOOKUP($E39,Setup!$A$76:$C$87,3,FALSE)="",Setup!$B$15,VLOOKUP($E39,Setup!$A$76:$C$87,3,FALSE)),Setup!$B$15),2)) | P39: 500 | Q39: 0 | R39: 14300 | S39: 1250 | T39: 0 | U39: =IF($K39="","",SUM($R39:$T39)) | V39: =IF($K39="","",$M39-(N($N39)+N($O39)+IF($P39="",Setup!$B$17,$P39)+N($Q39))-N($U39)) | W39: Paid | X39: long haul — diesel receipt attached | Z39: =IF($A39="","",DATE(YEAR($A39),MONTH($A39),1))
A40: 46305 | B40: DR-1036 | C40: TRUCK 1 | D40: M. Reyes | E40: A. Bautista | F40: ORION | G40: TARLAC | H40: 20 | I40: =IF($G40="","",IF($F40="",IFERROR(INDEX(Setup!$C$21:$C$60,MATCH("|"&UPPER(TRIM($G40)),Setup!$Q$21:$Q$60,0)),"NO RATE"),IFERROR(INDEX(Setup!$C$21:$C$60,MATCH(UPPER(TRIM($F40))&"|"&UPPER(TRIM($G40)),Setup!$P$21:$P$60,0)),IFERROR(INDEX(Setup!$C$21:$C$60,MATCH(UPPER(TRIM($G40))&"|"&UPPER(TRIM($F40)),Setup!$P$21:$P$60,0)),"NO RATE")))) | K40: =IF(OR($G40="",$H40="",NOT(ISNUMBER($I40))),"",ROUND($H40*$I40*(1+IF($J40="",Setup!$B$16,$J40)),2)) | L40: =IF($K40="","",ROUND($K40*Setup!$B$13,2)) | M40: =IF($K40="","",$K40-$L40) | N40: =IF(OR($M40="",$D40=""),"",ROUND($M40*IFERROR(IF(VLOOKUP($D40,Setup!$A$76:$C$87,3,FALSE)="",Setup!$B$14,VLOOKUP($D40,Setup!$A$76:$C$87,3,FALSE)),Setup!$B$14),2)) | O40: =IF(OR($M40="",$E40=""),"",ROUND($M40*IFERROR(IF(VLOOKUP($E40,Setup!$A$76:$C$87,3,FALSE)="",Setup!$B$15,VLOOKUP($E40,Setup!$A$76:$C$87,3,FALSE)),Setup!$B$15),2)) | P40: 500 | Q40: 0 | R40: 6400 | S40: 610 | T40: 0 | U40: =IF($K40="","",SUM($R40:$T40)) | V40: =IF($K40="","",$M40-(N($N40)+N($O40)+IF($P40="",Setup!$B$17,$P40)+N($Q40))-N($U40)) | W40: Paid | Z40: =IF($A40="","",DATE(YEAR($A40),MONTH($A40),1))
A41: 46307 | B41: DR-1037 | C41: TRUCK 1 | D41: R. Dela Cruz | E41: J. Santos | F41: MABINI, BATANGAS | G41: TARLAC | H41: 19 | I41: =IF($G41="","",IF($F41="",IFERROR(INDEX(Setup!$C$21:$C$60,MATCH("|"&UPPER(TRIM($G41)),Setup!$Q$21:$Q$60,0)),"NO RATE"),IFERROR(INDEX(Setup!$C$21:$C$60,MATCH(UPPER(TRIM($F41))&"|"&UPPER(TRIM($G41)),Setup!$P$21:$P$60,0)),IFERROR(INDEX(Setup!$C$21:$C$60,MATCH(UPPER(TRIM($G41))&"|"&UPPER(TRIM($F41)),Setup!$P$21:$P$60,0)),"NO RATE")))) | K41: =IF(OR($G41="",$H41="",NOT(ISNUMBER($I41))),"",ROUND($H41*$I41*(1+IF($J41="",Setup!$B$16,$J41)),2)) | L41: =IF($K41="","",ROUND($K41*Setup!$B$13,2)) | M41: =IF($K41="","",$K41-$L41) | N41: =IF(OR($M41="",$D41=""),"",ROUND($M41*IFERROR(IF(VLOOKUP($D41,Setup!$A$76:$C$87,3,FALSE)="",Setup!$B$14,VLOOKUP($D41,Setup!$A$76:$C$87,3,FALSE)),Setup!$B$14),2)) | O41: =IF(OR($M41="",$E41=""),"",ROUND($M41*IFERROR(IF(VLOOKUP($E41,Setup!$A$76:$C$87,3,FALSE)="",Setup!$B$15,VLOOKUP($E41,Setup!$A$76:$C$87,3,FALSE)),Setup!$B$15),2)) | P41: 500 | Q41: 0 | R41: 11700 | S41: 900 | T41: 0 | U41: =IF($K41="","",SUM($R41:$T41)) | V41: =IF($K41="","",$M41-(N($N41)+N($O41)+IF($P41="",Setup!$B$17,$P41)+N($Q41))-N($U41)) | W41: Paid | Z41: =IF($A41="","",DATE(YEAR($A41),MONTH($A41),1))
A42: 46309 | B42: DR-1038 | C42: TRUCK 1 | D42: M. Reyes | E42: A. Bautista | F42: BATAAN | G42: ARMOR | H42: 19 | I42: =IF($G42="","",IF($F42="",IFERROR(INDEX(Setup!$C$21:$C$60,MATCH("|"&UPPER(TRIM($G42)),Setup!$Q$21:$Q$60,0)),"NO RATE"),IFERROR(INDEX(Setup!$C$21:$C$60,MATCH(UPPER(TRIM($F42))&"|"&UPPER(TRIM($G42)),Setup!$P$21:$P$60,0)),IFERROR(INDEX(Setup!$C$21:$C$60,MATCH(UPPER(TRIM($G42))&"|"&UPPER(TRIM($F42)),Setup!$P$21:$P$60,0)),"NO RATE")))) | K42: =IF(OR($G42="",$H42="",NOT(ISNUMBER($I42))),"",ROUND($H42*$I42*(1+IF($J42="",Setup!$B$16,$J42)),2)) | L42: =IF($K42="","",ROUND($K42*Setup!$B$13,2)) | M42: =IF($K42="","",$K42-$L42) | N42: =IF(OR($M42="",$D42=""),"",ROUND($M42*IFERROR(IF(VLOOKUP($D42,Setup!$A$76:$C$87,3,FALSE)="",Setup!$B$14,VLOOKUP($D42,Setup!$A$76:$C$87,3,FALSE)),Setup!$B$14),2)) | O42: =IF(OR($M42="",$E42=""),"",ROUND($M42*IFERROR(IF(VLOOKUP($E42,Setup!$A$76:$C$87,3,FALSE)="",Setup!$B$15,VLOOKUP($E42,Setup!$A$76:$C$87,3,FALSE)),Setup!$B$15),2)) | P42: 500 | Q42: 0 | R42: 6900 | S42: 520 | T42: 0 | U42: =IF($K42="","",SUM($R42:$T42)) | V42: =IF($K42="","",$M42-(N($N42)+N($O42)+IF($P42="",Setup!$B$17,$P42)+N($Q42))-N($U42)) | W42: Paid | Z42: =IF($A42="","",DATE(YEAR($A42),MONTH($A42),1))
A43: 46310 | B43: DR-1039 | C43: TRUCK 1 | D43: R. Dela Cruz | E43: J. Santos | F43: ORION | G43: BULACAN | H43: 22 | I43: =IF($G43="","",IF($F43="",IFERROR(INDEX(Setup!$C$21:$C$60,MATCH("|"&UPPER(TRIM($G43)),Setup!$Q$21:$Q$60,0)),"NO RATE"),IFERROR(INDEX(Setup!$C$21:$C$60,MATCH(UPPER(TRIM($F43))&"|"&UPPER(TRIM($G43)),Setup!$P$21:$P$60,0)),IFERROR(INDEX(Setup!$C$21:$C$60,MATCH(UPPER(TRIM($G43))&"|"&UPPER(TRIM($F43)),Setup!$P$21:$P$60,0)),"NO RATE")))) | K43: =IF(OR($G43="",$H43="",NOT(ISNUMBER($I43))),"",ROUND($H43*$I43*(1+IF($J43="",Setup!$B$16,$J43)),2)) | L43: =IF($K43="","",ROUND($K43*Setup!$B$13,2)) | M43: =IF($K43="","",$K43-$L43) | N43: =IF(OR($M43="",$D43=""),"",ROUND($M43*IFERROR(IF(VLOOKUP($D43,Setup!$A$76:$C$87,3,FALSE)="",Setup!$B$14,VLOOKUP($D43,Setup!$A$76:$C$87,3,FALSE)),Setup!$B$14),2)) | O43: =IF(OR($M43="",$E43=""),"",ROUND($M43*IFERROR(IF(VLOOKUP($E43,Setup!$A$76:$C$87,3,FALSE)="",Setup!$B$15,VLOOKUP($E43,Setup!$A$76:$C$87,3,FALSE)),Setup!$B$15),2)) | P43: 500 | Q43: 450 | R43: 6800 | S43: 590 | T43: 0 | U43: =IF($K43="","",SUM($R43:$T43)) | V43: =IF($K43="","",$M43-(N($N43)+N($O43)+IF($P43="",Setup!$B$17,$P43)+N($Q43))-N($U43)) | W43: Paid | Z43: =IF($A43="","",DATE(YEAR($A43),MONTH($A43),1))
A44: 46312 | B44: DR-1040 | C44: TRUCK 1 | D44: M. Reyes | E44: A. Bautista | F44: MABINI, BATANGAS | G44: MONCADA | H44: 19 | I44: =IF($G44="","",IF($F44="",IFERROR(INDEX(Setup!$C$21:$C$60,MATCH("|"&UPPER(TRIM($G44)),Setup!$Q$21:$Q$60,0)),"NO RATE"),IFERROR(INDEX(Setup!$C$21:$C$60,MATCH(UPPER(TRIM($F44))&"|"&UPPER(TRIM($G44)),Setup!$P$21:$P$60,0)),IFERROR(INDEX(Setup!$C$21:$C$60,MATCH(UPPER(TRIM($G44))&"|"&UPPER(TRIM($F44)),Setup!$P$21:$P$60,0)),"NO RATE")))) | K44: =IF(OR($G44="",$H44="",NOT(ISNUMBER($I44))),"",ROUND($H44*$I44*(1+IF($J44="",Setup!$B$16,$J44)),2)) | L44: =IF($K44="","",ROUND($K44*Setup!$B$13,2)) | M44: =IF($K44="","",$K44-$L44) | N44: =IF(OR($M44="",$D44=""),"",ROUND($M44*IFERROR(IF(VLOOKUP($D44,Setup!$A$76:$C$87,3,FALSE)="",Setup!$B$14,VLOOKUP($D44,Setup!$A$76:$C$87,3,FALSE)),Setup!$B$14),2)) | O44: =IF(OR($M44="",$E44=""),"",ROUND($M44*IFERROR(IF(VLOOKUP($E44,Setup!$A$76:$C$87,3,FALSE)="",Setup!$B$15,VLOOKUP($E44,Setup!$A$76:$C$87,3,FALSE)),Setup!$B$15),2)) | P44: 500 | Q44: 0 | R44: 8700 | S44: 430 | T44: 0 | U44: =IF($K44="","",SUM($R44:$T44)) | V44: =IF($K44="","",$M44-(N($N44)+N($O44)+IF($P44="",Setup!$B$17,$P44)+N($Q44))-N($U44)) | W44: Unpaid | X44: helper not available, driver solo | Z44: =IF($A44="","",DATE(YEAR($A44),MONTH($A44),1))
A45: 46314 | B45: DR-1041 | C45: TRUCK 1 | D45: R. Dela Cruz | E45: J. Santos | F45: BATAAN | G45: BULACAN | H45: 19 | I45: =IF($G45="","",IF($F45="",IFERROR(INDEX(Setup!$C$21:$C$60,MATCH("|"&UPPER(TRIM($G45)),Setup!$Q$21:$Q$60,0)),"NO RATE"),IFERROR(INDEX(Setup!$C$21:$C$60,MATCH(UPPER(TRIM($F45))&"|"&UPPER(TRIM($G45)),Setup!$P$21:$P$60,0)),IFERROR(INDEX(Setup!$C$21:$C$60,MATCH(UPPER(TRIM($G45))&"|"&UPPER(TRIM($F45)),Setup!$P$21:$P$60,0)),"NO RATE")))) | K45: =IF(OR($G45="",$H45="",NOT(ISNUMBER($I45))),"",ROUND($H45*$I45*(1+IF($J45="",Setup!$B$16,$J45)),2)) | L45: =IF($K45="","",ROUND($K45*Setup!$B$13,2)) | M45: =IF($K45="","",$K45-$L45) | N45: =IF(OR($M45="",$D45=""),"",ROUND($M45*IFERROR(IF(VLOOKUP($D45,Setup!$A$76:$C$87,3,FALSE)="",Setup!$B$14,VLOOKUP($D45,Setup!$A$76:$C$87,3,FALSE)),Setup!$B$14),2)) | O45: =IF(OR($M45="",$E45=""),"",ROUND($M45*IFERROR(IF(VLOOKUP($E45,Setup!$A$76:$C$87,3,FALSE)="",Setup!$B$15,VLOOKUP($E45,Setup!$A$76:$C$87,3,FALSE)),Setup!$B$15),2)) | P45: 500 | Q45: 0 | R45: 6600 | S45: 480 | T45: 0 | U45: =IF($K45="","",SUM($R45:$T45)) | V45: =IF($K45="","",$M45-(N($N45)+N($O45)+IF($P45="",Setup!$B$17,$P45)+N($Q45))-N($U45)) | W45: Unpaid | Z45: =IF($A45="","",DATE(YEAR($A45),MONTH($A45),1))
A46: 46316 | B46: DR-1042 | C46: TRUCK 1 | D46: M. Reyes | E46: A. Bautista | F46: ORION | G46: ROSALES | H46: 20 | I46: =IF($G46="","",IF($F46="",IFERROR(INDEX(Setup!$C$21:$C$60,MATCH("|"&UPPER(TRIM($G46)),Setup!$Q$21:$Q$60,0)),"NO RATE"),IFERROR(INDEX(Setup!$C$21:$C$60,MATCH(UPPER(TRIM($F46))&"|"&UPPER(TRIM($G46)),Setup!$P$21:$P$60,0)),IFERROR(INDEX(Setup!$C$21:$C$60,MATCH(UPPER(TRIM($G46))&"|"&UPPER(TRIM($F46)),Setup!$P$21:$P$60,0)),"NO RATE")))) | K46: =IF(OR($G46="",$H46="",NOT(ISNUMBER($I46))),"",ROUND($H46*$I46*(1+IF($J46="",Setup!$B$16,$J46)),2)) | L46: =IF($K46="","",ROUND($K46*Setup!$B$13,2)) | M46: =IF($K46="","",$K46-$L46) | N46: =IF(OR($M46="",$D46=""),"",ROUND($M46*IFERROR(IF(VLOOKUP($D46,Setup!$A$76:$C$87,3,FALSE)="",Setup!$B$14,VLOOKUP($D46,Setup!$A$76:$C$87,3,FALSE)),Setup!$B$14),2)) | O46: =IF(OR($M46="",$E46=""),"",ROUND($M46*IFERROR(IF(VLOOKUP($E46,Setup!$A$76:$C$87,3,FALSE)="",Setup!$B$15,VLOOKUP($E46,Setup!$A$76:$C$87,3,FALSE)),Setup!$B$15),2)) | P46: 500 | Q46: 0 | R46: 6900 | S46: 700 | T46: 0 | U46: =IF($K46="","",SUM($R46:$T46)) | V46: =IF($K46="","",$M46-(N($N46)+N($O46)+IF($P46="",Setup!$B$17,$P46)+N($Q46))-N($U46)) | W46: Unpaid | Z46: =IF($A46="","",DATE(YEAR($A46),MONTH($A46),1))
A47: 46318 | B47: DR-1043 | C47: TRUCK 1 | D47: R. Dela Cruz | E47: J. Santos | F47: MABINI, BATANGAS | G47: BATAAN | H47: 19 | I47: =IF($G47="","",IF($F47="",IFERROR(INDEX(Setup!$C$21:$C$60,MATCH("|"&UPPER(TRIM($G47)),Setup!$Q$21:$Q$60,0)),"NO RATE"),IFERROR(INDEX(Setup!$C$21:$C$60,MATCH(UPPER(TRIM($F47))&"|"&UPPER(TRIM($G47)),Setup!$P$21:$P$60,0)),IFERROR(INDEX(Setup!$C$21:$C$60,MATCH(UPPER(TRIM($G47))&"|"&UPPER(TRIM($F47)),Setup!$P$21:$P$60,0)),"NO RATE")))) | J47: 0.2 | K47: =IF(OR($G47="",$H47="",NOT(ISNUMBER($I47))),"",ROUND($H47*$I47*(1+IF($J47="",Setup!$B$16,$J47)),2)) | L47: =IF($K47="","",ROUND($K47*Setup!$B$13,2)) | M47: =IF($K47="","",$K47-$L47) | N47: =IF(OR($M47="",$D47=""),"",ROUND($M47*IFERROR(IF(VLOOKUP($D47,Setup!$A$76:$C$87,3,FALSE)="",Setup!$B$14,VLOOKUP($D47,Setup!$A$76:$C$87,3,FALSE)),Setup!$B$14),2)) | O47: =IF(OR($M47="",$E47=""),"",ROUND($M47*IFERROR(IF(VLOOKUP($E47,Setup!$A$76:$C$87,3,FALSE)="",Setup!$B$15,VLOOKUP($E47,Setup!$A$76:$C$87,3,FALSE)),Setup!$B$15),2)) | P47: 500 | Q47: 0 | R47: 13100 | S47: 880 | T47: 0 | U47: =IF($K47="","",SUM($R47:$T47)) | V47: =IF($K47="","",$M47-(N($N47)+N($O47)+IF($P47="",Setup!$B$17,$P47)+N($Q47))-N($U47)) | W47: Unpaid | X47: surcharge raised to 20% | Z47: =IF($A47="","",DATE(YEAR($A47),MONTH($A47),1))
A48: 46320 | B48: DR-1044 | C48: TRUCK 1 | D48: M. Reyes | E48: A. Bautista | F48: BATAAN | G48: BMEG BATAAN | H48: 19 | I48: =IF($G48="","",IF($F48="",IFERROR(INDEX(Setup!$C$21:$C$60,MATCH("|"&UPPER(TRIM($G48)),Setup!$Q$21:$Q$60,0)),"NO RATE"),IFERROR(INDEX(Setup!$C$21:$C$60,MATCH(UPPER(TRIM($F48))&"|"&UPPER(TRIM($G48)),Setup!$P$21:$P$60,0)),IFERROR(INDEX(Setup!$C$21:$C$60,MATCH(UPPER(TRIM($G48))&"|"&UPPER(TRIM($F48)),Setup!$P$21:$P$60,0)),"NO RATE")))) | K48: =IF(OR($G48="",$H48="",NOT(ISNUMBER($I48))),"",ROUND($H48*$I48*(1+IF($J48="",Setup!$B$16,$J48)),2)) | L48: =IF($K48="","",ROUND($K48*Setup!$B$13,2)) | M48: =IF($K48="","",$K48-$L48) | N48: =IF(OR($M48="",$D48=""),"",ROUND($M48*IFERROR(IF(VLOOKUP($D48,Setup!$A$76:$C$87,3,FALSE)="",Setup!$B$14,VLOOKUP($D48,Setup!$A$76:$C$87,3,FALSE)),Setup!$B$14),2)) | O48: =IF(OR($M48="",$E48=""),"",ROUND($M48*IFERROR(IF(VLOOKUP($E48,Setup!$A$76:$C$87,3,FALSE)="",Setup!$B$15,VLOOKUP($E48,Setup!$A$76:$C$87,3,FALSE)),Setup!$B$15),2)) | P48: 400 | Q48: 450 | R48: 800 | S48: 120 | T48: 0 | U48: =IF($K48="","",SUM($R48:$T48)) | V48: =IF($K48="","",$M48-(N($N48)+N($O48)+IF($P48="",Setup!$B$17,$P48)+N($Q48))-N($U48)) | W48: Unpaid | Z48: =IF($A48="","",DATE(YEAR($A48),MONTH($A48),1))
A49: 46322 | B49: DR-1045 | C49: TRUCK 1 | D49: R. Dela Cruz | E49: J. Santos | F49: BATAAN | G49: TARLAC | H49: 18 | I49: =IF($G49="","",IF($F49="",IFERROR(INDEX(Setup!$C$21:$C$60,MATCH("|"&UPPER(TRIM($G49)),Setup!$Q$21:$Q$60,0)),"NO RATE"),IFERROR(INDEX(Setup!$C$21:$C$60,MATCH(UPPER(TRIM($F49))&"|"&UPPER(TRIM($G49)),Setup!$P$21:$P$60,0)),IFERROR(INDEX(Setup!$C$21:$C$60,MATCH(UPPER(TRIM($G49))&"|"&UPPER(TRIM($F49)),Setup!$P$21:$P$60,0)),"NO RATE")))) | K49: =IF(OR($G49="",$H49="",NOT(ISNUMBER($I49))),"",ROUND($H49*$I49*(1+IF($J49="",Setup!$B$16,$J49)),2)) | L49: =IF($K49="","",ROUND($K49*Setup!$B$13,2)) | M49: =IF($K49="","",$K49-$L49) | N49: =IF(OR($M49="",$D49=""),"",ROUND($M49*IFERROR(IF(VLOOKUP($D49,Setup!$A$76:$C$87,3,FALSE)="",Setup!$B$14,VLOOKUP($D49,Setup!$A$76:$C$87,3,FALSE)),Setup!$B$14),2)) | O49: =IF(OR($M49="",$E49=""),"",ROUND($M49*IFERROR(IF(VLOOKUP($E49,Setup!$A$76:$C$87,3,FALSE)="",Setup!$B$15,VLOOKUP($E49,Setup!$A$76:$C$87,3,FALSE)),Setup!$B$15),2)) | P49: 500 | Q49: 0 | R49: 6400 | S49: 620 | T49: 0 | U49: =IF($K49="","",SUM($R49:$T49)) | V49: =IF($K49="","",$M49-(N($N49)+N($O49)+IF($P49="",Setup!$B$17,$P49)+N($Q49))-N($U49)) | W49: Unpaid | Z49: =IF($A49="","",DATE(YEAR($A49),MONTH($A49),1))
I50: =IF($G50="","",IF($F50="",IFERROR(INDEX(Setup!$C$21:$C$60,MATCH("|"&UPPER(TRIM($G50)),Setup!$Q$21:$Q$60,0)),"NO RATE"),IFERROR(INDEX(Setup!$C$21:$C$60,MATCH(UPPER(TRIM($F50))&"|"&UPPER(TRIM($G50)),Setup!$P$21:$P$60,0)),IFERROR(INDEX(Setup!$C$21:$C$60,MATCH(UPPER(TRIM($G50))&"|"&UPPER(TRIM($F50)),Setup!$P$21:$P$60,0)),"NO RATE")))) | K50: =IF(OR($G50="",$H50="",NOT(ISNUMBER($I50))),"",ROUND($H50*$I50*(1+IF($J50="",Setup!$B$16,$J50)),2)) | L50: =IF($K50="","",ROUND($K50*Setup!$B$13,2)) | M50: =IF($K50="","",$K50-$L50) | N50: =IF(OR($M50="",$D50=""),"",ROUND($M50*IFERROR(IF(VLOOKUP($D50,Setup!$A$76:$C$87,3,FALSE)="",Setup!$B$14,VLOOKUP($D50,Setup!$A$76:$C$87,3,FALSE)),Setup!$B$14),2)) | O50: =IF(OR($M50="",$E50=""),"",ROUND($M50*IFERROR(IF(VLOOKUP($E50,Setup!$A$76:$C$87,3,FALSE)="",Setup!$B$15,VLOOKUP($E50,Setup!$A$76:$C$87,3,FALSE)),Setup!$B$15),2)) | U50: =IF($K50="","",SUM($R50:$T50)) | V50: =IF($K50="","",$M50-(N($N50)+N($O50)+IF($P50="",Setup!$B$17,$P50)+N($Q50))-N($U50)) | Z50: =IF($A50="","",DATE(YEAR($A50),MONTH($A50),1))
I51: =IF($G51="","",IF($F51="",IFERROR(INDEX(Setup!$C$21:$C$60,MATCH("|"&UPPER(TRIM($G51)),Setup!$Q$21:$Q$60,0)),"NO RATE"),IFERROR(INDEX(Setup!$C$21:$C$60,MATCH(UPPER(TRIM($F51))&"|"&UPPER(TRIM($G51)),Setup!$P$21:$P$60,0)),IFERROR(INDEX(Setup!$C$21:$C$60,MATCH(UPPER(TRIM($G51))&"|"&UPPER(TRIM($F51)),Setup!$P$21:$P$60,0)),"NO RATE")))) | K51: =IF(OR($G51="",$H51="",NOT(ISNUMBER($I51))),"",ROUND($H51*$I51*(1+IF($J51="",Setup!$B$16,$J51)),2)) | L51: =IF($K51="","",ROUND($K51*Setup!$B$13,2)) | M51: =IF($K51="","",$K51-$L51) | N51: =IF(OR($M51="",$D51=""),"",ROUND($M51*IFERROR(IF(VLOOKUP($D51,Setup!$A$76:$C$87,3,FALSE)="",Setup!$B$14,VLOOKUP($D51,Setup!$A$76:$C$87,3,FALSE)),Setup!$B$14),2)) | O51: =IF(OR($M51="",$E51=""),"",ROUND($M51*IFERROR(IF(VLOOKUP($E51,Setup!$A$76:$C$87,3,FALSE)="",Setup!$B$15,VLOOKUP($E51,Setup!$A$76:$C$87,3,FALSE)),Setup!$B$15),2)) | U51: =IF($K51="","",SUM($R51:$T51)) | V51: =IF($K51="","",$M51-(N($N51)+N($O51)+IF($P51="",Setup!$B$17,$P51)+N($Q51))-N($U51)) | Z51: =IF($A51="","",DATE(YEAR($A51),MONTH($A51),1))
I52: =IF($G52="","",IF($F52="",IFERROR(INDEX(Setup!$C$21:$C$60,MATCH("|"&UPPER(TRIM($G52)),Setup!$Q$21:$Q$60,0)),"NO RATE"),IFERROR(INDEX(Setup!$C$21:$C$60,MATCH(UPPER(TRIM($F52))&"|"&UPPER(TRIM($G52)),Setup!$P$21:$P$60,0)),IFERROR(INDEX(Setup!$C$21:$C$60,MATCH(UPPER(TRIM($G52))&"|"&UPPER(TRIM($F52)),Setup!$P$21:$P$60,0)),"NO RATE")))) | K52: =IF(OR($G52="",$H52="",NOT(ISNUMBER($I52))),"",ROUND($H52*$I52*(1+IF($J52="",Setup!$B$16,$J52)),2)) | L52: =IF($K52="","",ROUND($K52*Setup!$B$13,2)) | M52: =IF($K52="","",$K52-$L52) | N52: =IF(OR($M52="",$D52=""),"",ROUND($M52*IFERROR(IF(VLOOKUP($D52,Setup!$A$76:$C$87,3,FALSE)="",Setup!$B$14,VLOOKUP($D52,Setup!$A$76:$C$87,3,FALSE)),Setup!$B$14),2)) | O52: =IF(OR($M52="",$E52=""),"",ROUND($M52*IFERROR(IF(VLOOKUP($E52,Setup!$A$76:$C$87,3,FALSE)="",Setup!$B$15,VLOOKUP($E52,Setup!$A$76:$C$87,3,FALSE)),Setup!$B$15),2)) | U52: =IF($K52="","",SUM($R52:$T52)) | V52: =IF($K52="","",$M52-(N($N52)+N($O52)+IF($P52="",Setup!$B$17,$P52)+N($Q52))-N($U52)) | Z52: =IF($A52="","",DATE(YEAR($A52),MONTH($A52),1))
I53: =IF($G53="","",IF($F53="",IFERROR(INDEX(Setup!$C$21:$C$60,MATCH("|"&UPPER(TRIM($G53)),Setup!$Q$21:$Q$60,0)),"NO RATE"),IFERROR(INDEX(Setup!$C$21:$C$60,MATCH(UPPER(TRIM($F53))&"|"&UPPER(TRIM($G53)),Setup!$P$21:$P$60,0)),IFERROR(INDEX(Setup!$C$21:$C$60,MATCH(UPPER(TRIM($G53))&"|"&UPPER(TRIM($F53)),Setup!$P$21:$P$60,0)),"NO RATE")))) | K53: =IF(OR($G53="",$H53="",NOT(ISNUMBER($I53))),"",ROUND($H53*$I53*(1+IF($J53="",Setup!$B$16,$J53)),2)) | L53: =IF($K53="","",ROUND($K53*Setup!$B$13,2)) | M53: =IF($K53="","",$K53-$L53) | N53: =IF(OR($M53="",$D53=""),"",ROUND($M53*IFERROR(IF(VLOOKUP($D53,Setup!$A$76:$C$87,3,FALSE)="",Setup!$B$14,VLOOKUP($D53,Setup!$A$76:$C$87,3,FALSE)),Setup!$B$14),2)) | O53: =IF(OR($M53="",$E53=""),"",ROUND($M53*IFERROR(IF(VLOOKUP($E53,Setup!$A$76:$C$87,3,FALSE)="",Setup!$B$15,VLOOKUP($E53,Setup!$A$76:$C$87,3,FALSE)),Setup!$B$15),2)) | U53: =IF($K53="","",SUM($R53:$T53)) | V53: =IF($K53="","",$M53-(N($N53)+N($O53)+IF($P53="",Setup!$B$17,$P53)+N($Q53))-N($U53)) | Z53: =IF($A53="","",DATE(YEAR($A53),MONTH($A53),1))
I54: =IF($G54="","",IF($F54="",IFERROR(INDEX(Setup!$C$21:$C$60,MATCH("|"&UPPER(TRIM($G54)),Setup!$Q$21:$Q$60,0)),"NO RATE"),IFERROR(INDEX(Setup!$C$21:$C$60,MATCH(UPPER(TRIM($F54))&"|"&UPPER(TRIM($G54)),Setup!$P$21:$P$60,0)),IFERROR(INDEX(Setup!$C$21:$C$60,MATCH(UPPER(TRIM($G54))&"|"&UPPER(TRIM($F54)),Setup!$P$21:$P$60,0)),"NO RATE")))) | K54: =IF(OR($G54="",$H54="",NOT(ISNUMBER($I54))),"",ROUND($H54*$I54*(1+IF($J54="",Setup!$B$16,$J54)),2)) | L54: =IF($K54="","",ROUND($K54*Setup!$B$13,2)) | M54: =IF($K54="","",$K54-$L54) | N54: =IF(OR($M54="",$D54=""),"",ROUND($M54*IFERROR(IF(VLOOKUP($D54,Setup!$A$76:$C$87,3,FALSE)="",Setup!$B$14,VLOOKUP($D54,Setup!$A$76:$C$87,3,FALSE)),Setup!$B$14),2)) | O54: =IF(OR($M54="",$E54=""),"",ROUND($M54*IFERROR(IF(VLOOKUP($E54,Setup!$A$76:$C$87,3,FALSE)="",Setup!$B$15,VLOOKUP($E54,Setup!$A$76:$C$87,3,FALSE)),Setup!$B$15),2)) | U54: =IF($K54="","",SUM($R54:$T54)) | V54: =IF($K54="","",$M54-(N($N54)+N($O54)+IF($P54="",Setup!$B$17,$P54)+N($Q54))-N($U54)) | Z54: =IF($A54="","",DATE(YEAR($A54),MONTH($A54),1))
I55: =IF($G55="","",IF($F55="",IFERROR(INDEX(Setup!$C$21:$C$60,MATCH("|"&UPPER(TRIM($G55)),Setup!$Q$21:$Q$60,0)),"NO RATE"),IFERROR(INDEX(Setup!$C$21:$C$60,MATCH(UPPER(TRIM($F55))&"|"&UPPER(TRIM($G55)),Setup!$P$21:$P$60,0)),IFERROR(INDEX(Setup!$C$21:$C$60,MATCH(UPPER(TRIM($G55))&"|"&UPPER(TRIM($F55)),Setup!$P$21:$P$60,0)),"NO RATE")))) | K55: =IF(OR($G55="",$H55="",NOT(ISNUMBER($I55))),"",ROUND($H55*$I55*(1+IF($J55="",Setup!$B$16,$J55)),2)) | L55: =IF($K55="","",ROUND($K55*Setup!$B$13,2)) | M55: =IF($K55="","",$K55-$L55) | N55: =IF(OR($M55="",$D55=""),"",ROUND($M55*IFERROR(IF(VLOOKUP($D55,Setup!$A$76:$C$87,3,FALSE)="",Setup!$B$14,VLOOKUP($D55,Setup!$A$76:$C$87,3,FALSE)),Setup!$B$14),2)) | O55: =IF(OR($M55="",$E55=""),"",ROUND($M55*IFERROR(IF(VLOOKUP($E55,Setup!$A$76:$C$87,3,FALSE)="",Setup!$B$15,VLOOKUP($E55,Setup!$A$76:$C$87,3,FALSE)),Setup!$B$15),2)) | U55: =IF($K55="","",SUM($R55:$T55)) | V55: =IF($K55="","",$M55-(N($N55)+N($O55)+IF($P55="",Setup!$B$17,$P55)+N($Q55))-N($U55)) | Z55: =IF($A55="","",DATE(YEAR($A55),MONTH($A55),1))
I56: =IF($G56="","",IF($F56="",IFERROR(INDEX(Setup!$C$21:$C$60,MATCH("|"&UPPER(TRIM($G56)),Setup!$Q$21:$Q$60,0)),"NO RATE"),IFERROR(INDEX(Setup!$C$21:$C$60,MATCH(UPPER(TRIM($F56))&"|"&UPPER(TRIM($G56)),Setup!$P$21:$P$60,0)),IFERROR(INDEX(Setup!$C$21:$C$60,MATCH(UPPER(TRIM($G56))&"|"&UPPER(TRIM($F56)),Setup!$P$21:$P$60,0)),"NO RATE")))) | K56: =IF(OR($G56="",$H56="",NOT(ISNUMBER($I56))),"",ROUND($H56*$I56*(1+IF($J56="",Setup!$B$16,$J56)),2)) | L56: =IF($K56="","",ROUND($K56*Setup!$B$13,2)) | M56: =IF($K56="","",$K56-$L56) | N56: =IF(OR($M56="",$D56=""),"",ROUND($M56*IFERROR(IF(VLOOKUP($D56,Setup!$A$76:$C$87,3,FALSE)="",Setup!$B$14,VLOOKUP($D56,Setup!$A$76:$C$87,3,FALSE)),Setup!$B$14),2)) | O56: =IF(OR($M56="",$E56=""),"",ROUND($M56*IFERROR(IF(VLOOKUP($E56,Setup!$A$76:$C$87,3,FALSE)="",Setup!$B$15,VLOOKUP($E56,Setup!$A$76:$C$87,3,FALSE)),Setup!$B$15),2)) | U56: =IF($K56="","",SUM($R56:$T56)) | V56: =IF($K56="","",$M56-(N($N56)+N($O56)+IF($P56="",Setup!$B$17,$P56)+N($Q56))-N($U56)) | Z56: =IF($A56="","",DATE(YEAR($A56),MONTH($A56),1))
I57: =IF($G57="","",IF($F57="",IFERROR(INDEX(Setup!$C$21:$C$60,MATCH("|"&UPPER(TRIM($G57)),Setup!$Q$21:$Q$60,0)),"NO RATE"),IFERROR(INDEX(Setup!$C$21:$C$60,MATCH(UPPER(TRIM($F57))&"|"&UPPER(TRIM($G57)),Setup!$P$21:$P$60,0)),IFERROR(INDEX(Setup!$C$21:$C$60,MATCH(UPPER(TRIM($G57))&"|"&UPPER(TRIM($F57)),Setup!$P$21:$P$60,0)),"NO RATE")))) | K57: =IF(OR($G57="",$H57="",NOT(ISNUMBER($I57))),"",ROUND($H57*$I57*(1+IF($J57="",Setup!$B$16,$J57)),2)) | L57: =IF($K57="","",ROUND($K57*Setup!$B$13,2)) | M57: =IF($K57="","",$K57-$L57) | N57: =IF(OR($M57="",$D57=""),"",ROUND($M57*IFERROR(IF(VLOOKUP($D57,Setup!$A$76:$C$87,3,FALSE)="",Setup!$B$14,VLOOKUP($D57,Setup!$A$76:$C$87,3,FALSE)),Setup!$B$14),2)) | O57: =IF(OR($M57="",$E57=""),"",ROUND($M57*IFERROR(IF(VLOOKUP($E57,Setup!$A$76:$C$87,3,FALSE)="",Setup!$B$15,VLOOKUP($E57,Setup!$A$76:$C$87,3,FALSE)),Setup!$B$15),2)) | U57: =IF($K57="","",SUM($R57:$T57)) | V57: =IF($K57="","",$M57-(N($N57)+N($O57)+IF($P57="",Setup!$B$17,$P57)+N($Q57))-N($U57)) | Z57: =IF($A57="","",DATE(YEAR($A57),MONTH($A57),1))
I58: =IF($G58="","",IF($F58="",IFERROR(INDEX(Setup!$C$21:$C$60,MATCH("|"&UPPER(TRIM($G58)),Setup!$Q$21:$Q$60,0)),"NO RATE"),IFERROR(INDEX(Setup!$C$21:$C$60,MATCH(UPPER(TRIM($F58))&"|"&UPPER(TRIM($G58)),Setup!$P$21:$P$60,0)),IFERROR(INDEX(Setup!$C$21:$C$60,MATCH(UPPER(TRIM($G58))&"|"&UPPER(TRIM($F58)),Setup!$P$21:$P$60,0)),"NO RATE")))) | K58: =IF(OR($G58="",$H58="",NOT(ISNUMBER($I58))),"",ROUND($H58*$I58*(1+IF($J58="",Setup!$B$16,$J58)),2)) | L58: =IF($K58="","",ROUND($K58*Setup!$B$13,2)) | M58: =IF($K58="","",$K58-$L58) | N58: =IF(OR($M58="",$D58=""),"",ROUND($M58*IFERROR(IF(VLOOKUP($D58,Setup!$A$76:$C$87,3,FALSE)="",Setup!$B$14,VLOOKUP($D58,Setup!$A$76:$C$87,3,FALSE)),Setup!$B$14),2)) | O58: =IF(OR($M58="",$E58=""),"",ROUND($M58*IFERROR(IF(VLOOKUP($E58,Setup!$A$76:$C$87,3,FALSE)="",Setup!$B$15,VLOOKUP($E58,Setup!$A$76:$C$87,3,FALSE)),Setup!$B$15),2)) | U58: =IF($K58="","",SUM($R58:$T58)) | V58: =IF($K58="","",$M58-(N($N58)+N($O58)+IF($P58="",Setup!$B$17,$P58)+N($Q58))-N($U58)) | Z58: =IF($A58="","",DATE(YEAR($A58),MONTH($A58),1))
I59: =IF($G59="","",IF($F59="",IFERROR(INDEX(Setup!$C$21:$C$60,MATCH("|"&UPPER(TRIM($G59)),Setup!$Q$21:$Q$60,0)),"NO RATE"),IFERROR(INDEX(Setup!$C$21:$C$60,MATCH(UPPER(TRIM($F59))&"|"&UPPER(TRIM($G59)),Setup!$P$21:$P$60,0)),IFERROR(INDEX(Setup!$C$21:$C$60,MATCH(UPPER(TRIM($G59))&"|"&UPPER(TRIM($F59)),Setup!$P$21:$P$60,0)),"NO RATE")))) | K59: =IF(OR($G59="",$H59="",NOT(ISNUMBER($I59))),"",ROUND($H59*$I59*(1+IF($J59="",Setup!$B$16,$J59)),2)) | L59: =IF($K59="","",ROUND($K59*Setup!$B$13,2)) | M59: =IF($K59="","",$K59-$L59) | N59: =IF(OR($M59="",$D59=""),"",ROUND($M59*IFERROR(IF(VLOOKUP($D59,Setup!$A$76:$C$87,3,FALSE)="",Setup!$B$14,VLOOKUP($D59,Setup!$A$76:$C$87,3,FALSE)),Setup!$B$14),2)) | O59: =IF(OR($M59="",$E59=""),"",ROUND($M59*IFERROR(IF(VLOOKUP($E59,Setup!$A$76:$C$87,3,FALSE)="",Setup!$B$15,VLOOKUP($E59,Setup!$A$76:$C$87,3,FALSE)),Setup!$B$15),2)) | U59: =IF($K59="","",SUM($R59:$T59)) | V59: =IF($K59="","",$M59-(N($N59)+N($O59)+IF($P59="",Setup!$B$17,$P59)+N($Q59))-N($U59)) | Z59: =IF($A59="","",DATE(YEAR($A59),MONTH($A59),1))
I60: =IF($G60="","",IF($F60="",IFERROR(INDEX(Setup!$C$21:$C$60,MATCH("|"&UPPER(TRIM($G60)),Setup!$Q$21:$Q$60,0)),"NO RATE"),IFERROR(INDEX(Setup!$C$21:$C$60,MATCH(UPPER(TRIM($F60))&"|"&UPPER(TRIM($G60)),Setup!$P$21:$P$60,0)),IFERROR(INDEX(Setup!$C$21:$C$60,MATCH(UPPER(TRIM($G60))&"|"&UPPER(TRIM($F60)),Setup!$P$21:$P$60,0)),"NO RATE")))) | K60: =IF(OR($G60="",$H60="",NOT(ISNUMBER($I60))),"",ROUND($H60*$I60*(1+IF($J60="",Setup!$B$16,$J60)),2)) | L60: =IF($K60="","",ROUND($K60*Setup!$B$13,2)) | M60: =IF($K60="","",$K60-$L60) | N60: =IF(OR($M60="",$D60=""),"",ROUND($M60*IFERROR(IF(VLOOKUP($D60,Setup!$A$76:$C$87,3,FALSE)="",Setup!$B$14,VLOOKUP($D60,Setup!$A$76:$C$87,3,FALSE)),Setup!$B$14),2)) | O60: =IF(OR($M60="",$E60=""),"",ROUND($M60*IFERROR(IF(VLOOKUP($E60,Setup!$A$76:$C$87,3,FALSE)="",Setup!$B$15,VLOOKUP($E60,Setup!$A$76:$C$87,3,FALSE)),Setup!$B$15),2)) | U60: =IF($K60="","",SUM($R60:$T60)) | V60: =IF($K60="","",$M60-(N($N60)+N($O60)+IF($P60="",Setup!$B$17,$P60)+N($Q60))-N($U60)) | Z60: =IF($A60="","",DATE(YEAR($A60),MONTH($A60),1))
I61: =IF($G61="","",IF($F61="",IFERROR(INDEX(Setup!$C$21:$C$60,MATCH("|"&UPPER(TRIM($G61)),Setup!$Q$21:$Q$60,0)),"NO RATE"),IFERROR(INDEX(Setup!$C$21:$C$60,MATCH(UPPER(TRIM($F61))&"|"&UPPER(TRIM($G61)),Setup!$P$21:$P$60,0)),IFERROR(INDEX(Setup!$C$21:$C$60,MATCH(UPPER(TRIM($G61))&"|"&UPPER(TRIM($F61)),Setup!$P$21:$P$60,0)),"NO RATE")))) | K61: =IF(OR($G61="",$H61="",NOT(ISNUMBER($I61))),"",ROUND($H61*$I61*(1+IF($J61="",Setup!$B$16,$J61)),2)) | L61: =IF($K61="","",ROUND($K61*Setup!$B$13,2)) | M61: =IF($K61="","",$K61-$L61) | N61: =IF(OR($M61="",$D61=""),"",ROUND($M61*IFERROR(IF(VLOOKUP($D61,Setup!$A$76:$C$87,3,FALSE)="",Setup!$B$14,VLOOKUP($D61,Setup!$A$76:$C$87,3,FALSE)),Setup!$B$14),2)) | O61: =IF(OR($M61="",$E61=""),"",ROUND($M61*IFERROR(IF(VLOOKUP($E61,Setup!$A$76:$C$87,3,FALSE)="",Setup!$B$15,VLOOKUP($E61,Setup!$A$76:$C$87,3,FALSE)),Setup!$B$15),2)) | U61: =IF($K61="","",SUM($R61:$T61)) | V61: =IF($K61="","",$M61-(N($N61)+N($O61)+IF($P61="",Setup!$B$17,$P61)+N($Q61))-N($U61)) | Z61: =IF($A61="","",DATE(YEAR($A61),MONTH($A61),1))
... I1004: =IF($G1004="","",IF($F1004="",IFERROR(INDEX(Setup!$C$21:$C$60,MATCH("|"&UPPER(TRIM($G1004)),Setup!$Q$21:$Q$60,0)),"NO RATE"),IFERROR(INDEX(Setup!$C$21:$C$60,MATCH(UPPER(TRIM($F1004))&"|"&UPPER(TRIM($G1004)),Setup!$P$21:$P$60,0)),IFERROR(INDEX(Setup!$C$21:$C$60,MATCH(UPPER(TRIM($G1004))&"|"&UPPER(TRIM($F1004)),Setup!$P$21:$P$60,0)),"NO RATE")))) | K1004: =IF(OR($G1004="",$H1004="",NOT(ISNUMBER($I1004))),"",ROUND($H1004*$I1004*(1+IF($J1004="",Setup!$B$16,$J1004)),2)) | L1004: =IF($K1004="","",ROUND($K1004*Setup!$B$13,2)) | M1004: =IF($K1004="","",$K1004-$L1004) | N1004: =IF(OR($M1004="",$D1004=""),"",ROUND($M1004*IFERROR(IF(VLOOKUP($D1004,Setup!$A$76:$C$87,3,FALSE)="",Setup!$B$14,VLOOKUP($D1004,Setup!$A$76:$C$87,3,FALSE)),Setup!$B$14),2)) | O1004: =IF(OR($M1004="",$E1004=""),"",ROUND($M1004*IFERROR(IF(VLOOKUP($E1004,Setup!$A$76:$C$87,3,FALSE)="",Setup!$B$15,VLOOKUP($E1004,Setup!$A$76:$C$87,3,FALSE)),Setup!$B$15),2)) | U1004: =IF($K1004="","",SUM($R1004:$T1004)) | V1004: =IF($K1004="","",$M1004-(N($N1004)+N($O1004)+IF($P1004="",Setup!$B$17,$P1004)+N($Q1004))-N($U1004)) | Z1004: =IF($A1004="","",DATE(YEAR($A1004),MONTH($A1004),1))

Sheet Expenses
A1: 🚚 EXPENSES — one row per receipt (fuel, repairs, toll, loans, rent, cash advances)
A2: Do NOT log crew pay here — the Payroll sheet computes it from Trips. Cash advances and payroll releases are logged here so the Payroll sheet can clear them.
A3: ALL-TIME TOTALS → | B3: =COUNT(5:1004)&" entries logged" | F3: =SUM(F5:F1004)
A4: DATE | B4: EXPENSE TYPE | C4: DESCRIPTION | D4: TRUCK | E4: PAID TO / LENDER | F4: AMOUNT | G4: PAYMENT METHOD | H4: RECEIPT? | I4: COST GROUP
A5: 46239 | B5: Repairs & Maintenance | C5: PMS + brake adjustment | D5: TRUCK 1 | E5: Casa Mechanic | F5: 8500 | G5: Cash | H5: Y | I5: =IF($B5="","",IFERROR(INDEX(Setup!$B$99:$B$128,MATCH($B5,Setup!$A$99:$A$128,0)),"CHECK TYPE")) | J5: =IF($A5="","",DATE(YEAR($A5),MONTH($A5),1))
A6: 46246 | B6: Insurance | C6: Comprehensive premium (quarterly) | D6: TRUCK 1 | E6: Fortune Insurance | F6: 18500 | G6: Bank Transfer | H6: Y | I6: =IF($B6="","",IFERROR(INDEX(Setup!$B$99:$B$128,MATCH($B6,Setup!$A$99:$A$128,0)),"CHECK TYPE")) | J6: =IF($A6="","",DATE(YEAR($A6),MONTH($A6),1))
A7: 46265 | B7: Loan Payment | C7: August amortisation | D7: TRUCK 1 | E7: BDO Leasing | F7: 32000 | G7: Bank Transfer | H7: Y | I7: =IF($B7="","",IFERROR(INDEX(Setup!$B$99:$B$128,MATCH($B7,Setup!$A$99:$A$128,0)),"CHECK TYPE")) | J7: =IF($A7="","",DATE(YEAR($A7),MONTH($A7),1))
A8: 46265 | B8: Loan Payment | C8: August amortisation | D8: TRUCK 1 | E8: Security Bank | F8: 18500 | G8: Bank Transfer | H8: Y | I8: =IF($B8="","",IFERROR(INDEX(Setup!$B$99:$B$128,MATCH($B8,Setup!$A$99:$A$128,0)),"CHECK TYPE")) | J8: =IF($A8="","",DATE(YEAR($A8),MONTH($A8),1))
A9: 46265 | B9: Loan Payment | C9: August amortisation | D9: TRUCK 1 | E9: Private Lender | F9: 12500 | G9: GCash | H9: N | I9: =IF($B9="","",IFERROR(INDEX(Setup!$B$99:$B$128,MATCH($B9,Setup!$A$99:$A$128,0)),"CHECK TYPE")) | J9: =IF($A9="","",DATE(YEAR($A9),MONTH($A9),1))
A10: 46265 | B10: Rent | C10: Yard rent | E10: Mrs. Lim | F10: 5000 | G10: Cash | H10: N | I10: =IF($B10="","",IFERROR(INDEX(Setup!$B$99:$B$128,MATCH($B10,Setup!$A$99:$A$128,0)),"CHECK TYPE")) | J10: =IF($A10="","",DATE(YEAR($A10),MONTH($A10),1))
A11: 46265 | B11: Payroll Payout | C11: August release | E11: R. Dela Cruz | F11: 13000 | G11: Cash | H11: N | I11: =IF($B11="","",IFERROR(INDEX(Setup!$B$99:$B$128,MATCH($B11,Setup!$A$99:$A$128,0)),"CHECK TYPE")) | J11: =IF($A11="","",DATE(YEAR($A11),MONTH($A11),1))
A12: 46265 | B12: Payroll Payout | C12: August release | E12: M. Reyes | F12: 13000 | G12: Cash | H12: N | I12: =IF($B12="","",IFERROR(INDEX(Setup!$B$99:$B$128,MATCH($B12,Setup!$A$99:$A$128,0)),"CHECK TYPE")) | J12: =IF($A12="","",DATE(YEAR($A12),MONTH($A12),1))
A13: 46269 | B13: Tires & Batteries | C13: 2 pcs rear tires | D13: TRUCK 1 | E13: Goodyear Dealer | F13: 21000 | G13: Bank Transfer | H13: Y | I13: =IF($B13="","",IFERROR(INDEX(Setup!$B$99:$B$128,MATCH($B13,Setup!$A$99:$A$128,0)),"CHECK TYPE")) | J13: =IF($A13="","",DATE(YEAR($A13),MONTH($A13),1))
A14: 46274 | B14: Repairs & Maintenance | C14: Clutch lining + labour | D14: TRUCK 1 | E14: Diesel Works | F14: 6200 | G14: Cash | H14: Y | I14: =IF($B14="","",IFERROR(INDEX(Setup!$B$99:$B$128,MATCH($B14,Setup!$A$99:$A$128,0)),"CHECK TYPE")) | J14: =IF($A14="","",DATE(YEAR($A14),MONTH($A14),1))
A15: 46275 | B15: LTO Registration | C15: Registration + emission test | D15: TRUCK 1 | E15: LTO | F15: 4200 | G15: Cash | H15: Y | I15: =IF($B15="","",IFERROR(INDEX(Setup!$B$99:$B$128,MATCH($B15,Setup!$A$99:$A$128,0)),"CHECK TYPE")) | J15: =IF($A15="","",DATE(YEAR($A15),MONTH($A15),1))
A16: 46280 | B16: Cash Advance | C16: Advance — family emergency | E16: R. Dela Cruz | F16: 5000 | G16: Cash | H16: N | I16: =IF($B16="","",IFERROR(INDEX(Setup!$B$99:$B$128,MATCH($B16,Setup!$A$99:$A$128,0)),"CHECK TYPE")) | J16: =IF($A16="","",DATE(YEAR($A16),MONTH($A16),1))
A17: 46285 | B17: Office / Staff Salary | C17: Dispatcher salary | E17: L. Garcia | F17: 12000 | G17: Cash | H17: N | I17: =IF($B17="","",IFERROR(INDEX(Setup!$B$99:$B$128,MATCH($B17,Setup!$A$99:$A$128,0)),"CHECK TYPE")) | J17: =IF($A17="","",DATE(YEAR($A17),MONTH($A17),1))
A18: 46295 | B18: Loan Payment | C18: September amortisation | D18: TRUCK 1 | E18: BDO Leasing | F18: 32000 | G18: Bank Transfer | H18: Y | I18: =IF($B18="","",IFERROR(INDEX(Setup!$B$99:$B$128,MATCH($B18,Setup!$A$99:$A$128,0)),"CHECK TYPE")) | J18: =IF($A18="","",DATE(YEAR($A18),MONTH($A18),1))
A19: 46295 | B19: Loan Payment | C19: September amortisation | D19: TRUCK 1 | E19: Security Bank | F19: 18500 | G19: Bank Transfer | H19: Y | I19: =IF($B19="","",IFERROR(INDEX(Setup!$B$99:$B$128,MATCH($B19,Setup!$A$99:$A$128,0)),"CHECK TYPE")) | J19: =IF($A19="","",DATE(YEAR($A19),MONTH($A19),1))
A20: 46295 | B20: Loan Payment | C20: September amortisation | D20: TRUCK 1 | E20: Private Lender | F20: 12500 | G20: GCash | H20: N | I20: =IF($B20="","",IFERROR(INDEX(Setup!$B$99:$B$128,MATCH($B20,Setup!$A$99:$A$128,0)),"CHECK TYPE")) | J20: =IF($A20="","",DATE(YEAR($A20),MONTH($A20),1))
A21: 46295 | B21: Rent | C21: Yard rent | E21: Mrs. Lim | F21: 5000 | G21: Cash | H21: N | I21: =IF($B21="","",IFERROR(INDEX(Setup!$B$99:$B$128,MATCH($B21,Setup!$A$99:$A$128,0)),"CHECK TYPE")) | J21: =IF($A21="","",DATE(YEAR($A21),MONTH($A21),1))
A22: 46295 | B22: Utilities | C22: Water + internet | E22: Meralco / PLDT | F22: 2800 | G22: GCash | H22: Y | I22: =IF($B22="","",IFERROR(INDEX(Setup!$B$99:$B$128,MATCH($B22,Setup!$A$99:$A$128,0)),"CHECK TYPE")) | J22: =IF($A22="","",DATE(YEAR($A22),MONTH($A22),1))
A23: 46295 | B23: Truck Washing | C23: Wash + greasing | D23: TRUCK 1 | E23: Jomar Carwash | F23: 700 | G23: Cash | H23: N | I23: =IF($B23="","",IFERROR(INDEX(Setup!$B$99:$B$128,MATCH($B23,Setup!$A$99:$A$128,0)),"CHECK TYPE")) | J23: =IF($A23="","",DATE(YEAR($A23),MONTH($A23),1))
A24: 46298 | B24: Cash Advance | C24: Trip pocket money | E24: J. Santos | F24: 3000 | G24: Cash | H24: N | I24: =IF($B24="","",IFERROR(INDEX(Setup!$B$99:$B$128,MATCH($B24,Setup!$A$99:$A$128,0)),"CHECK TYPE")) | J24: =IF($A24="","",DATE(YEAR($A24),MONTH($A24),1))
A25: 46303 | B25: Spare Parts & Lubricants | C25: Oil filters + coolant | D25: TRUCK 1 | E25: Truck Parts Center | F25: 3900 | G25: Cash | H25: Y | I25: =IF($B25="","",IFERROR(INDEX(Setup!$B$99:$B$128,MATCH($B25,Setup!$A$99:$A$128,0)),"CHECK TYPE")) | J25: =IF($A25="","",DATE(YEAR($A25),MONTH($A25),1))
A26: 46305 | B26: Truck Washing | C26: Wash + greasing | D26: TRUCK 1 | E26: Jomar Carwash | F26: 700 | G26: Cash | H26: N | I26: =IF($B26="","",IFERROR(INDEX(Setup!$B$99:$B$128,MATCH($B26,Setup!$A$99:$A$128,0)),"CHECK TYPE")) | J26: =IF($A26="","",DATE(YEAR($A26),MONTH($A26),1))
A27: 46307 | B27: Owner's Draw | C27: Owner's personal withdrawal | E27: Owner | F27: 15000 | G27: Cash | H27: N | I27: =IF($B27="","",IFERROR(INDEX(Setup!$B$99:$B$128,MATCH($B27,Setup!$A$99:$A$128,0)),"CHECK TYPE")) | J27: =IF($A27="","",DATE(YEAR($A27),MONTH($A27),1))
A28: 46310 | B28: Loan Payment | C28: October amortisation | D28: TRUCK 1 | E28: BDO Leasing | F28: 32000 | G28: Bank Transfer | H28: Y | I28: =IF($B28="","",IFERROR(INDEX(Setup!$B$99:$B$128,MATCH($B28,Setup!$A$99:$A$128,0)),"CHECK TYPE")) | J28: =IF($A28="","",DATE(YEAR($A28),MONTH($A28),1))
A29: 46310 | B29: Loan Payment | C29: October amortisation | D29: TRUCK 1 | E29: Security Bank | F29: 18500 | G29: Bank Transfer | H29: Y | I29: =IF($B29="","",IFERROR(INDEX(Setup!$B$99:$B$128,MATCH($B29,Setup!$A$99:$A$128,0)),"CHECK TYPE")) | J29: =IF($A29="","",DATE(YEAR($A29),MONTH($A29),1))
A30: 46311 | B30: Rent | C30: Yard rent | E30: Mrs. Lim | F30: 5000 | G30: Cash | H30: N | I30: =IF($B30="","",IFERROR(INDEX(Setup!$B$99:$B$128,MATCH($B30,Setup!$A$99:$A$128,0)),"CHECK TYPE")) | J30: =IF($A30="","",DATE(YEAR($A30),MONTH($A30),1))
A31: 46312 | B31: Utilities | C31: Water + internet | E31: Meralco / PLDT | F31: 2800 | G31: GCash | H31: Y | I31: =IF($B31="","",IFERROR(INDEX(Setup!$B$99:$B$128,MATCH($B31,Setup!$A$99:$A$128,0)),"CHECK TYPE")) | J31: =IF($A31="","",DATE(YEAR($A31),MONTH($A31),1))
A32: 46314 | B32: Payroll Payout | C32: Mid-month release | E32: R. Dela Cruz | F32: 10000 | G32: GCash | H32: N | I32: =IF($B32="","",IFERROR(INDEX(Setup!$B$99:$B$128,MATCH($B32,Setup!$A$99:$A$128,0)),"CHECK TYPE")) | J32: =IF($A32="","",DATE(YEAR($A32),MONTH($A32),1))
A33: 46315 | B33: Bank Charges | C33: InstaPay transfers | E33: BDO | F33: 350 | G33: Bank Transfer | H33: Y | I33: =IF($B33="","",IFERROR(INDEX(Setup!$B$99:$B$128,MATCH($B33,Setup!$A$99:$A$128,0)),"CHECK TYPE")) | J33: =IF($A33="","",DATE(YEAR($A33),MONTH($A33),1))
I34: =IF($B34="","",IFERROR(INDEX(Setup!$B$99:$B$128,MATCH($B34,Setup!$A$99:$A$128,0)),"CHECK TYPE")) | J34: =IF($A34="","",DATE(YEAR($A34),MONTH($A34),1))
I35: =IF($B35="","",IFERROR(INDEX(Setup!$B$99:$B$128,MATCH($B35,Setup!$A$99:$A$128,0)),"CHECK TYPE")) | J35: =IF($A35="","",DATE(YEAR($A35),MONTH($A35),1))
I36: =IF($B36="","",IFERROR(INDEX(Setup!$B$99:$B$128,MATCH($B36,Setup!$A$99:$A$128,0)),"CHECK TYPE")) | J36: =IF($A36="","",DATE(YEAR($A36),MONTH($A36),1))
I37: =IF($B37="","",IFERROR(INDEX(Setup!$B$99:$B$128,MATCH($B37,Setup!$A$99:$A$128,0)),"CHECK TYPE")) | J37: =IF($A37="","",DATE(YEAR($A37),MONTH($A37),1))
I38: =IF($B38="","",IFERROR(INDEX(Setup!$B$99:$B$128,MATCH($B38,Setup!$A$99:$A$128,0)),"CHECK TYPE")) | J38: =IF($A38="","",DATE(YEAR($A38),MONTH($A38),1))
I39: =IF($B39="","",IFERROR(INDEX(Setup!$B$99:$B$128,MATCH($B39,Setup!$A$99:$A$128,0)),"CHECK TYPE")) | J39: =IF($A39="","",DATE(YEAR($A39),MONTH($A39),1))
I40: =IF($B40="","",IFERROR(INDEX(Setup!$B$99:$B$128,MATCH($B40,Setup!$A$99:$A$128,0)),"CHECK TYPE")) | J40: =IF($A40="","",DATE(YEAR($A40),MONTH($A40),1))
I41: =IF($B41="","",IFERROR(INDEX(Setup!$B$99:$B$128,MATCH($B41,Setup!$A$99:$A$128,0)),"CHECK TYPE")) | J41: =IF($A41="","",DATE(YEAR($A41),MONTH($A41),1))
I42: =IF($B42="","",IFERROR(INDEX(Setup!$B$99:$B$128,MATCH($B42,Setup!$A$99:$A$128,0)),"CHECK TYPE")) | J42: =IF($A42="","",DATE(YEAR($A42),MONTH($A42),1))
I43: =IF($B43="","",IFERROR(INDEX(Setup!$B$99:$B$128,MATCH($B43,Setup!$A$99:$A$128,0)),"CHECK TYPE")) | J43: =IF($A43="","",DATE(YEAR($A43),MONTH($A43),1))
I44: =IF($B44="","",IFERROR(INDEX(Setup!$B$99:$B$128,MATCH($B44,Setup!$A$99:$A$128,0)),"CHECK TYPE")) | J44: =IF($A44="","",DATE(YEAR($A44),MONTH($A44),1))
I45: =IF($B45="","",IFERROR(INDEX(Setup!$B$99:$B$128,MATCH($B45,Setup!$A$99:$A$128,0)),"CHECK TYPE")) | J45: =IF($A45="","",DATE(YEAR($A45),MONTH($A45),1))
... I1004: =IF($B1004="","",IFERROR(INDEX(Setup!$B$99:$B$128,MATCH($B1004,Setup!$A$99:$A$128,0)),"CHECK TYPE")) | J1004: =IF($A1004="","",DATE(YEAR($A1004),MONTH($A1004),1))

Sheet Payroll
A1: 🚚 PAYROLL — automatic, per month, per crew member
A2: Nothing to type here. Salary is computed from the driver/helper share on every trip; cash advances & payouts are picked up from the Expenses sheet.
A4: CREW NAME | B4: ROLE | C4: TRIPS | D4: GROSS FEE HANDLED | E4: SHARE EARNED | F4: ALLOWANCE | G4: REIMBURSED | H4: TOTAL EARNED | I4: CASH ADVANCE | J4: PAYOUT RELEASED | K4: BALANCE (to pay / owes) | L4: STATUS
A5: JANUARY 2026 · crew earnings & settlement
A6: =IF(Setup!$A76="","",Setup!$A76) | B6: =IF($A6="","",Setup!$B76) | C6: =IF($A6="","",IF(COUNTIFS(Trips!$Z5:$Z1004,$R6,Trips!$D5:$D1004,$A6)+COUNTIFS(Trips!$Z5:$Z1004,$R6,Trips!$E5:$E1004,$A6)=0,"",COUNTIFS(Trips!$Z5:$Z1004,$R6,Trips!$D5:$D1004,$A6)+COUNTIFS(Trips!$Z5:$Z1004,$R6,Trips!$E5:$E1004,$A6))) | D6: =IF($C6="","",SUMIFS(Trips!$K5:$K1004,Trips!$Z5:$Z1004,$R6,Trips!$D5:$D1004,$A6)+SUMIFS(Trips!$K5:$K1004,Trips!$Z5:$Z1004,$R6,Trips!$E5:$E1004,$A6)) | E6: =IF($C6="","",SUMIFS(Trips!$N5:$N1004,Trips!$Z5:$Z1004,$R6,Trips!$D5:$D1004,$A6)+SUMIFS(Trips!$O5:$O1004,Trips!$Z5:$Z1004,$R6,Trips!$E5:$E1004,$A6)) | F6: =IF($C6="","",SUMIFS(Trips!$P5:$P1004,Trips!$Z5:$Z1004,$R6,Trips!$D5:$D1004,$A6)) | G6: =IF($C6="","",SUMIFS(Trips!$Q5:$Q1004,Trips!$Z5:$Z1004,$R6,Trips!$D5:$D1004,$A6)) | H6: =IF(AND($C6="",$I6="",$J6=""),"",N($E6)+N($F6)+N($G6)) | I6: =IF($A6="","",IFERROR(1/(1/SUMIFS(Expenses!$F5:$F1004,Expenses!$B5:$B1004,"Cash Advance",Expenses!$J5:$J1004,$R6,Expenses!$E5:$E1004,$A6)),"")) | J6: =IF($A6="","",IFERROR(1/(1/SUMIFS(Expenses!$F5:$F1004,Expenses!$B5:$B1004,"Payroll Payout",Expenses!$J5:$J1004,$R6,Expenses!$E5:$E1004,$A6)),"")) | K6: =IF($H6="","",N($H6)-N($I6)-N($J6)) | L6: =IF($K6="","",IF($K6>0.5,"TO PAY",IF($K6<-0.5,"ADVANCE / OWES","SETTLED"))) | R6: 46023
A7: =IF(Setup!$A77="","",Setup!$A77) | B7: =IF($A7="","",Setup!$B77) | C7: =IF($A7="","",IF(COUNTIFS(Trips!$Z5:$Z1004,$R7,Trips!$D5:$D1004,$A7)+COUNTIFS(Trips!$Z5:$Z1004,$R7,Trips!$E5:$E1004,$A7)=0,"",COUNTIFS(Trips!$Z5:$Z1004,$R7,Trips!$D5:$D1004,$A7)+COUNTIFS(Trips!$Z5:$Z1004,$R7,Trips!$E5:$E1004,$A7))) | D7: =IF($C7="","",SUMIFS(Trips!$K5:$K1004,Trips!$Z5:$Z1004,$R7,Trips!$D5:$D1004,$A7)+SUMIFS(Trips!$K5:$K1004,Trips!$Z5:$Z1004,$R7,Trips!$E5:$E1004,$A7)) | E7: =IF($C7="","",SUMIFS(Trips!$N5:$N1004,Trips!$Z5:$Z1004,$R7,Trips!$D5:$D1004,$A7)+SUMIFS(Trips!$O5:$O1004,Trips!$Z5:$Z1004,$R7,Trips!$E5:$E1004,$A7)) | F7: =IF($C7="","",SUMIFS(Trips!$P5:$P1004,Trips!$Z5:$Z1004,$R7,Trips!$D5:$D1004,$A7)) | G7: =IF($C7="","",SUMIFS(Trips!$Q5:$Q1004,Trips!$Z5:$Z1004,$R7,Trips!$D5:$D1004,$A7)) | H7: =IF(AND($C7="",$I7="",$J7=""),"",N($E7)+N($F7)+N($G7)) | I7: =IF($A7="","",IFERROR(1/(1/SUMIFS(Expenses!$F5:$F1004,Expenses!$B5:$B1004,"Cash Advance",Expenses!$J5:$J1004,$R7,Expenses!$E5:$E1004,$A7)),"")) | J7: =IF($A7="","",IFERROR(1/(1/SUMIFS(Expenses!$F5:$F1004,Expenses!$B5:$B1004,"Payroll Payout",Expenses!$J5:$J1004,$R7,Expenses!$E5:$E1004,$A7)),"")) | K7: =IF($H7="","",N($H7)-N($I7)-N($J7)) | L7: =IF($K7="","",IF($K7>0.5,"TO PAY",IF($K7<-0.5,"ADVANCE / OWES","SETTLED"))) | R7: 46023
A8: =IF(Setup!$A78="","",Setup!$A78) | B8: =IF($A8="","",Setup!$B78) | C8: =IF($A8="","",IF(COUNTIFS(Trips!$Z5:$Z1004,$R8,Trips!$D5:$D1004,$A8)+COUNTIFS(Trips!$Z5:$Z1004,$R8,Trips!$E5:$E1004,$A8)=0,"",COUNTIFS(Trips!$Z5:$Z1004,$R8,Trips!$D5:$D1004,$A8)+COUNTIFS(Trips!$Z5:$Z1004,$R8,Trips!$E5:$E1004,$A8))) | D8: =IF($C8="","",SUMIFS(Trips!$K5:$K1004,Trips!$Z5:$Z1004,$R8,Trips!$D5:$D1004,$A8)+SUMIFS(Trips!$K5:$K1004,Trips!$Z5:$Z1004,$R8,Trips!$E5:$E1004,$A8)) | E8: =IF($C8="","",SUMIFS(Trips!$N5:$N1004,Trips!$Z5:$Z1004,$R8,Trips!$D5:$D1004,$A8)+SUMIFS(Trips!$O5:$O1004,Trips!$Z5:$Z1004,$R8,Trips!$E5:$E1004,$A8)) | F8: =IF($C8="","",SUMIFS(Trips!$P5:$P1004,Trips!$Z5:$Z1004,$R8,Trips!$D5:$D1004,$A8)) | G8: =IF($C8="","",SUMIFS(Trips!$Q5:$Q1004,Trips!$Z5:$Z1004,$R8,Trips!$D5:$D1004,$A8)) | H8: =IF(AND($C8="",$I8="",$J8=""),"",N($E8)+N($F8)+N($G8)) | I8: =IF($A8="","",IFERROR(1/(1/SUMIFS(Expenses!$F5:$F1004,Expenses!$B5:$B1004,"Cash Advance",Expenses!$J5:$J1004,$R8,Expenses!$E5:$E1004,$A8)),"")) | J8: =IF($A8="","",IFERROR(1/(1/SUMIFS(Expenses!$F5:$F1004,Expenses!$B5:$B1004,"Payroll Payout",Expenses!$J5:$J1004,$R8,Expenses!$E5:$E1004,$A8)),"")) | K8: =IF($H8="","",N($H8)-N($I8)-N($J8)) | L8: =IF($K8="","",IF($K8>0.5,"TO PAY",IF($K8<-0.5,"ADVANCE / OWES","SETTLED"))) | R8: 46023
A9: =IF(Setup!$A79="","",Setup!$A79) | B9: =IF($A9="","",Setup!$B79) | C9: =IF($A9="","",IF(COUNTIFS(Trips!$Z5:$Z1004,$R9,Trips!$D5:$D1004,$A9)+COUNTIFS(Trips!$Z5:$Z1004,$R9,Trips!$E5:$E1004,$A9)=0,"",COUNTIFS(Trips!$Z5:$Z1004,$R9,Trips!$D5:$D1004,$A9)+COUNTIFS(Trips!$Z5:$Z1004,$R9,Trips!$E5:$E1004,$A9))) | D9: =IF($C9="","",SUMIFS(Trips!$K5:$K1004,Trips!$Z5:$Z1004,$R9,Trips!$D5:$D1004,$A9)+SUMIFS(Trips!$K5:$K1004,Trips!$Z5:$Z1004,$R9,Trips!$E5:$E1004,$A9)) | E9: =IF($C9="","",SUMIFS(Trips!$N5:$N1004,Trips!$Z5:$Z1004,$R9,Trips!$D5:$D1004,$A9)+SUMIFS(Trips!$O5:$O1004,Trips!$Z5:$Z1004,$R9,Trips!$E5:$E1004,$A9)) | F9: =IF($C9="","",SUMIFS(Trips!$P5:$P1004,Trips!$Z5:$Z1004,$R9,Trips!$D5:$D1004,$A9)) | G9: =IF($C9="","",SUMIFS(Trips!$Q5:$Q1004,Trips!$Z5:$Z1004,$R9,Trips!$D5:$D1004,$A9)) | H9: =IF(AND($C9="",$I9="",$J9=""),"",N($E9)+N($F9)+N($G9)) | I9: =IF($A9="","",IFERROR(1/(1/SUMIFS(Expenses!$F5:$F1004,Expenses!$B5:$B1004,"Cash Advance",Expenses!$J5:$J1004,$R9,Expenses!$E5:$E1004,$A9)),"")) | J9: =IF($A9="","",IFERROR(1/(1/SUMIFS(Expenses!$F5:$F1004,Expenses!$B5:$B1004,"Payroll Payout",Expenses!$J5:$J1004,$R9,Expenses!$E5:$E1004,$A9)),"")) | K9: =IF($H9="","",N($H9)-N($I9)-N($J9)) | L9: =IF($K9="","",IF($K9>0.5,"TO PAY",IF($K9<-0.5,"ADVANCE / OWES","SETTLED"))) | R9: 46023
A10: =IF(Setup!$A80="","",Setup!$A80) | B10: =IF($A10="","",Setup!$B80) | C10: =IF($A10="","",IF(COUNTIFS(Trips!$Z5:$Z1004,$R10,Trips!$D5:$D1004,$A10)+COUNTIFS(Trips!$Z5:$Z1004,$R10,Trips!$E5:$E1004,$A10)=0,"",COUNTIFS(Trips!$Z5:$Z1004,$R10,Trips!$D5:$D1004,$A10)+COUNTIFS(Trips!$Z5:$Z1004,$R10,Trips!$E5:$E1004,$A10))) | D10: =IF($C10="","",SUMIFS(Trips!$K5:$K1004,Trips!$Z5:$Z1004,$R10,Trips!$D5:$D1004,$A10)+SUMIFS(Trips!$K5:$K1004,Trips!$Z5:$Z1004,$R10,Trips!$E5:$E1004,$A10)) | E10: =IF($C10="","",SUMIFS(Trips!$N5:$N1004,Trips!$Z5:$Z1004,$R10,Trips!$D5:$D1004,$A10)+SUMIFS(Trips!$O5:$O1004,Trips!$Z5:$Z1004,$R10,Trips!$E5:$E1004,$A10)) | F10: =IF($C10="","",SUMIFS(Trips!$P5:$P1004,Trips!$Z5:$Z1004,$R10,Trips!$D5:$D1004,$A10)) | G10: =IF($C10="","",SUMIFS(Trips!$Q5:$Q1004,Trips!$Z5:$Z1004,$R10,Trips!$D5:$D1004,$A10)) | H10: =IF(AND($C10="",$I10="",$J10=""),"",N($E10)+N($F10)+N($G10)) | I10: =IF($A10="","",IFERROR(1/(1/SUMIFS(Expenses!$F5:$F1004,Expenses!$B5:$B1004,"Cash Advance",Expenses!$J5:$J1004,$R10,Expenses!$E5:$E1004,$A10)),"")) | J10: =IF($A10="","",IFERROR(1/(1/SUMIFS(Expenses!$F5:$F1004,Expenses!$B5:$B1004,"Payroll Payout",Expenses!$J5:$J1004,$R10,Expenses!$E5:$E1004,$A10)),"")) | K10: =IF($H10="","",N($H10)-N($I10)-N($J10)) | L10: =IF($K10="","",IF($K10>0.5,"TO PAY",IF($K10<-0.5,"ADVANCE / OWES","SETTLED"))) | R10: 46023
A11: =IF(Setup!$A81="","",Setup!$A81) | B11: =IF($A11="","",Setup!$B81) | C11: =IF($A11="","",IF(COUNTIFS(Trips!$Z5:$Z1004,$R11,Trips!$D5:$D1004,$A11)+COUNTIFS(Trips!$Z5:$Z1004,$R11,Trips!$E5:$E1004,$A11)=0,"",COUNTIFS(Trips!$Z5:$Z1004,$R11,Trips!$D5:$D1004,$A11)+COUNTIFS(Trips!$Z5:$Z1004,$R11,Trips!$E5:$E1004,$A11))) | D11: =IF($C11="","",SUMIFS(Trips!$K5:$K1004,Trips!$Z5:$Z1004,$R11,Trips!$D5:$D1004,$A11)+SUMIFS(Trips!$K5:$K1004,Trips!$Z5:$Z1004,$R11,Trips!$E5:$E1004,$A11)) | E11: =IF($C11="","",SUMIFS(Trips!$N5:$N1004,Trips!$Z5:$Z1004,$R11,Trips!$D5:$D1004,$A11)+SUMIFS(Trips!$O5:$O1004,Trips!$Z5:$Z1004,$R11,Trips!$E5:$E1004,$A11)) | F11: =IF($C11="","",SUMIFS(Trips!$P5:$P1004,Trips!$Z5:$Z1004,$R11,Trips!$D5:$D1004,$A11)) | G11: =IF($C11="","",SUMIFS(Trips!$Q5:$Q1004,Trips!$Z5:$Z1004,$R11,Trips!$D5:$D1004,$A11)) | H11: =IF(AND($C11="",$I11="",$J11=""),"",N($E11)+N($F11)+N($G11)) | I11: =IF($A11="","",IFERROR(1/(1/SUMIFS(Expenses!$F5:$F1004,Expenses!$B5:$B1004,"Cash Advance",Expenses!$J5:$J1004,$R11,Expenses!$E5:$E1004,$A11)),"")) | J11: =IF($A11="","",IFERROR(1/(1/SUMIFS(Expenses!$F5:$F1004,Expenses!$B5:$B1004,"Payroll Payout",Expenses!$J5:$J1004,$R11,Expenses!$E5:$E1004,$A11)),"")) | K11: =IF($H11="","",N($H11)-N($I11)-N($J11)) | L11: =IF($K11="","",IF($K11>0.5,"TO PAY",IF($K11<-0.5,"ADVANCE / OWES","SETTLED"))) | R11: 46023
A12: =IF(Setup!$A82="","",Setup!$A82) | B12: =IF($A12="","",Setup!$B82) | C12: =IF($A12="","",IF(COUNTIFS(Trips!$Z5:$Z1004,$R12,Trips!$D5:$D1004,$A12)+COUNTIFS(Trips!$Z5:$Z1004,$R12,Trips!$E5:$E1004,$A12)=0,"",COUNTIFS(Trips!$Z5:$Z1004,$R12,Trips!$D5:$D1004,$A12)+COUNTIFS(Trips!$Z5:$Z1004,$R12,Trips!$E5:$E1004,$A12))) | D12: =IF($C12="","",SUMIFS(Trips!$K5:$K1004,Trips!$Z5:$Z1004,$R12,Trips!$D5:$D1004,$A12)+SUMIFS(Trips!$K5:$K1004,Trips!$Z5:$Z1004,$R12,Trips!$E5:$E1004,$A12)) | E12: =IF($C12="","",SUMIFS(Trips!$N5:$N1004,Trips!$Z5:$Z1004,$R12,Trips!$D5:$D1004,$A12)+SUMIFS(Trips!$O5:$O1004,Trips!$Z5:$Z1004,$R12,Trips!$E5:$E1004,$A12)) | F12: =IF($C12="","",SUMIFS(Trips!$P5:$P1004,Trips!$Z5:$Z1004,$R12,Trips!$D5:$D1004,$A12)) | G12: =IF($C12="","",SUMIFS(Trips!$Q5:$Q1004,Trips!$Z5:$Z1004,$R12,Trips!$D5:$D1004,$A12)) | H12: =IF(AND($C12="",$I12="",$J12=""),"",N($E12)+N($F12)+N($G12)) | I12: =IF($A12="","",IFERROR(1/(1/SUMIFS(Expenses!$F5:$F1004,Expenses!$B5:$B1004,"Cash Advance",Expenses!$J5:$J1004,$R12,Expenses!$E5:$E1004,$A12)),"")) | J12: =IF($A12="","",IFERROR(1/(1/SUMIFS(Expenses!$F5:$F1004,Expenses!$B5:$B1004,"Payroll Payout",Expenses!$J5:$J1004,$R12,Expenses!$E5:$E1004,$A12)),"")) | K12: =IF($H12="","",N($H12)-N($I12)-N($J12)) | L12: =IF($K12="","",IF($K12>0.5,"TO PAY",IF($K12<-0.5,"ADVANCE / OWES","SETTLED"))) | R12: 46023
A13: =IF(Setup!$A83="","",Setup!$A83) | B13: =IF($A13="","",Setup!$B83) | C13: =IF($A13="","",IF(COUNTIFS(Trips!$Z5:$Z1004,$R13,Trips!$D5:$D1004,$A13)+COUNTIFS(Trips!$Z5:$Z1004,$R13,Trips!$E5:$E1004,$A13)=0,"",COUNTIFS(Trips!$Z5:$Z1004,$R13,Trips!$D5:$D1004,$A13)+COUNTIFS(Trips!$Z5:$Z1004,$R13,Trips!$E5:$E1004,$A13))) | D13: =IF($C13="","",SUMIFS(Trips!$K5:$K1004,Trips!$Z5:$Z1004,$R13,Trips!$D5:$D1004,$A13)+SUMIFS(Trips!$K5:$K1004,Trips!$Z5:$Z1004,$R13,Trips!$E5:$E1004,$A13)) | E13: =IF($C13="","",SUMIFS(Trips!$N5:$N1004,Trips!$Z5:$Z1004,$R13,Trips!$D5:$D1004,$A13)+SUMIFS(Trips!$O5:$O1004,Trips!$Z5:$Z1004,$R13,Trips!$E5:$E1004,$A13)) | F13: =IF($C13="","",SUMIFS(Trips!$P5:$P1004,Trips!$Z5:$Z1004,$R13,Trips!$D5:$D1004,$A13)) | G13: =IF($C13="","",SUMIFS(Trips!$Q5:$Q1004,Trips!$Z5:$Z1004,$R13,Trips!$D5:$D1004,$A13)) | H13: =IF(AND($C13="",$I13="",$J13=""),"",N($E13)+N($F13)+N($G13)) | I13: =IF($A13="","",IFERROR(1/(1/SUMIFS(Expenses!$F5:$F1004,Expenses!$B5:$B1004,"Cash Advance",Expenses!$J5:$J1004,$R13,Expenses!$E5:$E1004,$A13)),"")) | J13: =IF($A13="","",IFERROR(1/(1/SUMIFS(Expenses!$F5:$F1004,Expenses!$B5:$B1004,"Payroll Payout",Expenses!$J5:$J1004,$R13,Expenses!$E5:$E1004,$A13)),"")) | K13: =IF($H13="","",N($H13)-N($I13)-N($J13)) | L13: =IF($K13="","",IF($K13>0.5,"TO PAY",IF($K13<-0.5,"ADVANCE / OWES","SETTLED"))) | R13: 46023
A14: =IF(Setup!$A84="","",Setup!$A84) | B14: =IF($A14="","",Setup!$B84) | C14: =IF($A14="","",IF(COUNTIFS(Trips!$Z5:$Z1004,$R14,Trips!$D5:$D1004,$A14)+COUNTIFS(Trips!$Z5:$Z1004,$R14,Trips!$E5:$E1004,$A14)=0,"",COUNTIFS(Trips!$Z5:$Z1004,$R14,Trips!$D5:$D1004,$A14)+COUNTIFS(Trips!$Z5:$Z1004,$R14,Trips!$E5:$E1004,$A14))) | D14: =IF($C14="","",SUMIFS(Trips!$K5:$K1004,Trips!$Z5:$Z1004,$R14,Trips!$D5:$D1004,$A14)+SUMIFS(Trips!$K5:$K1004,Trips!$Z5:$Z1004,$R14,Trips!$E5:$E1004,$A14)) | E14: =IF($C14="","",SUMIFS(Trips!$N5:$N1004,Trips!$Z5:$Z1004,$R14,Trips!$D5:$D1004,$A14)+SUMIFS(Trips!$O5:$O1004,Trips!$Z5:$Z1004,$R14,Trips!$E5:$E1004,$A14)) | F14: =IF($C14="","",SUMIFS(Trips!$P5:$P1004,Trips!$Z5:$Z1004,$R14,Trips!$D5:$D1004,$A14)) | G14: =IF($C14="","",SUMIFS(Trips!$Q5:$Q1004,Trips!$Z5:$Z1004,$R14,Trips!$D5:$D1004,$A14)) | H14: =IF(AND($C14="",$I14="",$J14=""),"",N($E14)+N($F14)+N($G14)) | I14: =IF($A14="","",IFERROR(1/(1/SUMIFS(Expenses!$F5:$F1004,Expenses!$B5:$B1004,"Cash Advance",Expenses!$J5:$J1004,$R14,Expenses!$E5:$E1004,$A14)),"")) | J14: =IF($A14="","",IFERROR(1/(1/SUMIFS(Expenses!$F5:$F1004,Expenses!$B5:$B1004,"Payroll Payout",Expenses!$J5:$J1004,$R14,Expenses!$E5:$E1004,$A14)),"")) | K14: =IF($H14="","",N($H14)-N($I14)-N($J14)) | L14: =IF($K14="","",IF($K14>0.5,"TO PAY",IF($K14<-0.5,"ADVANCE / OWES","SETTLED"))) | R14: 46023
A15: =IF(Setup!$A85="","",Setup!$A85) | B15: =IF($A15="","",Setup!$B85) | C15: =IF($A15="","",IF(COUNTIFS(Trips!$Z5:$Z1004,$R15,Trips!$D5:$D1004,$A15)+COUNTIFS(Trips!$Z5:$Z1004,$R15,Trips!$E5:$E1004,$A15)=0,"",COUNTIFS(Trips!$Z5:$Z1004,$R15,Trips!$D5:$D1004,$A15)+COUNTIFS(Trips!$Z5:$Z1004,$R15,Trips!$E5:$E1004,$A15))) | D15: =IF($C15="","",SUMIFS(Trips!$K5:$K1004,Trips!$Z5:$Z1004,$R15,Trips!$D5:$D1004,$A15)+SUMIFS(Trips!$K5:$K1004,Trips!$Z5:$Z1004,$R15,Trips!$E5:$E1004,$A15)) | E15: =IF($C15="","",SUMIFS(Trips!$N5:$N1004,Trips!$Z5:$Z1004,$R15,Trips!$D5:$D1004,$A15)+SUMIFS(Trips!$O5:$O1004,Trips!$Z5:$Z1004,$R15,Trips!$E5:$E1004,$A15)) | F15: =IF($C15="","",SUMIFS(Trips!$P5:$P1004,Trips!$Z5:$Z1004,$R15,Trips!$D5:$D1004,$A15)) | G15: =IF($C15="","",SUMIFS(Trips!$Q5:$Q1004,Trips!$Z5:$Z1004,$R15,Trips!$D5:$D1004,$A15)) | H15: =IF(AND($C15="",$I15="",$J15=""),"",N($E15)+N($F15)+N($G15)) | I15: =IF($A15="","",IFERROR(1/(1/SUMIFS(Expenses!$F5:$F1004,Expenses!$B5:$B1004,"Cash Advance",Expenses!$J5:$J1004,$R15,Expenses!$E5:$E1004,$A15)),"")) | J15: =IF($A15="","",IFERROR(1/(1/SUMIFS(Expenses!$F5:$F1004,Expenses!$B5:$B1004,"Payroll Payout",Expenses!$J5:$J1004,$R15,Expenses!$E5:$E1004,$A15)),"")) | K15: =IF($H15="","",N($H15)-N($I15)-N($J15)) | L15: =IF($K15="","",IF($K15>0.5,"TO PAY",IF($K15<-0.5,"ADVANCE / OWES","SETTLED"))) | R15: 46023
A16: =IF(Setup!$A86="","",Setup!$A86) | B16: =IF($A16="","",Setup!$B86) | C16: =IF($A16="","",IF(COUNTIFS(Trips!$Z5:$Z1004,$R16,Trips!$D5:$D1004,$A16)+COUNTIFS(Trips!$Z5:$Z1004,$R16,Trips!$E5:$E1004,$A16)=0,"",COUNTIFS(Trips!$Z5:$Z1004,$R16,Trips!$D5:$D1004,$A16)+COUNTIFS(Trips!$Z5:$Z1004,$R16,Trips!$E5:$E1004,$A16))) | D16: =IF($C16="","",SUMIFS(Trips!$K5:$K1004,Trips!$Z5:$Z1004,$R16,Trips!$D5:$D1004,$A16)+SUMIFS(Trips!$K5:$K1004,Trips!$Z5:$Z1004,$R16,Trips!$E5:$E1004,$A16)) | E16: =IF($C16="","",SUMIFS(Trips!$N5:$N1004,Trips!$Z5:$Z1004,$R16,Trips!$D5:$D1004,$A16)+SUMIFS(Trips!$O5:$O1004,Trips!$Z5:$Z1004,$R16,Trips!$E5:$E1004,$A16)) | F16: =IF($C16="","",SUMIFS(Trips!$P5:$P1004,Trips!$Z5:$Z1004,$R16,Trips!$D5:$D1004,$A16)) | G16: =IF($C16="","",SUMIFS(Trips!$Q5:$Q1004,Trips!$Z5:$Z1004,$R16,Trips!$D5:$D1004,$A16)) | H16: =IF(AND($C16="",$I16="",$J16=""),"",N($E16)+N($F16)+N($G16)) | I16: =IF($A16="","",IFERROR(1/(1/SUMIFS(Expenses!$F5:$F1004,Expenses!$B5:$B1004,"Cash Advance",Expenses!$J5:$J1004,$R16,Expenses!$E5:$E1004,$A16)),"")) | J16: =IF($A16="","",IFERROR(1/(1/SUMIFS(Expenses!$F5:$F1004,Expenses!$B5:$B1004,"Payroll Payout",Expenses!$J5:$J1004,$R16,Expenses!$E5:$E1004,$A16)),"")) | K16: =IF($H16="","",N($H16)-N($I16)-N($J16)) | L16: =IF($K16="","",IF($K16>0.5,"TO PAY",IF($K16<-0.5,"ADVANCE / OWES","SETTLED"))) | R16: 46023
A17: =IF(Setup!$A87="","",Setup!$A87) | B17: =IF($A17="","",Setup!$B87) | C17: =IF($A17="","",IF(COUNTIFS(Trips!$Z5:$Z1004,$R17,Trips!$D5:$D1004,$A17)+COUNTIFS(Trips!$Z5:$Z1004,$R17,Trips!$E5:$E1004,$A17)=0,"",COUNTIFS(Trips!$Z5:$Z1004,$R17,Trips!$D5:$D1004,$A17)+COUNTIFS(Trips!$Z5:$Z1004,$R17,Trips!$E5:$E1004,$A17))) | D17: =IF($C17="","",SUMIFS(Trips!$K5:$K1004,Trips!$Z5:$Z1004,$R17,Trips!$D5:$D1004,$A17)+SUMIFS(Trips!$K5:$K1004,Trips!$Z5:$Z1004,$R17,Trips!$E5:$E1004,$A17)) | E17: =IF($C17="","",SUMIFS(Trips!$N5:$N1004,Trips!$Z5:$Z1004,$R17,Trips!$D5:$D1004,$A17)+SUMIFS(Trips!$O5:$O1004,Trips!$Z5:$Z1004,$R17,Trips!$E5:$E1004,$A17)) | F17: =IF($C17="","",SUMIFS(Trips!$P5:$P1004,Trips!$Z5:$Z1004,$R17,Trips!$D5:$D1004,$A17)) | G17: =IF($C17="","",SUMIFS(Trips!$Q5:$Q1004,Trips!$Z5:$Z1004,$R17,Trips!$D5:$D1004,$A17)) | H17: =IF(AND($C17="",$I17="",$J17=""),"",N($E17)+N($F17)+N($G17)) | I17: =IF($A17="","",IFERROR(1/(1/SUMIFS(Expenses!$F5:$F1004,Expenses!$B5:$B1004,"Cash Advance",Expenses!$J5:$J1004,$R17,Expenses!$E5:$E1004,$A17)),"")) | J17: =IF($A17="","",IFERROR(1/(1/SUMIFS(Expenses!$F5:$F1004,Expenses!$B5:$B1004,"Payroll Payout",Expenses!$J5:$J1004,$R17,Expenses!$E5:$E1004,$A17)),"")) | K17: =IF($H17="","",N($H17)-N($I17)-N($J17)) | L17: =IF($K17="","",IF($K17>0.5,"TO PAY",IF($K17<-0.5,"ADVANCE / OWES","SETTLED"))) | R17: 46023
A18: MONTH TOTAL | C18: =IF(COUNT(C6:C17)=0,"",SUM(C6:C17)) | D18: =IF(COUNT(D6:D17)=0,"",SUM(D6:D17)) | E18: =IF(COUNT(E6:E17)=0,"",SUM(E6:E17)) | F18: =IF(COUNT(F6:F17)=0,"",SUM(F6:F17)) | G18: =IF(COUNT(G6:G17)=0,"",SUM(G6:G17)) | H18: =IF(COUNT(H6:H17)=0,"",SUM(H6:H17)) | I18: =IF(COUNT(I6:I17)=0,"",SUM(I6:I17)) | J18: =IF(COUNT(J6:J17)=0,"",SUM(J6:J17)) | K18: =IF(COUNT(K6:K17)=0,"",SUM(K6:K17))
A19: FEBRUARY 2026 · crew earnings & settlement
A20: =IF(Setup!$A76="","",Setup!$A76) | B20: =IF($A20="","",Setup!$B76) | C20: =IF($A20="","",IF(COUNTIFS(Trips!$Z5:$Z1004,$R20,Trips!$D5:$D1004,$A20)+COUNTIFS(Trips!$Z5:$Z1004,$R20,Trips!$E5:$E1004,$A20)=0,"",COUNTIFS(Trips!$Z5:$Z1004,$R20,Trips!$D5:$D1004,$A20)+COUNTIFS(Trips!$Z5:$Z1004,$R20,Trips!$E5:$E1004,$A20))) | D20: =IF($C20="","",SUMIFS(Trips!$K5:$K1004,Trips!$Z5:$Z1004,$R20,Trips!$D5:$D1004,$A20)+SUMIFS(Trips!$K5:$K1004,Trips!$Z5:$Z1004,$R20,Trips!$E5:$E1004,$A20)) | E20: =IF($C20="","",SUMIFS(Trips!$N5:$N1004,Trips!$Z5:$Z1004,$R20,Trips!$D5:$D1004,$A20)+SUMIFS(Trips!$O5:$O1004,Trips!$Z5:$Z1004,$R20,Trips!$E5:$E1004,$A20)) | F20: =IF($C20="","",SUMIFS(Trips!$P5:$P1004,Trips!$Z5:$Z1004,$R20,Trips!$D5:$D1004,$A20)) | G20: =IF($C20="","",SUMIFS(Trips!$Q5:$Q1004,Trips!$Z5:$Z1004,$R20,Trips!$D5:$D1004,$A20)) | H20: =IF(AND($C20="",$I20="",$J20=""),"",N($E20)+N($F20)+N($G20)) | I20: =IF($A20="","",IFERROR(1/(1/SUMIFS(Expenses!$F5:$F1004,Expenses!$B5:$B1004,"Cash Advance",Expenses!$J5:$J1004,$R20,Expenses!$E5:$E1004,$A20)),"")) | J20: =IF($A20="","",IFERROR(1/(1/SUMIFS(Expenses!$F5:$F1004,Expenses!$B5:$B1004,"Payroll Payout",Expenses!$J5:$J1004,$R20,Expenses!$E5:$E1004,$A20)),"")) | K20: =IF($H20="","",N($H20)-N($I20)-N($J20)) | L20: =IF($K20="","",IF($K20>0.5,"TO PAY",IF($K20<-0.5,"ADVANCE / OWES","SETTLED"))) | R20: 46054
A21: =IF(Setup!$A77="","",Setup!$A77) | B21: =IF($A21="","",Setup!$B77) | C21: =IF($A21="","",IF(COUNTIFS(Trips!$Z5:$Z1004,$R21,Trips!$D5:$D1004,$A21)+COUNTIFS(Trips!$Z5:$Z1004,$R21,Trips!$E5:$E1004,$A21)=0,"",COUNTIFS(Trips!$Z5:$Z1004,$R21,Trips!$D5:$D1004,$A21)+COUNTIFS(Trips!$Z5:$Z1004,$R21,Trips!$E5:$E1004,$A21))) | D21: =IF($C21="","",SUMIFS(Trips!$K5:$K1004,Trips!$Z5:$Z1004,$R21,Trips!$D5:$D1004,$A21)+SUMIFS(Trips!$K5:$K1004,Trips!$Z5:$Z1004,$R21,Trips!$E5:$E1004,$A21)) | E21: =IF($C21="","",SUMIFS(Trips!$N5:$N1004,Trips!$Z5:$Z1004,$R21,Trips!$D5:$D1004,$A21)+SUMIFS(Trips!$O5:$O1004,Trips!$Z5:$Z1004,$R21,Trips!$E5:$E1004,$A21)) | F21: =IF($C21="","",SUMIFS(Trips!$P5:$P1004,Trips!$Z5:$Z1004,$R21,Trips!$D5:$D1004,$A21)) | G21: =IF($C21="","",SUMIFS(Trips!$Q5:$Q1004,Trips!$Z5:$Z1004,$R21,Trips!$D5:$D1004,$A21)) | H21: =IF(AND($C21="",$I21="",$J21=""),"",N($E21)+N($F21)+N($G21)) | I21: =IF($A21="","",IFERROR(1/(1/SUMIFS(Expenses!$F5:$F1004,Expenses!$B5:$B1004,"Cash Advance",Expenses!$J5:$J1004,$R21,Expenses!$E5:$E1004,$A21)),"")) | J21: =IF($A21="","",IFERROR(1/(1/SUMIFS(Expenses!$F5:$F1004,Expenses!$B5:$B1004,"Payroll Payout",Expenses!$J5:$J1004,$R21,Expenses!$E5:$E1004,$A21)),"")) | K21: =IF($H21="","",N($H21)-N($I21)-N($J21)) | L21: =IF($K21="","",IF($K21>0.5,"TO PAY",IF($K21<-0.5,"ADVANCE / OWES","SETTLED"))) | R21: 46054
A22: =IF(Setup!$A78="","",Setup!$A78) | B22: =IF($A22="","",Setup!$B78) | C22: =IF($A22="","",IF(COUNTIFS(Trips!$Z5:$Z1004,$R22,Trips!$D5:$D1004,$A22)+COUNTIFS(Trips!$Z5:$Z1004,$R22,Trips!$E5:$E1004,$A22)=0,"",COUNTIFS(Trips!$Z5:$Z1004,$R22,Trips!$D5:$D1004,$A22)+COUNTIFS(Trips!$Z5:$Z1004,$R22,Trips!$E5:$E1004,$A22))) | D22: =IF($C22="","",SUMIFS(Trips!$K5:$K1004,Trips!$Z5:$Z1004,$R22,Trips!$D5:$D1004,$A22)+SUMIFS(Trips!$K5:$K1004,Trips!$Z5:$Z1004,$R22,Trips!$E5:$E1004,$A22)) | E22: =IF($C22="","",SUMIFS(Trips!$N5:$N1004,Trips!$Z5:$Z1004,$R22,Trips!$D5:$D1004,$A22)+SUMIFS(Trips!$O5:$O1004,Trips!$Z5:$Z1004,$R22,Trips!$E5:$E1004,$A22)) | F22: =IF($C22="","",SUMIFS(Trips!$P5:$P1004,Trips!$Z5:$Z1004,$R22,Trips!$D5:$D1004,$A22)) | G22: =IF($C22="","",SUMIFS(Trips!$Q5:$Q1004,Trips!$Z5:$Z1004,$R22,Trips!$D5:$D1004,$A22)) | H22: =IF(AND($C22="",$I22="",$J22=""),"",N($E22)+N($F22)+N($G22)) | I22: =IF($A22="","",IFERROR(1/(1/SUMIFS(Expenses!$F5:$F1004,Expenses!$B5:$B1004,"Cash Advance",Expenses!$J5:$J1004,$R22,Expenses!$E5:$E1004,$A22)),"")) | J22: =IF($A22="","",IFERROR(1/(1/SUMIFS(Expenses!$F5:$F1004,Expenses!$B5:$B1004,"Payroll Payout",Expenses!$J5:$J1004,$R22,Expenses!$E5:$E1004,$A22)),"")) | K22: =IF($H22="","",N($H22)-N($I22)-N($J22)) | L22: =IF($K22="","",IF($K22>0.5,"TO PAY",IF($K22<-0.5,"ADVANCE / OWES","SETTLED"))) | R22: 46054
A23: =IF(Setup!$A79="","",Setup!$A79) | B23: =IF($A23="","",Setup!$B79) | C23: =IF($A23="","",IF(COUNTIFS(Trips!$Z5:$Z1004,$R23,Trips!$D5:$D1004,$A23)+COUNTIFS(Trips!$Z5:$Z1004,$R23,Trips!$E5:$E1004,$A23)=0,"",COUNTIFS(Trips!$Z5:$Z1004,$R23,Trips!$D5:$D1004,$A23)+COUNTIFS(Trips!$Z5:$Z1004,$R23,Trips!$E5:$E1004,$A23))) | D23: =IF($C23="","",SUMIFS(Trips!$K5:$K1004,Trips!$Z5:$Z1004,$R23,Trips!$D5:$D1004,$A23)+SUMIFS(Trips!$K5:$K1004,Trips!$Z5:$Z1004,$R23,Trips!$E5:$E1004,$A23)) | E23: =IF($C23="","",SUMIFS(Trips!$N5:$N1004,Trips!$Z5:$Z1004,$R23,Trips!$D5:$D1004,$A23)+SUMIFS(Trips!$O5:$O1004,Trips!$Z5:$Z1004,$R23,Trips!$E5:$E1004,$A23)) | F23: =IF($C23="","",SUMIFS(Trips!$P5:$P1004,Trips!$Z5:$Z1004,$R23,Trips!$D5:$D1004,$A23)) | G23: =IF($C23="","",SUMIFS(Trips!$Q5:$Q1004,Trips!$Z5:$Z1004,$R23,Trips!$D5:$D1004,$A23)) | H23: =IF(AND($C23="",$I23="",$J23=""),"",N($E23)+N($F23)+N($G23)) | I23: =IF($A23="","",IFERROR(1/(1/SUMIFS(Expenses!$F5:$F1004,Expenses!$B5:$B1004,"Cash Advance",Expenses!$J5:$J1004,$R23,Expenses!$E5:$E1004,$A23)),"")) | J23: =IF($A23="","",IFERROR(1/(1/SUMIFS(Expenses!$F5:$F1004,Expenses!$B5:$B1004,"Payroll Payout",Expenses!$J5:$J1004,$R23,Expenses!$E5:$E1004,$A23)),"")) | K23: =IF($H23="","",N($H23)-N($I23)-N($J23)) | L23: =IF($K23="","",IF($K23>0.5,"TO PAY",IF($K23<-0.5,"ADVANCE / OWES","SETTLED"))) | R23: 46054
A24: =IF(Setup!$A80="","",Setup!$A80) | B24: =IF($A24="","",Setup!$B80) | C24: =IF($A24="","",IF(COUNTIFS(Trips!$Z5:$Z1004,$R24,Trips!$D5:$D1004,$A24)+COUNTIFS(Trips!$Z5:$Z1004,$R24,Trips!$E5:$E1004,$A24)=0,"",COUNTIFS(Trips!$Z5:$Z1004,$R24,Trips!$D5:$D1004,$A24)+COUNTIFS(Trips!$Z5:$Z1004,$R24,Trips!$E5:$E1004,$A24))) | D24: =IF($C24="","",SUMIFS(Trips!$K5:$K1004,Trips!$Z5:$Z1004,$R24,Trips!$D5:$D1004,$A24)+SUMIFS(Trips!$K5:$K1004,Trips!$Z5:$Z1004,$R24,Trips!$E5:$E1004,$A24)) | E24: =IF($C24="","",SUMIFS(Trips!$N5:$N1004,Trips!$Z5:$Z1004,$R24,Trips!$D5:$D1004,$A24)+SUMIFS(Trips!$O5:$O1004,Trips!$Z5:$Z1004,$R24,Trips!$E5:$E1004,$A24)) | F24: =IF($C24="","",SUMIFS(Trips!$P5:$P1004,Trips!$Z5:$Z1004,$R24,Trips!$D5:$D1004,$A24)) | G24: =IF($C24="","",SUMIFS(Trips!$Q5:$Q1004,Trips!$Z5:$Z1004,$R24,Trips!$D5:$D1004,$A24)) | H24: =IF(AND($C24="",$I24="",$J24=""),"",N($E24)+N($F24)+N($G24)) | I24: =IF($A24="","",IFERROR(1/(1/SUMIFS(Expenses!$F5:$F1004,Expenses!$B5:$B1004,"Cash Advance",Expenses!$J5:$J1004,$R24,Expenses!$E5:$E1004,$A24)),"")) | J24: =IF($A24="","",IFERROR(1/(1/SUMIFS(Expenses!$F5:$F1004,Expenses!$B5:$B1004,"Payroll Payout",Expenses!$J5:$J1004,$R24,Expenses!$E5:$E1004,$A24)),"")) | K24: =IF($H24="","",N($H24)-N($I24)-N($J24)) | L24: =IF($K24="","",IF($K24>0.5,"TO PAY",IF($K24<-0.5,"ADVANCE / OWES","SETTLED"))) | R24: 46054
A25: =IF(Setup!$A81="","",Setup!$A81) | B25: =IF($A25="","",Setup!$B81) | C25: =IF($A25="","",IF(COUNTIFS(Trips!$Z5:$Z1004,$R25,Trips!$D5:$D1004,$A25)+COUNTIFS(Trips!$Z5:$Z1004,$R25,Trips!$E5:$E1004,$A25)=0,"",COUNTIFS(Trips!$Z5:$Z1004,$R25,Trips!$D5:$D1004,$A25)+COUNTIFS(Trips!$Z5:$Z1004,$R25,Trips!$E5:$E1004,$A25))) | D25: =IF($C25="","",SUMIFS(Trips!$K5:$K1004,Trips!$Z5:$Z1004,$R25,Trips!$D5:$D1004,$A25)+SUMIFS(Trips!$K5:$K1004,Trips!$Z5:$Z1004,$R25,Trips!$E5:$E1004,$A25)) | E25: =IF($C25="","",SUMIFS(Trips!$N5:$N1004,Trips!$Z5:$Z1004,$R25,Trips!$D5:$D1004,$A25)+SUMIFS(Trips!$O5:$O1004,Trips!$Z5:$Z1004,$R25,Trips!$E5:$E1004,$A25)) | F25: =IF($C25="","",SUMIFS(Trips!$P5:$P1004,Trips!$Z5:$Z1004,$R25,Trips!$D5:$D1004,$A25)) | G25: =IF($C25="","",SUMIFS(Trips!$Q5:$Q1004,Trips!$Z5:$Z1004,$R25,Trips!$D5:$D1004,$A25)) | H25: =IF(AND($C25="",$I25="",$J25=""),"",N($E25)+N($F25)+N($G25)) | I25: =IF($A25="","",IFERROR(1/(1/SUMIFS(Expenses!$F5:$F1004,Expenses!$B5:$B1004,"Cash Advance",Expenses!$J5:$J1004,$R25,Expenses!$E5:$E1004,$A25)),"")) | J25: =IF($A25="","",IFERROR(1/(1/SUMIFS(Expenses!$F5:$F1004,Expenses!$B5:$B1004,"Payroll Payout",Expenses!$J5:$J1004,$R25,Expenses!$E5:$E1004,$A25)),"")) | K25: =IF($H25="","",N($H25)-N($I25)-N($J25)) | L25: =IF($K25="","",IF($K25>0.5,"TO PAY",IF($K25<-0.5,"ADVANCE / OWES","SETTLED"))) | R25: 46054
A26: =IF(Setup!$A82="","",Setup!$A82) | B26: =IF($A26="","",Setup!$B82) | C26: =IF($A26="","",IF(COUNTIFS(Trips!$Z5:$Z1004,$R26,Trips!$D5:$D1004,$A26)+COUNTIFS(Trips!$Z5:$Z1004,$R26,Trips!$E5:$E1004,$A26)=0,"",COUNTIFS(Trips!$Z5:$Z1004,$R26,Trips!$D5:$D1004,$A26)+COUNTIFS(Trips!$Z5:$Z1004,$R26,Trips!$E5:$E1004,$A26))) | D26: =IF($C26="","",SUMIFS(Trips!$K5:$K1004,Trips!$Z5:$Z1004,$R26,Trips!$D5:$D1004,$A26)+SUMIFS(Trips!$K5:$K1004,Trips!$Z5:$Z1004,$R26,Trips!$E5:$E1004,$A26)) | E26: =IF($C26="","",SUMIFS(Trips!$N5:$N1004,Trips!$Z5:$Z1004,$R26,Trips!$D5:$D1004,$A26)+SUMIFS(Trips!$O5:$O1004,Trips!$Z5:$Z1004,$R26,Trips!$E5:$E1004,$A26)) | F26: =IF($C26="","",SUMIFS(Trips!$P5:$P1004,Trips!$Z5:$Z1004,$R26,Trips!$D5:$D1004,$A26)) | G26: =IF($C26="","",SUMIFS(Trips!$Q5:$Q1004,Trips!$Z5:$Z1004,$R26,Trips!$D5:$D1004,$A26)) | H26: =IF(AND($C26="",$I26="",$J26=""),"",N($E26)+N($F26)+N($G26)) | I26: =IF($A26="","",IFERROR(1/(1/SUMIFS(Expenses!$F5:$F1004,Expenses!$B5:$B1004,"Cash Advance",Expenses!$J5:$J1004,$R26,Expenses!$E5:$E1004,$A26)),"")) | J26: =IF($A26="","",IFERROR(1/(1/SUMIFS(Expenses!$F5:$F1004,Expenses!$B5:$B1004,"Payroll Payout",Expenses!$J5:$J1004,$R26,Expenses!$E5:$E1004,$A26)),"")) | K26: =IF($H26="","",N($H26)-N($I26)-N($J26)) | L26: =IF($K26="","",IF($K26>0.5,"TO PAY",IF($K26<-0.5,"ADVANCE / OWES","SETTLED"))) | R26: 46054
A27: =IF(Setup!$A83="","",Setup!$A83) | B27: =IF($A27="","",Setup!$B83) | C27: =IF($A27="","",IF(COUNTIFS(Trips!$Z5:$Z1004,$R27,Trips!$D5:$D1004,$A27)+COUNTIFS(Trips!$Z5:$Z1004,$R27,Trips!$E5:$E1004,$A27)=0,"",COUNTIFS(Trips!$Z5:$Z1004,$R27,Trips!$D5:$D1004,$A27)+COUNTIFS(Trips!$Z5:$Z1004,$R27,Trips!$E5:$E1004,$A27))) | D27: =IF($C27="","",SUMIFS(Trips!$K5:$K1004,Trips!$Z5:$Z1004,$R27,Trips!$D5:$D1004,$A27)+SUMIFS(Trips!$K5:$K1004,Trips!$Z5:$Z1004,$R27,Trips!$E5:$E1004,$A27)) | E27: =IF($C27="","",SUMIFS(Trips!$N5:$N1004,Trips!$Z5:$Z1004,$R27,Trips!$D5:$D1004,$A27)+SUMIFS(Trips!$O5:$O1004,Trips!$Z5:$Z1004,$R27,Trips!$E5:$E1004,$A27)) | F27: =IF($C27="","",SUMIFS(Trips!$P5:$P1004,Trips!$Z5:$Z1004,$R27,Trips!$D5:$D1004,$A27)) | G27: =IF($C27="","",SUMIFS(Trips!$Q5:$Q1004,Trips!$Z5:$Z1004,$R27,Trips!$D5:$D1004,$A27)) | H27: =IF(AND($C27="",$I27="",$J27=""),"",N($E27)+N($F27)+N($G27)) | I27: =IF($A27="","",IFERROR(1/(1/SUMIFS(Expenses!$F5:$F1004,Expenses!$B5:$B1004,"Cash Advance",Expenses!$J5:$J1004,$R27,Expenses!$E5:$E1004,$A27)),"")) | J27: =IF($A27="","",IFERROR(1/(1/SUMIFS(Expenses!$F5:$F1004,Expenses!$B5:$B1004,"Payroll Payout",Expenses!$J5:$J1004,$R27,Expenses!$E5:$E1004,$A27)),"")) | K27: =IF($H27="","",N($H27)-N($I27)-N($J27)) | L27: =IF($K27="","",IF($K27>0.5,"TO PAY",IF($K27<-0.5,"ADVANCE / OWES","SETTLED"))) | R27: 46054
A28: =IF(Setup!$A84="","",Setup!$A84) | B28: =IF($A28="","",Setup!$B84) | C28: =IF($A28="","",IF(COUNTIFS(Trips!$Z5:$Z1004,$R28,Trips!$D5:$D1004,$A28)+COUNTIFS(Trips!$Z5:$Z1004,$R28,Trips!$E5:$E1004,$A28)=0,"",COUNTIFS(Trips!$Z5:$Z1004,$R28,Trips!$D5:$D1004,$A28)+COUNTIFS(Trips!$Z5:$Z1004,$R28,Trips!$E5:$E1004,$A28))) | D28: =IF($C28="","",SUMIFS(Trips!$K5:$K1004,Trips!$Z5:$Z1004,$R28,Trips!$D5:$D1004,$A28)+SUMIFS(Trips!$K5:$K1004,Trips!$Z5:$Z1004,$R28,Trips!$E5:$E1004,$A28)) | E28: =IF($C28="","",SUMIFS(Trips!$N5:$N1004,Trips!$Z5:$Z1004,$R28,Trips!$D5:$D1004,$A28)+SUMIFS(Trips!$O5:$O1004,Trips!$Z5:$Z1004,$R28,Trips!$E5:$E1004,$A28)) | F28: =IF($C28="","",SUMIFS(Trips!$P5:$P1004,Trips!$Z5:$Z1004,$R28,Trips!$D5:$D1004,$A28)) | G28: =IF($C28="","",SUMIFS(Trips!$Q5:$Q1004,Trips!$Z5:$Z1004,$R28,Trips!$D5:$D1004,$A28)) | H28: =IF(AND($C28="",$I28="",$J28=""),"",N($E28)+N($F28)+N($G28)) | I28: =IF($A28="","",IFERROR(1/(1/SUMIFS(Expenses!$F5:$F1004,Expenses!$B5:$B1004,"Cash Advance",Expenses!$J5:$J1004,$R28,Expenses!$E5:$E1004,$A28)),"")) | J28: =IF($A28="","",IFERROR(1/(1/SUMIFS(Expenses!$F5:$F1004,Expenses!$B5:$B1004,"Payroll Payout",Expenses!$J5:$J1004,$R28,Expenses!$E5:$E1004,$A28)),"")) | K28: =IF($H28="","",N($H28)-N($I28)-N($J28)) | L28: =IF($K28="","",IF($K28>0.5,"TO PAY",IF($K28<-0.5,"ADVANCE / OWES","SETTLED"))) | R28: 46054
A29: =IF(Setup!$A85="","",Setup!$A85) | B29: =IF($A29="","",Setup!$B85) | C29: =IF($A29="","",IF(COUNTIFS(Trips!$Z5:$Z1004,$R29,Trips!$D5:$D1004,$A29)+COUNTIFS(Trips!$Z5:$Z1004,$R29,Trips!$E5:$E1004,$A29)=0,"",COUNTIFS(Trips!$Z5:$Z1004,$R29,Trips!$D5:$D1004,$A29)+COUNTIFS(Trips!$Z5:$Z1004,$R29,Trips!$E5:$E1004,$A29))) | D29: =IF($C29="","",SUMIFS(Trips!$K5:$K1004,Trips!$Z5:$Z1004,$R29,Trips!$D5:$D1004,$A29)+SUMIFS(Trips!$K5:$K1004,Trips!$Z5:$Z1004,$R29,Trips!$E5:$E1004,$A29)) | E29: =IF($C29="","",SUMIFS(Trips!$N5:$N1004,Trips!$Z5:$Z1004,$R29,Trips!$D5:$D1004,$A29)+SUMIFS(Trips!$O5:$O1004,Trips!$Z5:$Z1004,$R29,Trips!$E5:$E1004,$A29)) | F29: =IF($C29="","",SUMIFS(Trips!$P5:$P1004,Trips!$Z5:$Z1004,$R29,Trips!$D5:$D1004,$A29)) | G29: =IF($C29="","",SUMIFS(Trips!$Q5:$Q1004,Trips!$Z5:$Z1004,$R29,Trips!$D5:$D1004,$A29)) | H29: =IF(AND($C29="",$I29="",$J29=""),"",N($E29)+N($F29)+N($G29)) | I29: =IF($A29="","",IFERROR(1/(1/SUMIFS(Expenses!$F5:$F1004,Expenses!$B5:$B1004,"Cash Advance",Expenses!$J5:$J1004,$R29,Expenses!$E5:$E1004,$A29)),"")) | J29: =IF($A29="","",IFERROR(1/(1/SUMIFS(Expenses!$F5:$F1004,Expenses!$B5:$B1004,"Payroll Payout",Expenses!$J5:$J1004,$R29,Expenses!$E5:$E1004,$A29)),"")) | K29: =IF($H29="","",N($H29)-N($I29)-N($J29)) | L29: =IF($K29="","",IF($K29>0.5,"TO PAY",IF($K29<-0.5,"ADVANCE / OWES","SETTLED"))) | R29: 46054
A30: =IF(Setup!$A86="","",Setup!$A86) | B30: =IF($A30="","",Setup!$B86) | C30: =IF($A30="","",IF(COUNTIFS(Trips!$Z5:$Z1004,$R30,Trips!$D5:$D1004,$A30)+COUNTIFS(Trips!$Z5:$Z1004,$R30,Trips!$E5:$E1004,$A30)=0,"",COUNTIFS(Trips!$Z5:$Z1004,$R30,Trips!$D5:$D1004,$A30)+COUNTIFS(Trips!$Z5:$Z1004,$R30,Trips!$E5:$E1004,$A30))) | D30: =IF($C30="","",SUMIFS(Trips!$K5:$K1004,Trips!$Z5:$Z1004,$R30,Trips!$D5:$D1004,$A30)+SUMIFS(Trips!$K5:$K1004,Trips!$Z5:$Z1004,$R30,Trips!$E5:$E1004,$A30)) | E30: =IF($C30="","",SUMIFS(Trips!$N5:$N1004,Trips!$Z5:$Z1004,$R30,Trips!$D5:$D1004,$A30)+SUMIFS(Trips!$O5:$O1004,Trips!$Z5:$Z1004,$R30,Trips!$E5:$E1004,$A30)) | F30: =IF($C30="","",SUMIFS(Trips!$P5:$P1004,Trips!$Z5:$Z1004,$R30,Trips!$D5:$D1004,$A30)) | G30: =IF($C30="","",SUMIFS(Trips!$Q5:$Q1004,Trips!$Z5:$Z1004,$R30,Trips!$D5:$D1004,$A30)) | H30: =IF(AND($C30="",$I30="",$J30=""),"",N($E30)+N($F30)+N($G30)) | I30: =IF($A30="","",IFERROR(1/(1/SUMIFS(Expenses!$F5:$F1004,Expenses!$B5:$B1004,"Cash Advance",Expenses!$J5:$J1004,$R30,Expenses!$E5:$E1004,$A30)),"")) | J30: =IF($A30="","",IFERROR(1/(1/SUMIFS(Expenses!$F5:$F1004,Expenses!$B5:$B1004,"Payroll Payout",Expenses!$J5:$J1004,$R30,Expenses!$E5:$E1004,$A30)),"")) | K30: =IF($H30="","",N($H30)-N($I30)-N($J30)) | L30: =IF($K30="","",IF($K30>0.5,"TO PAY",IF($K30<-0.5,"ADVANCE / OWES","SETTLED"))) | R30: 46054
A31: =IF(Setup!$A87="","",Setup!$A87) | B31: =IF($A31="","",Setup!$B87) | C31: =IF($A31="","",IF(COUNTIFS(Trips!$Z5:$Z1004,$R31,Trips!$D5:$D1004,$A31)+COUNTIFS(Trips!$Z5:$Z1004,$R31,Trips!$E5:$E1004,$A31)=0,"",COUNTIFS(Trips!$Z5:$Z1004,$R31,Trips!$D5:$D1004,$A31)+COUNTIFS(Trips!$Z5:$Z1004,$R31,Trips!$E5:$E1004,$A31))) | D31: =IF($C31="","",SUMIFS(Trips!$K5:$K1004,Trips!$Z5:$Z1004,$R31,Trips!$D5:$D1004,$A31)+SUMIFS(Trips!$K5:$K1004,Trips!$Z5:$Z1004,$R31,Trips!$E5:$E1004,$A31)) | E31: =IF($C31="","",SUMIFS(Trips!$N5:$N1004,Trips!$Z5:$Z1004,$R31,Trips!$D5:$D1004,$A31)+SUMIFS(Trips!$O5:$O1004,Trips!$Z5:$Z1004,$R31,Trips!$E5:$E1004,$A31)) | F31: =IF($C31="","",SUMIFS(Trips!$P5:$P1004,Trips!$Z5:$Z1004,$R31,Trips!$D5:$D1004,$A31)) | G31: =IF($C31="","",SUMIFS(Trips!$Q5:$Q1004,Trips!$Z5:$Z1004,$R31,Trips!$D5:$D1004,$A31)) | H31: =IF(AND($C31="",$I31="",$J31=""),"",N($E31)+N($F31)+N($G31)) | I31: =IF($A31="","",IFERROR(1/(1/SUMIFS(Expenses!$F5:$F1004,Expenses!$B5:$B1004,"Cash Advance",Expenses!$J5:$J1004,$R31,Expenses!$E5:$E1004,$A31)),"")) | J31: =IF($A31="","",IFERROR(1/(1/SUMIFS(Expenses!$F5:$F1004,Expenses!$B5:$B1004,"Payroll Payout",Expenses!$J5:$J1004,$R31,Expenses!$E5:$E1004,$A31)),"")) | K31: =IF($H31="","",N($H31)-N($I31)-N($J31)) | L31: =IF($K31="","",IF($K31>0.5,"TO PAY",IF($K31<-0.5,"ADVANCE / OWES","SETTLED"))) | R31: 46054
A32: MONTH TOTAL | C32: =IF(COUNT(C20:C31)=0,"",SUM(C20:C31)) | D32: =IF(COUNT(D20:D31)=0,"",SUM(D20:D31)) | E32: =IF(COUNT(E20:E31)=0,"",SUM(E20:E31)) | F32: =IF(COUNT(F20:F31)=0,"",SUM(F20:F31)) | G32: =IF(COUNT(G20:G31)=0,"",SUM(G20:G31)) | H32: =IF(COUNT(H20:H31)=0,"",SUM(H20:H31)) | I32: =IF(COUNT(I20:I31)=0,"",SUM(I20:I31)) | J32: =IF(COUNT(J20:J31)=0,"",SUM(J20:J31)) | K32: =IF(COUNT(K20:K31)=0,"",SUM(K20:K31))
A33: MARCH 2026 · crew earnings & settlement
A34: =IF(Setup!$A76="","",Setup!$A76) | B34: =IF($A34="","",Setup!$B76) | C34: =IF($A34="","",IF(COUNTIFS(Trips!$Z5:$Z1004,$R34,Trips!$D5:$D1004,$A34)+COUNTIFS(Trips!$Z5:$Z1004,$R34,Trips!$E5:$E1004,$A34)=0,"",COUNTIFS(Trips!$Z5:$Z1004,$R34,Trips!$D5:$D1004,$A34)+COUNTIFS(Trips!$Z5:$Z1004,$R34,Trips!$E5:$E1004,$A34))) | D34: =IF($C34="","",SUMIFS(Trips!$K5:$K1004,Trips!$Z5:$Z1004,$R34,Trips!$D5:$D1004,$A34)+SUMIFS(Trips!$K5:$K1004,Trips!$Z5:$Z1004,$R34,Trips!$E5:$E1004,$A34)) | E34: =IF($C34="","",SUMIFS(Trips!$N5:$N1004,Trips!$Z5:$Z1004,$R34,Trips!$D5:$D1004,$A34)+SUMIFS(Trips!$O5:$O1004,Trips!$Z5:$Z1004,$R34,Trips!$E5:$E1004,$A34)) | F34: =IF($C34="","",SUMIFS(Trips!$P5:$P1004,Trips!$Z5:$Z1004,$R34,Trips!$D5:$D1004,$A34)) | G34: =IF($C34="","",SUMIFS(Trips!$Q5:$Q1004,Trips!$Z5:$Z1004,$R34,Trips!$D5:$D1004,$A34)) | H34: =IF(AND($C34="",$I34="",$J34=""),"",N($E34)+N($F34)+N($G34)) | I34: =IF($A34="","",IFERROR(1/(1/SUMIFS(Expenses!$F5:$F1004,Expenses!$B5:$B1004,"Cash Advance",Expenses!$J5:$J1004,$R34,Expenses!$E5:$E1004,$A34)),"")) | J34: =IF($A34="","",IFERROR(1/(1/SUMIFS(Expenses!$F5:$F1004,Expenses!$B5:$B1004,"Payroll Payout",Expenses!$J5:$J1004,$R34,Expenses!$E5:$E1004,$A34)),"")) | K34: =IF($H34="","",N($H34)-N($I34)-N($J34)) | L34: =IF($K34="","",IF($K34>0.5,"TO PAY",IF($K34<-0.5,"ADVANCE / OWES","SETTLED"))) | R34: 46082
A35: =IF(Setup!$A77="","",Setup!$A77) | B35: =IF($A35="","",Setup!$B77) | C35: =IF($A35="","",IF(COUNTIFS(Trips!$Z5:$Z1004,$R35,Trips!$D5:$D1004,$A35)+COUNTIFS(Trips!$Z5:$Z1004,$R35,Trips!$E5:$E1004,$A35)=0,"",COUNTIFS(Trips!$Z5:$Z1004,$R35,Trips!$D5:$D1004,$A35)+COUNTIFS(Trips!$Z5:$Z1004,$R35,Trips!$E5:$E1004,$A35))) | D35: =IF($C35="","",SUMIFS(Trips!$K5:$K1004,Trips!$Z5:$Z1004,$R35,Trips!$D5:$D1004,$A35)+SUMIFS(Trips!$K5:$K1004,Trips!$Z5:$Z1004,$R35,Trips!$E5:$E1004,$A35)) | E35: =IF($C35="","",SUMIFS(Trips!$N5:$N1004,Trips!$Z5:$Z1004,$R35,Trips!$D5:$D1004,$A35)+SUMIFS(Trips!$O5:$O1004,Trips!$Z5:$Z1004,$R35,Trips!$E5:$E1004,$A35)) | F35: =IF($C35="","",SUMIFS(Trips!$P5:$P1004,Trips!$Z5:$Z1004,$R35,Trips!$D5:$D1004,$A35)) | G35: =IF($C35="","",SUMIFS(Trips!$Q5:$Q1004,Trips!$Z5:$Z1004,$R35,Trips!$D5:$D1004,$A35)) | H35: =IF(AND($C35="",$I35="",$J35=""),"",N($E35)+N($F35)+N($G35)) | I35: =IF($A35="","",IFERROR(1/(1/SUMIFS(Expenses!$F5:$F1004,Expenses!$B5:$B1004,"Cash Advance",Expenses!$J5:$J1004,$R35,Expenses!$E5:$E1004,$A35)),"")) | J35: =IF($A35="","",IFERROR(1/(1/SUMIFS(Expenses!$F5:$F1004,Expenses!$B5:$B1004,"Payroll Payout",Expenses!$J5:$J1004,$R35,Expenses!$E5:$E1004,$A35)),"")) | K35: =IF($H35="","",N($H35)-N($I35)-N($J35)) | L35: =IF($K35="","",IF($K35>0.5,"TO PAY",IF($K35<-0.5,"ADVANCE / OWES","SETTLED"))) | R35: 46082
A36: =IF(Setup!$A78="","",Setup!$A78) | B36: =IF($A36="","",Setup!$B78) | C36: =IF($A36="","",IF(COUNTIFS(Trips!$Z5:$Z1004,$R36,Trips!$D5:$D1004,$A36)+COUNTIFS(Trips!$Z5:$Z1004,$R36,Trips!$E5:$E1004,$A36)=0,"",COUNTIFS(Trips!$Z5:$Z1004,$R36,Trips!$D5:$D1004,$A36)+COUNTIFS(Trips!$Z5:$Z1004,$R36,Trips!$E5:$E1004,$A36))) | D36: =IF($C36="","",SUMIFS(Trips!$K5:$K1004,Trips!$Z5:$Z1004,$R36,Trips!$D5:$D1004,$A36)+SUMIFS(Trips!$K5:$K1004,Trips!$Z5:$Z1004,$R36,Trips!$E5:$E1004,$A36)) | E36: =IF($C36="","",SUMIFS(Trips!$N5:$N1004,Trips!$Z5:$Z1004,$R36,Trips!$D5:$D1004,$A36)+SUMIFS(Trips!$O5:$O1004,Trips!$Z5:$Z1004,$R36,Trips!$E5:$E1004,$A36)) | F36: =IF($C36="","",SUMIFS(Trips!$P5:$P1004,Trips!$Z5:$Z1004,$R36,Trips!$D5:$D1004,$A36)) | G36: =IF($C36="","",SUMIFS(Trips!$Q5:$Q1004,Trips!$Z5:$Z1004,$R36,Trips!$D5:$D1004,$A36)) | H36: =IF(AND($C36="",$I36="",$J36=""),"",N($E36)+N($F36)+N($G36)) | I36: =IF($A36="","",IFERROR(1/(1/SUMIFS(Expenses!$F5:$F1004,Expenses!$B5:$B1004,"Cash Advance",Expenses!$J5:$J1004,$R36,Expenses!$E5:$E1004,$A36)),"")) | J36: =IF($A36="","",IFERROR(1/(1/SUMIFS(Expenses!$F5:$F1004,Expenses!$B5:$B1004,"Payroll Payout",Expenses!$J5:$J1004,$R36,Expenses!$E5:$E1004,$A36)),"")) | K36: =IF($H36="","",N($H36)-N($I36)-N($J36)) | L36: =IF($K36="","",IF($K36>0.5,"TO PAY",IF($K36<-0.5,"ADVANCE / OWES","SETTLED"))) | R36: 46082
A37: =IF(Setup!$A79="","",Setup!$A79) | B37: =IF($A37="","",Setup!$B79) | C37: =IF($A37="","",IF(COUNTIFS(Trips!$Z5:$Z1004,$R37,Trips!$D5:$D1004,$A37)+COUNTIFS(Trips!$Z5:$Z1004,$R37,Trips!$E5:$E1004,$A37)=0,"",COUNTIFS(Trips!$Z5:$Z1004,$R37,Trips!$D5:$D1004,$A37)+COUNTIFS(Trips!$Z5:$Z1004,$R37,Trips!$E5:$E1004,$A37))) | D37: =IF($C37="","",SUMIFS(Trips!$K5:$K1004,Trips!$Z5:$Z1004,$R37,Trips!$D5:$D1004,$A37)+SUMIFS(Trips!$K5:$K1004,Trips!$Z5:$Z1004,$R37,Trips!$E5:$E1004,$A37)) | E37: =IF($C37="","",SUMIFS(Trips!$N5:$N1004,Trips!$Z5:$Z1004,$R37,Trips!$D5:$D1004,$A37)+SUMIFS(Trips!$O5:$O1004,Trips!$Z5:$Z1004,$R37,Trips!$E5:$E1004,$A37)) | F37: =IF($C37="","",SUMIFS(Trips!$P5:$P1004,Trips!$Z5:$Z1004,$R37,Trips!$D5:$D1004,$A37)) | G37: =IF($C37="","",SUMIFS(Trips!$Q5:$Q1004,Trips!$Z5:$Z1004,$R37,Trips!$D5:$D1004,$A37)) | H37: =IF(AND($C37="",$I37="",$J37=""),"",N($E37)+N($F37)+N($G37)) | I37: =IF($A37="","",IFERROR(1/(1/SUMIFS(Expenses!$F5:$F1004,Expenses!$B5:$B1004,"Cash Advance",Expenses!$J5:$J1004,$R37,Expenses!$E5:$E1004,$A37)),"")) | J37: =IF($A37="","",IFERROR(1/(1/SUMIFS(Expenses!$F5:$F1004,Expenses!$B5:$B1004,"Payroll Payout",Expenses!$J5:$J1004,$R37,Expenses!$E5:$E1004,$A37)),"")) | K37: =IF($H37="","",N($H37)-N($I37)-N($J37)) | L37: =IF($K37="","",IF($K37>0.5,"TO PAY",IF($K37<-0.5,"ADVANCE / OWES","SETTLED"))) | R37: 46082
A38: =IF(Setup!$A80="","",Setup!$A80) | B38: =IF($A38="","",Setup!$B80) | C38: =IF($A38="","",IF(COUNTIFS(Trips!$Z5:$Z1004,$R38,Trips!$D5:$D1004,$A38)+COUNTIFS(Trips!$Z5:$Z1004,$R38,Trips!$E5:$E1004,$A38)=0,"",COUNTIFS(Trips!$Z5:$Z1004,$R38,Trips!$D5:$D1004,$A38)+COUNTIFS(Trips!$Z5:$Z1004,$R38,Trips!$E5:$E1004,$A38))) | D38: =IF($C38="","",SUMIFS(Trips!$K5:$K1004,Trips!$Z5:$Z1004,$R38,Trips!$D5:$D1004,$A38)+SUMIFS(Trips!$K5:$K1004,Trips!$Z5:$Z1004,$R38,Trips!$E5:$E1004,$A38)) | E38: =IF($C38="","",SUMIFS(Trips!$N5:$N1004,Trips!$Z5:$Z1004,$R38,Trips!$D5:$D1004,$A38)+SUMIFS(Trips!$O5:$O1004,Trips!$Z5:$Z1004,$R38,Trips!$E5:$E1004,$A38)) | F38: =IF($C38="","",SUMIFS(Trips!$P5:$P1004,Trips!$Z5:$Z1004,$R38,Trips!$D5:$D1004,$A38)) | G38: =IF($C38="","",SUMIFS(Trips!$Q5:$Q1004,Trips!$Z5:$Z1004,$R38,Trips!$D5:$D1004,$A38)) | H38: =IF(AND($C38="",$I38="",$J38=""),"",N($E38)+N($F38)+N($G38)) | I38: =IF($A38="","",IFERROR(1/(1/SUMIFS(Expenses!$F5:$F1004,Expenses!$B5:$B1004,"Cash Advance",Expenses!$J5:$J1004,$R38,Expenses!$E5:$E1004,$A38)),"")) | J38: =IF($A38="","",IFERROR(1/(1/SUMIFS(Expenses!$F5:$F1004,Expenses!$B5:$B1004,"Payroll Payout",Expenses!$J5:$J1004,$R38,Expenses!$E5:$E1004,$A38)),"")) | K38: =IF($H38="","",N($H38)-N($I38)-N($J38)) | L38: =IF($K38="","",IF($K38>0.5,"TO PAY",IF($K38<-0.5,"ADVANCE / OWES","SETTLED"))) | R38: 46082
A39: =IF(Setup!$A81="","",Setup!$A81) | B39: =IF($A39="","",Setup!$B81) | C39: =IF($A39="","",IF(COUNTIFS(Trips!$Z5:$Z1004,$R39,Trips!$D5:$D1004,$A39)+COUNTIFS(Trips!$Z5:$Z1004,$R39,Trips!$E5:$E1004,$A39)=0,"",COUNTIFS(Trips!$Z5:$Z1004,$R39,Trips!$D5:$D1004,$A39)+COUNTIFS(Trips!$Z5:$Z1004,$R39,Trips!$E5:$E1004,$A39))) | D39: =IF($C39="","",SUMIFS(Trips!$K5:$K1004,Trips!$Z5:$Z1004,$R39,Trips!$D5:$D1004,$A39)+SUMIFS(Trips!$K5:$K1004,Trips!$Z5:$Z1004,$R39,Trips!$E5:$E1004,$A39)) | E39: =IF($C39="","",SUMIFS(Trips!$N5:$N1004,Trips!$Z5:$Z1004,$R39,Trips!$D5:$D1004,$A39)+SUMIFS(Trips!$O5:$O1004,Trips!$Z5:$Z1004,$R39,Trips!$E5:$E1004,$A39)) | F39: =IF($C39="","",SUMIFS(Trips!$P5:$P1004,Trips!$Z5:$Z1004,$R39,Trips!$D5:$D1004,$A39)) | G39: =IF($C39="","",SUMIFS(Trips!$Q5:$Q1004,Trips!$Z5:$Z1004,$R39,Trips!$D5:$D1004,$A39)) | H39: =IF(AND($C39="",$I39="",$J39=""),"",N($E39)+N($F39)+N($G39)) | I39: =IF($A39="","",IFERROR(1/(1/SUMIFS(Expenses!$F5:$F1004,Expenses!$B5:$B1004,"Cash Advance",Expenses!$J5:$J1004,$R39,Expenses!$E5:$E1004,$A39)),"")) | J39: =IF($A39="","",IFERROR(1/(1/SUMIFS(Expenses!$F5:$F1004,Expenses!$B5:$B1004,"Payroll Payout",Expenses!$J5:$J1004,$R39,Expenses!$E5:$E1004,$A39)),"")) | K39: =IF($H39="","",N($H39)-N($I39)-N($J39)) | L39: =IF($K39="","",IF($K39>0.5,"TO PAY",IF($K39<-0.5,"ADVANCE / OWES","SETTLED"))) | R39: 46082
A40: =IF(Setup!$A82="","",Setup!$A82) | B40: =IF($A40="","",Setup!$B82) | C40: =IF($A40="","",IF(COUNTIFS(Trips!$Z5:$Z1004,$R40,Trips!$D5:$D1004,$A40)+COUNTIFS(Trips!$Z5:$Z1004,$R40,Trips!$E5:$E1004,$A40)=0,"",COUNTIFS(Trips!$Z5:$Z1004,$R40,Trips!$D5:$D1004,$A40)+COUNTIFS(Trips!$Z5:$Z1004,$R40,Trips!$E5:$E1004,$A40))) | D40: =IF($C40="","",SUMIFS(Trips!$K5:$K1004,Trips!$Z5:$Z1004,$R40,Trips!$D5:$D1004,$A40)+SUMIFS(Trips!$K5:$K1004,Trips!$Z5:$Z1004,$R40,Trips!$E5:$E1004,$A40)) | E40: =IF($C40="","",SUMIFS(Trips!$N5:$N1004,Trips!$Z5:$Z1004,$R40,Trips!$D5:$D1004,$A40)+SUMIFS(Trips!$O5:$O1004,Trips!$Z5:$Z1004,$R40,Trips!$E5:$E1004,$A40)) | F40: =IF($C40="","",SUMIFS(Trips!$P5:$P1004,Trips!$Z5:$Z1004,$R40,Trips!$D5:$D1004,$A40)) | G40: =IF($C40="","",SUMIFS(Trips!$Q5:$Q1004,Trips!$Z5:$Z1004,$R40,Trips!$D5:$D1004,$A40)) | H40: =IF(AND($C40="",$I40="",$J40=""),"",N($E40)+N($F40)+N($G40)) | I40: =IF($A40="","",IFERROR(1/(1/SUMIFS(Expenses!$F5:$F1004,Expenses!$B5:$B1004,"Cash Advance",Expenses!$J5:$J1004,$R40,Expenses!$E5:$E1004,$A40)),"")) | J40: =IF($A40="","",IFERROR(1/(1/SUMIFS(Expenses!$F5:$F1004,Expenses!$B5:$B1004,"Payroll Payout",Expenses!$J5:$J1004,$R40,Expenses!$E5:$E1004,$A40)),"")) | K40: =IF($H40="","",N($H40)-N($I40)-N($J40)) | L40: =IF($K40="","",IF($K40>0.5,"TO PAY",IF($K40<-0.5,"ADVANCE / OWES","SETTLED"))) | R40: 46082
A41: =IF(Setup!$A83="","",Setup!$A83) | B41: =IF($A41="","",Setup!$B83) | C41: =IF($A41="","",IF(COUNTIFS(Trips!$Z5:$Z1004,$R41,Trips!$D5:$D1004,$A41)+COUNTIFS(Trips!$Z5:$Z1004,$R41,Trips!$E5:$E1004,$A41)=0,"",COUNTIFS(Trips!$Z5:$Z1004,$R41,Trips!$D5:$D1004,$A41)+COUNTIFS(Trips!$Z5:$Z1004,$R41,Trips!$E5:$E1004,$A41))) | D41: =IF($C41="","",SUMIFS(Trips!$K5:$K1004,Trips!$Z5:$Z1004,$R41,Trips!$D5:$D1004,$A41)+SUMIFS(Trips!$K5:$K1004,Trips!$Z5:$Z1004,$R41,Trips!$E5:$E1004,$A41)) | E41: =IF($C41="","",SUMIFS(Trips!$N5:$N1004,Trips!$Z5:$Z1004,$R41,Trips!$D5:$D1004,$A41)+SUMIFS(Trips!$O5:$O1004,Trips!$Z5:$Z1004,$R41,Trips!$E5:$E1004,$A41)) | F41: =IF($C41="","",SUMIFS(Trips!$P5:$P1004,Trips!$Z5:$Z1004,$R41,Trips!$D5:$D1004,$A41)) | G41: =IF($C41="","",SUMIFS(Trips!$Q5:$Q1004,Trips!$Z5:$Z1004,$R41,Trips!$D5:$D1004,$A41)) | H41: =IF(AND($C41="",$I41="",$J41=""),"",N($E41)+N($F41)+N($G41)) | I41: =IF($A41="","",IFERROR(1/(1/SUMIFS(Expenses!$F5:$F1004,Expenses!$B5:$B1004,"Cash Advance",Expenses!$J5:$J1004,$R41,Expenses!$E5:$E1004,$A41)),"")) | J41: =IF($A41="","",IFERROR(1/(1/SUMIFS(Expenses!$F5:$F1004,Expenses!$B5:$B1004,"Payroll Payout",Expenses!$J5:$J1004,$R41,Expenses!$E5:$E1004,$A41)),"")) | K41: =IF($H41="","",N($H41)-N($I41)-N($J41)) | L41: =IF($K41="","",IF($K41>0.5,"TO PAY",IF($K41<-0.5,"ADVANCE / OWES","SETTLED"))) | R41: 46082
A42: =IF(Setup!$A84="","",Setup!$A84) | B42: =IF($A42="","",Setup!$B84) | C42: =IF($A42="","",IF(COUNTIFS(Trips!$Z5:$Z1004,$R42,Trips!$D5:$D1004,$A42)+COUNTIFS(Trips!$Z5:$Z1004,$R42,Trips!$E5:$E1004,$A42)=0,"",COUNTIFS(Trips!$Z5:$Z1004,$R42,Trips!$D5:$D1004,$A42)+COUNTIFS(Trips!$Z5:$Z1004,$R42,Trips!$E5:$E1004,$A42))) | D42: =IF($C42="","",SUMIFS(Trips!$K5:$K1004,Trips!$Z5:$Z1004,$R42,Trips!$D5:$D1004,$A42)+SUMIFS(Trips!$K5:$K1004,Trips!$Z5:$Z1004,$R42,Trips!$E5:$E1004,$A42)) | E42: =IF($C42="","",SUMIFS(Trips!$N5:$N1004,Trips!$Z5:$Z1004,$R42,Trips!$D5:$D1004,$A42)+SUMIFS(Trips!$O5:$O1004,Trips!$Z5:$Z1004,$R42,Trips!$E5:$E1004,$A42)) | F42: =IF($C42="","",SUMIFS(Trips!$P5:$P1004,Trips!$Z5:$Z1004,$R42,Trips!$D5:$D1004,$A42)) | G42: =IF($C42="","",SUMIFS(Trips!$Q5:$Q1004,Trips!$Z5:$Z1004,$R42,Trips!$D5:$D1004,$A42)) | H42: =IF(AND($C42="",$I42="",$J42=""),"",N($E42)+N($F42)+N($G42)) | I42: =IF($A42="","",IFERROR(1/(1/SUMIFS(Expenses!$F5:$F1004,Expenses!$B5:$B1004,"Cash Advance",Expenses!$J5:$J1004,$R42,Expenses!$E5:$E1004,$A42)),"")) | J42: =IF($A42="","",IFERROR(1/(1/SUMIFS(Expenses!$F5:$F1004,Expenses!$B5:$B1004,"Payroll Payout",Expenses!$J5:$J1004,$R42,Expenses!$E5:$E1004,$A42)),"")) | K42: =IF($H42="","",N($H42)-N($I42)-N($J42)) | L42: =IF($K42="","",IF($K42>0.5,"TO PAY",IF($K42<-0.5,"ADVANCE / OWES","SETTLED"))) | R42: 46082
A43: =IF(Setup!$A85="","",Setup!$A85) | B43: =IF($A43="","",Setup!$B85) | C43: =IF($A43="","",IF(COUNTIFS(Trips!$Z5:$Z1004,$R43,Trips!$D5:$D1004,$A43)+COUNTIFS(Trips!$Z5:$Z1004,$R43,Trips!$E5:$E1004,$A43)=0,"",COUNTIFS(Trips!$Z5:$Z1004,$R43,Trips!$D5:$D1004,$A43)+COUNTIFS(Trips!$Z5:$Z1004,$R43,Trips!$E5:$E1004,$A43))) | D43: =IF($C43="","",SUMIFS(Trips!$K5:$K1004,Trips!$Z5:$Z1004,$R43,Trips!$D5:$D1004,$A43)+SUMIFS(Trips!$K5:$K1004,Trips!$Z5:$Z1004,$R43,Trips!$E5:$E1004,$A43)) | E43: =IF($C43="","",SUMIFS(Trips!$N5:$N1004,Trips!$Z5:$Z1004,$R43,Trips!$D5:$D1004,$A43)+SUMIFS(Trips!$O5:$O1004,Trips!$Z5:$Z1004,$R43,Trips!$E5:$E1004,$A43)) | F43: =IF($C43="","",SUMIFS(Trips!$P5:$P1004,Trips!$Z5:$Z1004,$R43,Trips!$D5:$D1004,$A43)) | G43: =IF($C43="","",SUMIFS(Trips!$Q5:$Q1004,Trips!$Z5:$Z1004,$R43,Trips!$D5:$D1004,$A43)) | H43: =IF(AND($C43="",$I43="",$J43=""),"",N($E43)+N($F43)+N($G43)) | I43: =IF($A43="","",IFERROR(1/(1/SUMIFS(Expenses!$F5:$F1004,Expenses!$B5:$B1004,"Cash Advance",Expenses!$J5:$J1004,$R43,Expenses!$E5:$E1004,$A43)),"")) | J43: =IF($A43="","",IFERROR(1/(1/SUMIFS(Expenses!$F5:$F1004,Expenses!$B5:$B1004,"Payroll Payout",Expenses!$J5:$J1004,$R43,Expenses!$E5:$E1004,$A43)),"")) | K43: =IF($H43="","",N($H43)-N($I43)-N($J43)) | L43: =IF($K43="","",IF($K43>0.5,"TO PAY",IF($K43<-0.5,"ADVANCE / OWES","SETTLED"))) | R43: 46082
A44: =IF(Setup!$A86="","",Setup!$A86) | B44: =IF($A44="","",Setup!$B86) | C44: =IF($A44="","",IF(COUNTIFS(Trips!$Z5:$Z1004,$R44,Trips!$D5:$D1004,$A44)+COUNTIFS(Trips!$Z5:$Z1004,$R44,Trips!$E5:$E1004,$A44)=0,"",COUNTIFS(Trips!$Z5:$Z1004,$R44,Trips!$D5:$D1004,$A44)+COUNTIFS(Trips!$Z5:$Z1004,$R44,Trips!$E5:$E1004,$A44))) | D44: =IF($C44="","",SUMIFS(Trips!$K5:$K1004,Trips!$Z5:$Z1004,$R44,Trips!$D5:$D1004,$A44)+SUMIFS(Trips!$K5:$K1004,Trips!$Z5:$Z1004,$R44,Trips!$E5:$E1004,$A44)) | E44: =IF($C44="","",SUMIFS(Trips!$N5:$N1004,Trips!$Z5:$Z1004,$R44,Trips!$D5:$D1004,$A44)+SUMIFS(Trips!$O5:$O1004,Trips!$Z5:$Z1004,$R44,Trips!$E5:$E1004,$A44)) | F44: =IF($C44="","",SUMIFS(Trips!$P5:$P1004,Trips!$Z5:$Z1004,$R44,Trips!$D5:$D1004,$A44)) | G44: =IF($C44="","",SUMIFS(Trips!$Q5:$Q1004,Trips!$Z5:$Z1004,$R44,Trips!$D5:$D1004,$A44)) | H44: =IF(AND($C44="",$I44="",$J44=""),"",N($E44)+N($F44)+N($G44)) | I44: =IF($A44="","",IFERROR(1/(1/SUMIFS(Expenses!$F5:$F1004,Expenses!$B5:$B1004,"Cash Advance",Expenses!$J5:$J1004,$R44,Expenses!$E5:$E1004,$A44)),"")) | J44: =IF($A44="","",IFERROR(1/(1/SUMIFS(Expenses!$F5:$F1004,Expenses!$B5:$B1004,"Payroll Payout",Expenses!$J5:$J1004,$R44,Expenses!$E5:$E1004,$A44)),"")) | K44: =IF($H44="","",N($H44)-N($I44)-N($J44)) | L44: =IF($K44="","",IF($K44>0.5,"TO PAY",IF($K44<-0.5,"ADVANCE / OWES","SETTLED"))) | R44: 46082
A45: =IF(Setup!$A87="","",Setup!$A87) | B45: =IF($A45="","",Setup!$B87) | C45: =IF($A45="","",IF(COUNTIFS(Trips!$Z5:$Z1004,$R45,Trips!$D5:$D1004,$A45)+COUNTIFS(Trips!$Z5:$Z1004,$R45,Trips!$E5:$E1004,$A45)=0,"",COUNTIFS(Trips!$Z5:$Z1004,$R45,Trips!$D5:$D1004,$A45)+COUNTIFS(Trips!$Z5:$Z1004,$R45,Trips!$E5:$E1004,$A45))) | D45: =IF($C45="","",SUMIFS(Trips!$K5:$K1004,Trips!$Z5:$Z1004,$R45,Trips!$D5:$D1004,$A45)+SUMIFS(Trips!$K5:$K1004,Trips!$Z5:$Z1004,$R45,Trips!$E5:$E1004,$A45)) | E45: =IF($C45="","",SUMIFS(Trips!$N5:$N1004,Trips!$Z5:$Z1004,$R45,Trips!$D5:$D1004,$A45)+SUMIFS(Trips!$O5:$O1004,Trips!$Z5:$Z1004,$R45,Trips!$E5:$E1004,$A45)) | F45: =IF($C45="","",SUMIFS(Trips!$P5:$P1004,Trips!$Z5:$Z1004,$R45,Trips!$D5:$D1004,$A45)) | G45: =IF($C45="","",SUMIFS(Trips!$Q5:$Q1004,Trips!$Z5:$Z1004,$R45,Trips!$D5:$D1004,$A45)) | H45: =IF(AND($C45="",$I45="",$J45=""),"",N($E45)+N($F45)+N($G45)) | I45: =IF($A45="","",IFERROR(1/(1/SUMIFS(Expenses!$F5:$F1004,Expenses!$B5:$B1004,"Cash Advance",Expenses!$J5:$J1004,$R45,Expenses!$E5:$E1004,$A45)),"")) | J45: =IF($A45="","",IFERROR(1/(1/SUMIFS(Expenses!$F5:$F1004,Expenses!$B5:$B1004,"Payroll Payout",Expenses!$J5:$J1004,$R45,Expenses!$E5:$E1004,$A45)),"")) | K45: =IF($H45="","",N($H45)-N($I45)-N($J45)) | L45: =IF($K45="","",IF($K45>0.5,"TO PAY",IF($K45<-0.5,"ADVANCE / OWES","SETTLED"))) | R45: 46082
A46: MONTH TOTAL | C46: =IF(COUNT(C34:C45)=0,"",SUM(C34:C45)) | D46: =IF(COUNT(D34:D45)=0,"",SUM(D34:D45)) | E46: =IF(COUNT(E34:E45)=0,"",SUM(E34:E45)) | F46: =IF(COUNT(F34:F45)=0,"",SUM(F34:F45)) | G46: =IF(COUNT(G34:G45)=0,"",SUM(G34:G45)) | H46: =IF(COUNT(H34:H45)=0,"",SUM(H34:H45)) | I46: =IF(COUNT(I34:I45)=0,"",SUM(I34:I45)) | J46: =IF(COUNT(J34:J45)=0,"",SUM(J34:J45)) | K46: =IF(COUNT(K34:K45)=0,"",SUM(K34:K45))
A47: APRIL 2026 · crew earnings & settlement
A48: =IF(Setup!$A76="","",Setup!$A76) | B48: =IF($A48="","",Setup!$B76) | C48: =IF($A48="","",IF(COUNTIFS(Trips!$Z5:$Z1004,$R48,Trips!$D5:$D1004,$A48)+COUNTIFS(Trips!$Z5:$Z1004,$R48,Trips!$E5:$E1004,$A48)=0,"",COUNTIFS(Trips!$Z5:$Z1004,$R48,Trips!$D5:$D1004,$A48)+COUNTIFS(Trips!$Z5:$Z1004,$R48,Trips!$E5:$E1004,$A48))) | D48: =IF($C48="","",SUMIFS(Trips!$K5:$K1004,Trips!$Z5:$Z1004,$R48,Trips!$D5:$D1004,$A48)+SUMIFS(Trips!$K5:$K1004,Trips!$Z5:$Z1004,$R48,Trips!$E5:$E1004,$A48)) | E48: =IF($C48="","",SUMIFS(Trips!$N5:$N1004,Trips!$Z5:$Z1004,$R48,Trips!$D5:$D1004,$A48)+SUMIFS(Trips!$O5:$O1004,Trips!$Z5:$Z1004,$R48,Trips!$E5:$E1004,$A48)) | F48: =IF($C48="","",SUMIFS(Trips!$P5:$P1004,Trips!$Z5:$Z1004,$R48,Trips!$D5:$D1004,$A48)) | G48: =IF($C48="","",SUMIFS(Trips!$Q5:$Q1004,Trips!$Z5:$Z1004,$R48,Trips!$D5:$D1004,$A48)) | H48: =IF(AND($C48="",$I48="",$J48=""),"",N($E48)+N($F48)+N($G48)) | I48: =IF($A48="","",IFERROR(1/(1/SUMIFS(Expenses!$F5:$F1004,Expenses!$B5:$B1004,"Cash Advance",Expenses!$J5:$J1004,$R48,Expenses!$E5:$E1004,$A48)),"")) | J48: =IF($A48="","",IFERROR(1/(1/SUMIFS(Expenses!$F5:$F1004,Expenses!$B5:$B1004,"Payroll Payout",Expenses!$J5:$J1004,$R48,Expenses!$E5:$E1004,$A48)),"")) | K48: =IF($H48="","",N($H48)-N($I48)-N($J48)) | L48: =IF($K48="","",IF($K48>0.5,"TO PAY",IF($K48<-0.5,"ADVANCE / OWES","SETTLED"))) | R48: 46113
A49: =IF(Setup!$A77="","",Setup!$A77) | B49: =IF($A49="","",Setup!$B77) | C49: =IF($A49="","",IF(COUNTIFS(Trips!$Z5:$Z1004,$R49,Trips!$D5:$D1004,$A49)+COUNTIFS(Trips!$Z5:$Z1004,$R49,Trips!$E5:$E1004,$A49)=0,"",COUNTIFS(Trips!$Z5:$Z1004,$R49,Trips!$D5:$D1004,$A49)+COUNTIFS(Trips!$Z5:$Z1004,$R49,Trips!$E5:$E1004,$A49))) | D49: =IF($C49="","",SUMIFS(Trips!$K5:$K1004,Trips!$Z5:$Z1004,$R49,Trips!$D5:$D1004,$A49)+SUMIFS(Trips!$K5:$K1004,Trips!$Z5:$Z1004,$R49,Trips!$E5:$E1004,$A49)) | E49: =IF($C49="","",SUMIFS(Trips!$N5:$N1004,Trips!$Z5:$Z1004,$R49,Trips!$D5:$D1004,$A49)+SUMIFS(Trips!$O5:$O1004,Trips!$Z5:$Z1004,$R49,Trips!$E5:$E1004,$A49)) | F49: =IF($C49="","",SUMIFS(Trips!$P5:$P1004,Trips!$Z5:$Z1004,$R49,Trips!$D5:$D1004,$A49)) | G49: =IF($C49="","",SUMIFS(Trips!$Q5:$Q1004,Trips!$Z5:$Z1004,$R49,Trips!$D5:$D1004,$A49)) | H49: =IF(AND($C49="",$I49="",$J49=""),"",N($E49)+N($F49)+N($G49)) | I49: =IF($A49="","",IFERROR(1/(1/SUMIFS(Expenses!$F5:$F1004,Expenses!$B5:$B1004,"Cash Advance",Expenses!$J5:$J1004,$R49,Expenses!$E5:$E1004,$A49)),"")) | J49: =IF($A49="","",IFERROR(1/(1/SUMIFS(Expenses!$F5:$F1004,Expenses!$B5:$B1004,"Payroll Payout",Expenses!$J5:$J1004,$R49,Expenses!$E5:$E1004,$A49)),"")) | K49: =IF($H49="","",N($H49)-N($I49)-N($J49)) | L49: =IF($K49="","",IF($K49>0.5,"TO PAY",IF($K49<-0.5,"ADVANCE / OWES","SETTLED"))) | R49: 46113
A50: =IF(Setup!$A78="","",Setup!$A78) | B50: =IF($A50="","",Setup!$B78) | C50: =IF($A50="","",IF(COUNTIFS(Trips!$Z5:$Z1004,$R50,Trips!$D5:$D1004,$A50)+COUNTIFS(Trips!$Z5:$Z1004,$R50,Trips!$E5:$E1004,$A50)=0,"",COUNTIFS(Trips!$Z5:$Z1004,$R50,Trips!$D5:$D1004,$A50)+COUNTIFS(Trips!$Z5:$Z1004,$R50,Trips!$E5:$E1004,$A50))) | D50: =IF($C50="","",SUMIFS(Trips!$K5:$K1004,Trips!$Z5:$Z1004,$R50,Trips!$D5:$D1004,$A50)+SUMIFS(Trips!$K5:$K1004,Trips!$Z5:$Z1004,$R50,Trips!$E5:$E1004,$A50)) | E50: =IF($C50="","",SUMIFS(Trips!$N5:$N1004,Trips!$Z5:$Z1004,$R50,Trips!$D5:$D1004,$A50)+SUMIFS(Trips!$O5:$O1004,Trips!$Z5:$Z1004,$R50,Trips!$E5:$E1004,$A50)) | F50: =IF($C50="","",SUMIFS(Trips!$P5:$P1004,Trips!$Z5:$Z1004,$R50,Trips!$D5:$D1004,$A50)) | G50: =IF($C50="","",SUMIFS(Trips!$Q5:$Q1004,Trips!$Z5:$Z1004,$R50,Trips!$D5:$D1004,$A50)) | H50: =IF(AND($C50="",$I50="",$J50=""),"",N($E50)+N($F50)+N($G50)) | I50: =IF($A50="","",IFERROR(1/(1/SUMIFS(Expenses!$F5:$F1004,Expenses!$B5:$B1004,"Cash Advance",Expenses!$J5:$J1004,$R50,Expenses!$E5:$E1004,$A50)),"")) | J50: =IF($A50="","",IFERROR(1/(1/SUMIFS(Expenses!$F5:$F1004,Expenses!$B5:$B1004,"Payroll Payout",Expenses!$J5:$J1004,$R50,Expenses!$E5:$E1004,$A50)),"")) | K50: =IF($H50="","",N($H50)-N($I50)-N($J50)) | L50: =IF($K50="","",IF($K50>0.5,"TO PAY",IF($K50<-0.5,"ADVANCE / OWES","SETTLED"))) | R50: 46113
A51: =IF(Setup!$A79="","",Setup!$A79) | B51: =IF($A51="","",Setup!$B79) | C51: =IF($A51="","",IF(COUNTIFS(Trips!$Z5:$Z1004,$R51,Trips!$D5:$D1004,$A51)+COUNTIFS(Trips!$Z5:$Z1004,$R51,Trips!$E5:$E1004,$A51)=0,"",COUNTIFS(Trips!$Z5:$Z1004,$R51,Trips!$D5:$D1004,$A51)+COUNTIFS(Trips!$Z5:$Z1004,$R51,Trips!$E5:$E1004,$A51))) | D51: =IF($C51="","",SUMIFS(Trips!$K5:$K1004,Trips!$Z5:$Z1004,$R51,Trips!$D5:$D1004,$A51)+SUMIFS(Trips!$K5:$K1004,Trips!$Z5:$Z1004,$R51,Trips!$E5:$E1004,$A51)) | E51: =IF($C51="","",SUMIFS(Trips!$N5:$N1004,Trips!$Z5:$Z1004,$R51,Trips!$D5:$D1004,$A51)+SUMIFS(Trips!$O5:$O1004,Trips!$Z5:$Z1004,$R51,Trips!$E5:$E1004,$A51)) | F51: =IF($C51="","",SUMIFS(Trips!$P5:$P1004,Trips!$Z5:$Z1004,$R51,Trips!$D5:$D1004,$A51)) | G51: =IF($C51="","",SUMIFS(Trips!$Q5:$Q1004,Trips!$Z5:$Z1004,$R51,Trips!$D5:$D1004,$A51)) | H51: =IF(AND($C51="",$I51="",$J51=""),"",N($E51)+N($F51)+N($G51)) | I51: =IF($A51="","",IFERROR(1/(1/SUMIFS(Expenses!$F5:$F1004,Expenses!$B5:$B1004,"Cash Advance",Expenses!$J5:$J1004,$R51,Expenses!$E5:$E1004,$A51)),"")) | J51: =IF($A51="","",IFERROR(1/(1/SUMIFS(Expenses!$F5:$F1004,Expenses!$B5:$B1004,"Payroll Payout",Expenses!$J5:$J1004,$R51,Expenses!$E5:$E1004,$A51)),"")) | K51: =IF($H51="","",N($H51)-N($I51)-N($J51)) | L51: =IF($K51="","",IF($K51>0.5,"TO PAY",IF($K51<-0.5,"ADVANCE / OWES","SETTLED"))) | R51: 46113
A52: =IF(Setup!$A80="","",Setup!$A80) | B52: =IF($A52="","",Setup!$B80) | C52: =IF($A52="","",IF(COUNTIFS(Trips!$Z5:$Z1004,$R52,Trips!$D5:$D1004,$A52)+COUNTIFS(Trips!$Z5:$Z1004,$R52,Trips!$E5:$E1004,$A52)=0,"",COUNTIFS(Trips!$Z5:$Z1004,$R52,Trips!$D5:$D1004,$A52)+COUNTIFS(Trips!$Z5:$Z1004,$R52,Trips!$E5:$E1004,$A52))) | D52: =IF($C52="","",SUMIFS(Trips!$K5:$K1004,Trips!$Z5:$Z1004,$R52,Trips!$D5:$D1004,$A52)+SUMIFS(Trips!$K5:$K1004,Trips!$Z5:$Z1004,$R52,Trips!$E5:$E1004,$A52)) | E52: =IF($C52="","",SUMIFS(Trips!$N5:$N1004,Trips!$Z5:$Z1004,$R52,Trips!$D5:$D1004,$A52)+SUMIFS(Trips!$O5:$O1004,Trips!$Z5:$Z1004,$R52,Trips!$E5:$E1004,$A52)) | F52: =IF($C52="","",SUMIFS(Trips!$P5:$P1004,Trips!$Z5:$Z1004,$R52,Trips!$D5:$D1004,$A52)) | G52: =IF($C52="","",SUMIFS(Trips!$Q5:$Q1004,Trips!$Z5:$Z1004,$R52,Trips!$D5:$D1004,$A52)) | H52: =IF(AND($C52="",$I52="",$J52=""),"",N($E52)+N($F52)+N($G52)) | I52: =IF($A52="","",IFERROR(1/(1/SUMIFS(Expenses!$F5:$F1004,Expenses!$B5:$B1004,"Cash Advance",Expenses!$J5:$J1004,$R52,Expenses!$E5:$E1004,$A52)),"")) | J52: =IF($A52="","",IFERROR(1/(1/SUMIFS(Expenses!$F5:$F1004,Expenses!$B5:$B1004,"Payroll Payout",Expenses!$J5:$J1004,$R52,Expenses!$E5:$E1004,$A52)),"")) | K52: =IF($H52="","",N($H52)-N($I52)-N($J52)) | L52: =IF($K52="","",IF($K52>0.5,"TO PAY",IF($K52<-0.5,"ADVANCE / OWES","SETTLED"))) | R52: 46113
A53: =IF(Setup!$A81="","",Setup!$A81) | B53: =IF($A53="","",Setup!$B81) | C53: =IF($A53="","",IF(COUNTIFS(Trips!$Z5:$Z1004,$R53,Trips!$D5:$D1004,$A53)+COUNTIFS(Trips!$Z5:$Z1004,$R53,Trips!$E5:$E1004,$A53)=0,"",COUNTIFS(Trips!$Z5:$Z1004,$R53,Trips!$D5:$D1004,$A53)+COUNTIFS(Trips!$Z5:$Z1004,$R53,Trips!$E5:$E1004,$A53))) | D53: =IF($C53="","",SUMIFS(Trips!$K5:$K1004,Trips!$Z5:$Z1004,$R53,Trips!$D5:$D1004,$A53)+SUMIFS(Trips!$K5:$K1004,Trips!$Z5:$Z1004,$R53,Trips!$E5:$E1004,$A53)) | E53: =IF($C53="","",SUMIFS(Trips!$N5:$N1004,Trips!$Z5:$Z1004,$R53,Trips!$D5:$D1004,$A53)+SUMIFS(Trips!$O5:$O1004,Trips!$Z5:$Z1004,$R53,Trips!$E5:$E1004,$A53)) | F53: =IF($C53="","",SUMIFS(Trips!$P5:$P1004,Trips!$Z5:$Z1004,$R53,Trips!$D5:$D1004,$A53)) | G53: =IF($C53="","",SUMIFS(Trips!$Q5:$Q1004,Trips!$Z5:$Z1004,$R53,Trips!$D5:$D1004,$A53)) | H53: =IF(AND($C53="",$I53="",$J53=""),"",N($E53)+N($F53)+N($G53)) | I53: =IF($A53="","",IFERROR(1/(1/SUMIFS(Expenses!$F5:$F1004,Expenses!$B5:$B1004,"Cash Advance",Expenses!$J5:$J1004,$R53,Expenses!$E5:$E1004,$A53)),"")) | J53: =IF($A53="","",IFERROR(1/(1/SUMIFS(Expenses!$F5:$F1004,Expenses!$B5:$B1004,"Payroll Payout",Expenses!$J5:$J1004,$R53,Expenses!$E5:$E1004,$A53)),"")) | K53: =IF($H53="","",N($H53)-N($I53)-N($J53)) | L53: =IF($K53="","",IF($K53>0.5,"TO PAY",IF($K53<-0.5,"ADVANCE / OWES","SETTLED"))) | R53: 46113
A54: =IF(Setup!$A82="","",Setup!$A82) | B54: =IF($A54="","",Setup!$B82) | C54: =IF($A54="","",IF(COUNTIFS(Trips!$Z5:$Z1004,$R54,Trips!$D5:$D1004,$A54)+COUNTIFS(Trips!$Z5:$Z1004,$R54,Trips!$E5:$E1004,$A54)=0,"",COUNTIFS(Trips!$Z5:$Z1004,$R54,Trips!$D5:$D1004,$A54)+COUNTIFS(Trips!$Z5:$Z1004,$R54,Trips!$E5:$E1004,$A54))) | D54: =IF($C54="","",SUMIFS(Trips!$K5:$K1004,Trips!$Z5:$Z1004,$R54,Trips!$D5:$D1004,$A54)+SUMIFS(Trips!$K5:$K1004,Trips!$Z5:$Z1004,$R54,Trips!$E5:$E1004,$A54)) | E54: =IF($C54="","",SUMIFS(Trips!$N5:$N1004,Trips!$Z5:$Z1004,$R54,Trips!$D5:$D1004,$A54)+SUMIFS(Trips!$O5:$O1004,Trips!$Z5:$Z1004,$R54,Trips!$E5:$E1004,$A54)) | F54: =IF($C54="","",SUMIFS(Trips!$P5:$P1004,Trips!$Z5:$Z1004,$R54,Trips!$D5:$D1004,$A54)) | G54: =IF($C54="","",SUMIFS(Trips!$Q5:$Q1004,Trips!$Z5:$Z1004,$R54,Trips!$D5:$D1004,$A54)) | H54: =IF(AND($C54="",$I54="",$J54=""),"",N($E54)+N($F54)+N($G54)) | I54: =IF($A54="","",IFERROR(1/(1/SUMIFS(Expenses!$F5:$F1004,Expenses!$B5:$B1004,"Cash Advance",Expenses!$J5:$J1004,$R54,Expenses!$E5:$E1004,$A54)),"")) | J54: =IF($A54="","",IFERROR(1/(1/SUMIFS(Expenses!$F5:$F1004,Expenses!$B5:$B1004,"Payroll Payout",Expenses!$J5:$J1004,$R54,Expenses!$E5:$E1004,$A54)),"")) | K54: =IF($H54="","",N($H54)-N($I54)-N($J54)) | L54: =IF($K54="","",IF($K54>0.5,"TO PAY",IF($K54<-0.5,"ADVANCE / OWES","SETTLED"))) | R54: 46113
A55: =IF(Setup!$A83="","",Setup!$A83) | B55: =IF($A55="","",Setup!$B83) | C55: =IF($A55="","",IF(COUNTIFS(Trips!$Z5:$Z1004,$R55,Trips!$D5:$D1004,$A55)+COUNTIFS(Trips!$Z5:$Z1004,$R55,Trips!$E5:$E1004,$A55)=0,"",COUNTIFS(Trips!$Z5:$Z1004,$R55,Trips!$D5:$D1004,$A55)+COUNTIFS(Trips!$Z5:$Z1004,$R55,Trips!$E5:$E1004,$A55))) | D55: =IF($C55="","",SUMIFS(Trips!$K5:$K1004,Trips!$Z5:$Z1004,$R55,Trips!$D5:$D1004,$A55)+SUMIFS(Trips!$K5:$K1004,Trips!$Z5:$Z1004,$R55,Trips!$E5:$E1004,$A55)) | E55: =IF($C55="","",SUMIFS(Trips!$N5:$N1004,Trips!$Z5:$Z1004,$R55,Trips!$D5:$D1004,$A55)+SUMIFS(Trips!$O5:$O1004,Trips!$Z5:$Z1004,$R55,Trips!$E5:$E1004,$A55)) | F55: =IF($C55="","",SUMIFS(Trips!$P5:$P1004,Trips!$Z5:$Z1004,$R55,Trips!$D5:$D1004,$A55)) | G55: =IF($C55="","",SUMIFS(Trips!$Q5:$Q1004,Trips!$Z5:$Z1004,$R55,Trips!$D5:$D1004,$A55)) | H55: =IF(AND($C55="",$I55="",$J55=""),"",N($E55)+N($F55)+N($G55)) | I55: =IF($A55="","",IFERROR(1/(1/SUMIFS(Expenses!$F5:$F1004,Expenses!$B5:$B1004,"Cash Advance",Expenses!$J5:$J1004,$R55,Expenses!$E5:$E1004,$A55)),"")) | J55: =IF($A55="","",IFERROR(1/(1/SUMIFS(Expenses!$F5:$F1004,Expenses!$B5:$B1004,"Payroll Payout",Expenses!$J5:$J1004,$R55,Expenses!$E5:$E1004,$A55)),"")) | K55: =IF($H55="","",N($H55)-N($I55)-N($J55)) | L55: =IF($K55="","",IF($K55>0.5,"TO PAY",IF($K55<-0.5,"ADVANCE / OWES","SETTLED"))) | R55: 46113
A56: =IF(Setup!$A84="","",Setup!$A84) | B56: =IF($A56="","",Setup!$B84) | C56: =IF($A56="","",IF(COUNTIFS(Trips!$Z5:$Z1004,$R56,Trips!$D5:$D1004,$A56)+COUNTIFS(Trips!$Z5:$Z1004,$R56,Trips!$E5:$E1004,$A56)=0,"",COUNTIFS(Trips!$Z5:$Z1004,$R56,Trips!$D5:$D1004,$A56)+COUNTIFS(Trips!$Z5:$Z1004,$R56,Trips!$E5:$E1004,$A56))) | D56: =IF($C56="","",SUMIFS(Trips!$K5:$K1004,Trips!$Z5:$Z1004,$R56,Trips!$D5:$D1004,$A56)+SUMIFS(Trips!$K5:$K1004,Trips!$Z5:$Z1004,$R56,Trips!$E5:$E1004,$A56)) | E56: =IF($C56="","",SUMIFS(Trips!$N5:$N1004,Trips!$Z5:$Z1004,$R56,Trips!$D5:$D1004,$A56)+SUMIFS(Trips!$O5:$O1004,Trips!$Z5:$Z1004,$R56,Trips!$E5:$E1004,$A56)) | F56: =IF($C56="","",SUMIFS(Trips!$P5:$P1004,Trips!$Z5:$Z1004,$R56,Trips!$D5:$D1004,$A56)) | G56: =IF($C56="","",SUMIFS(Trips!$Q5:$Q1004,Trips!$Z5:$Z1004,$R56,Trips!$D5:$D1004,$A56)) | H56: =IF(AND($C56="",$I56="",$J56=""),"",N($E56)+N($F56)+N($G56)) | I56: =IF($A56="","",IFERROR(1/(1/SUMIFS(Expenses!$F5:$F1004,Expenses!$B5:$B1004,"Cash Advance",Expenses!$J5:$J1004,$R56,Expenses!$E5:$E1004,$A56)),"")) | J56: =IF($A56="","",IFERROR(1/(1/SUMIFS(Expenses!$F5:$F1004,Expenses!$B5:$B1004,"Payroll Payout",Expenses!$J5:$J1004,$R56,Expenses!$E5:$E1004,$A56)),"")) | K56: =IF($H56="","",N($H56)-N($I56)-N($J56)) | L56: =IF($K56="","",IF($K56>0.5,"TO PAY",IF($K56<-0.5,"ADVANCE / OWES","SETTLED"))) | R56: 46113
A57: =IF(Setup!$A85="","",Setup!$A85) | B57: =IF($A57="","",Setup!$B85) | C57: =IF($A57="","",IF(COUNTIFS(Trips!$Z5:$Z1004,$R57,Trips!$D5:$D1004,$A57)+COUNTIFS(Trips!$Z5:$Z1004,$R57,Trips!$E5:$E1004,$A57)=0,"",COUNTIFS(Trips!$Z5:$Z1004,$R57,Trips!$D5:$D1004,$A57)+COUNTIFS(Trips!$Z5:$Z1004,$R57,Trips!$E5:$E1004,$A57))) | D57: =IF($C57="","",SUMIFS(Trips!$K5:$K1004,Trips!$Z5:$Z1004,$R57,Trips!$D5:$D1004,$A57)+SUMIFS(Trips!$K5:$K1004,Trips!$Z5:$Z1004,$R57,Trips!$E5:$E1004,$A57)) | E57: =IF($C57="","",SUMIFS(Trips!$N5:$N1004,Trips!$Z5:$Z1004,$R57,Trips!$D5:$D1004,$A57)+SUMIFS(Trips!$O5:$O1004,Trips!$Z5:$Z1004,$R57,Trips!$E5:$E1004,$A57)) | F57: =IF($C57="","",SUMIFS(Trips!$P5:$P1004,Trips!$Z5:$Z1004,$R57,Trips!$D5:$D1004,$A57)) | G57: =IF($C57="","",SUMIFS(Trips!$Q5:$Q1004,Trips!$Z5:$Z1004,$R57,Trips!$D5:$D1004,$A57)) | H57: =IF(AND($C57="",$I57="",$J57=""),"",N($E57)+N($F57)+N($G57)) | I57: =IF($A57="","",IFERROR(1/(1/SUMIFS(Expenses!$F5:$F1004,Expenses!$B5:$B1004,"Cash Advance",Expenses!$J5:$J1004,$R57,Expenses!$E5:$E1004,$A57)),"")) | J57: =IF($A57="","",IFERROR(1/(1/SUMIFS(Expenses!$F5:$F1004,Expenses!$B5:$B1004,"Payroll Payout",Expenses!$J5:$J1004,$R57,Expenses!$E5:$E1004,$A57)),"")) | K57: =IF($H57="","",N($H57)-N($I57)-N($J57)) | L57: =IF($K57="","",IF($K57>0.5,"TO PAY",IF($K57<-0.5,"ADVANCE / OWES","SETTLED"))) | R57: 46113
A58: =IF(Setup!$A86="","",Setup!$A86) | B58: =IF($A58="","",Setup!$B86) | C58: =IF($A58="","",IF(COUNTIFS(Trips!$Z5:$Z1004,$R58,Trips!$D5:$D1004,$A58)+COUNTIFS(Trips!$Z5:$Z1004,$R58,Trips!$E5:$E1004,$A58)=0,"",COUNTIFS(Trips!$Z5:$Z1004,$R58,Trips!$D5:$D1004,$A58)+COUNTIFS(Trips!$Z5:$Z1004,$R58,Trips!$E5:$E1004,$A58))) | D58: =IF($C58="","",SUMIFS(Trips!$K5:$K1004,Trips!$Z5:$Z1004,$R58,Trips!$D5:$D1004,$A58)+SUMIFS(Trips!$K5:$K1004,Trips!$Z5:$Z1004,$R58,Trips!$E5:$E1004,$A58)) | E58: =IF($C58="","",SUMIFS(Trips!$N5:$N1004,Trips!$Z5:$Z1004,$R58,Trips!$D5:$D1004,$A58)+SUMIFS(Trips!$O5:$O1004,Trips!$Z5:$Z1004,$R58,Trips!$E5:$E1004,$A58)) | F58: =IF($C58="","",SUMIFS(Trips!$P5:$P1004,Trips!$Z5:$Z1004,$R58,Trips!$D5:$D1004,$A58)) | G58: =IF($C58="","",SUMIFS(Trips!$Q5:$Q1004,Trips!$Z5:$Z1004,$R58,Trips!$D5:$D1004,$A58)) | H58: =IF(AND($C58="",$I58="",$J58=""),"",N($E58)+N($F58)+N($G58)) | I58: =IF($A58="","",IFERROR(1/(1/SUMIFS(Expenses!$F5:$F1004,Expenses!$B5:$B1004,"Cash Advance",Expenses!$J5:$J1004,$R58,Expenses!$E5:$E1004,$A58)),"")) | J58: =IF($A58="","",IFERROR(1/(1/SUMIFS(Expenses!$F5:$F1004,Expenses!$B5:$B1004,"Payroll Payout",Expenses!$J5:$J1004,$R58,Expenses!$E5:$E1004,$A58)),"")) | K58: =IF($H58="","",N($H58)-N($I58)-N($J58)) | L58: =IF($K58="","",IF($K58>0.5,"TO PAY",IF($K58<-0.5,"ADVANCE / OWES","SETTLED"))) | R58: 46113
A59: =IF(Setup!$A87="","",Setup!$A87) | B59: =IF($A59="","",Setup!$B87) | C59: =IF($A59="","",IF(COUNTIFS(Trips!$Z5:$Z1004,$R59,Trips!$D5:$D1004,$A59)+COUNTIFS(Trips!$Z5:$Z1004,$R59,Trips!$E5:$E1004,$A59)=0,"",COUNTIFS(Trips!$Z5:$Z1004,$R59,Trips!$D5:$D1004,$A59)+COUNTIFS(Trips!$Z5:$Z1004,$R59,Trips!$E5:$E1004,$A59))) | D59: =IF($C59="","",SUMIFS(Trips!$K5:$K1004,Trips!$Z5:$Z1004,$R59,Trips!$D5:$D1004,$A59)+SUMIFS(Trips!$K5:$K1004,Trips!$Z5:$Z1004,$R59,Trips!$E5:$E1004,$A59)) | E59: =IF($C59="","",SUMIFS(Trips!$N5:$N1004,Trips!$Z5:$Z1004,$R59,Trips!$D5:$D1004,$A59)+SUMIFS(Trips!$O5:$O1004,Trips!$Z5:$Z1004,$R59,Trips!$E5:$E1004,$A59)) | F59: =IF($C59="","",SUMIFS(Trips!$P5:$P1004,Trips!$Z5:$Z1004,$R59,Trips!$D5:$D1004,$A59)) | G59: =IF($C59="","",SUMIFS(Trips!$Q5:$Q1004,Trips!$Z5:$Z1004,$R59,Trips!$D5:$D1004,$A59)) | H59: =IF(AND($C59="",$I59="",$J59=""),"",N($E59)+N($F59)+N($G59)) | I59: =IF($A59="","",IFERROR(1/(1/SUMIFS(Expenses!$F5:$F1004,Expenses!$B5:$B1004,"Cash Advance",Expenses!$J5:$J1004,$R59,Expenses!$E5:$E1004,$A59)),"")) | J59: =IF($A59="","",IFERROR(1/(1/SUMIFS(Expenses!$F5:$F1004,Expenses!$B5:$B1004,"Payroll Payout",Expenses!$J5:$J1004,$R59,Expenses!$E5:$E1004,$A59)),"")) | K59: =IF($H59="","",N($H59)-N($I59)-N($J59)) | L59: =IF($K59="","",IF($K59>0.5,"TO PAY",IF($K59<-0.5,"ADVANCE / OWES","SETTLED"))) | R59: 46113
A60: MONTH TOTAL | C60: =IF(COUNT(C48:C59)=0,"",SUM(C48:C59)) | D60: =IF(COUNT(D48:D59)=0,"",SUM(D48:D59)) | E60: =IF(COUNT(E48:E59)=0,"",SUM(E48:E59)) | F60: =IF(COUNT(F48:F59)=0,"",SUM(F48:F59)) | G60: =IF(COUNT(G48:G59)=0,"",SUM(G48:G59)) | H60: =IF(COUNT(H48:H59)=0,"",SUM(H48:H59)) | I60: =IF(COUNT(I48:I59)=0,"",SUM(I48:I59)) | J60: =IF(COUNT(J48:J59)=0,"",SUM(J48:J59)) | K60: =IF(COUNT(K48:K59)=0,"",SUM(K48:K59))
A61: MAY 2026 · crew earnings & settlement
A62: =IF(Setup!$A76="","",Setup!$A76) | B62: =IF($A62="","",Setup!$B76) | C62: =IF($A62="","",IF(COUNTIFS(Trips!$Z5:$Z1004,$R62,Trips!$D5:$D1004,$A62)+COUNTIFS(Trips!$Z5:$Z1004,$R62,Trips!$E5:$E1004,$A62)=0,"",COUNTIFS(Trips!$Z5:$Z1004,$R62,Trips!$D5:$D1004,$A62)+COUNTIFS(Trips!$Z5:$Z1004,$R62,Trips!$E5:$E1004,$A62))) | D62: =IF($C62="","",SUMIFS(Trips!$K5:$K1004,Trips!$Z5:$Z1004,$R62,Trips!$D5:$D1004,$A62)+SUMIFS(Trips!$K5:$K1004,Trips!$Z5:$Z1004,$R62,Trips!$E5:$E1004,$A62)) | E62: =IF($C62="","",SUMIFS(Trips!$N5:$N1004,Trips!$Z5:$Z1004,$R62,Trips!$D5:$D1004,$A62)+SUMIFS(Trips!$O5:$O1004,Trips!$Z5:$Z1004,$R62,Trips!$E5:$E1004,$A62)) | F62: =IF($C62="","",SUMIFS(Trips!$P5:$P1004,Trips!$Z5:$Z1004,$R62,Trips!$D5:$D1004,$A62)) | G62: =IF($C62="","",SUMIFS(Trips!$Q5:$Q1004,Trips!$Z5:$Z1004,$R62,Trips!$D5:$D1004,$A62)) | H62: =IF(AND($C62="",$I62="",$J62=""),"",N($E62)+N($F62)+N($G62)) | I62: =IF($A62="","",IFERROR(1/(1/SUMIFS(Expenses!$F5:$F1004,Expenses!$B5:$B1004,"Cash Advance",Expenses!$J5:$J1004,$R62,Expenses!$E5:$E1004,$A62)),"")) | J62: =IF($A62="","",IFERROR(1/(1/SUMIFS(Expenses!$F5:$F1004,Expenses!$B5:$B1004,"Payroll Payout",Expenses!$J5:$J1004,$R62,Expenses!$E5:$E1004,$A62)),"")) | K62: =IF($H62="","",N($H62)-N($I62)-N($J62)) | L62: =IF($K62="","",IF($K62>0.5,"TO PAY",IF($K62<-0.5,"ADVANCE / OWES","SETTLED"))) | R62: 46143
A63: =IF(Setup!$A77="","",Setup!$A77) | B63: =IF($A63="","",Setup!$B77) | C63: =IF($A63="","",IF(COUNTIFS(Trips!$Z5:$Z1004,$R63,Trips!$D5:$D1004,$A63)+COUNTIFS(Trips!$Z5:$Z1004,$R63,Trips!$E5:$E1004,$A63)=0,"",COUNTIFS(Trips!$Z5:$Z1004,$R63,Trips!$D5:$D1004,$A63)+COUNTIFS(Trips!$Z5:$Z1004,$R63,Trips!$E5:$E1004,$A63))) | D63: =IF($C63="","",SUMIFS(Trips!$K5:$K1004,Trips!$Z5:$Z1004,$R63,Trips!$D5:$D1004,$A63)+SUMIFS(Trips!$K5:$K1004,Trips!$Z5:$Z1004,$R63,Trips!$E5:$E1004,$A63)) | E63: =IF($C63="","",SUMIFS(Trips!$N5:$N1004,Trips!$Z5:$Z1004,$R63,Trips!$D5:$D1004,$A63)+SUMIFS(Trips!$O5:$O1004,Trips!$Z5:$Z1004,$R63,Trips!$E5:$E1004,$A63)) | F63: =IF($C63="","",SUMIFS(Trips!$P5:$P1004,Trips!$Z5:$Z1004,$R63,Trips!$D5:$D1004,$A63)) | G63: =IF($C63="","",SUMIFS(Trips!$Q5:$Q1004,Trips!$Z5:$Z1004,$R63,Trips!$D5:$D1004,$A63)) | H63: =IF(AND($C63="",$I63="",$J63=""),"",N($E63)+N($F63)+N($G63)) | I63: =IF($A63="","",IFERROR(1/(1/SUMIFS(Expenses!$F5:$F1004,Expenses!$B5:$B1004,"Cash Advance",Expenses!$J5:$J1004,$R63,Expenses!$E5:$E1004,$A63)),"")) | J63: =IF($A63="","",IFERROR(1/(1/SUMIFS(Expenses!$F5:$F1004,Expenses!$B5:$B1004,"Payroll Payout",Expenses!$J5:$J1004,$R63,Expenses!$E5:$E1004,$A63)),"")) | K63: =IF($H63="","",N($H63)-N($I63)-N($J63)) | L63: =IF($K63="","",IF($K63>0.5,"TO PAY",IF($K63<-0.5,"ADVANCE / OWES","SETTLED"))) | R63: 46143
A64: =IF(Setup!$A78="","",Setup!$A78) | B64: =IF($A64="","",Setup!$B78) | C64: =IF($A64="","",IF(COUNTIFS(Trips!$Z5:$Z1004,$R64,Trips!$D5:$D1004,$A64)+COUNTIFS(Trips!$Z5:$Z1004,$R64,Trips!$E5:$E1004,$A64)=0,"",COUNTIFS(Trips!$Z5:$Z1004,$R64,Trips!$D5:$D1004,$A64)+COUNTIFS(Trips!$Z5:$Z1004,$R64,Trips!$E5:$E1004,$A64))) | D64: =IF($C64="","",SUMIFS(Trips!$K5:$K1004,Trips!$Z5:$Z1004,$R64,Trips!$D5:$D1004,$A64)+SUMIFS(Trips!$K5:$K1004,Trips!$Z5:$Z1004,$R64,Trips!$E5:$E1004,$A64)) | E64: =IF($C64="","",SUMIFS(Trips!$N5:$N1004,Trips!$Z5:$Z1004,$R64,Trips!$D5:$D1004,$A64)+SUMIFS(Trips!$O5:$O1004,Trips!$Z5:$Z1004,$R64,Trips!$E5:$E1004,$A64)) | F64: =IF($C64="","",SUMIFS(Trips!$P5:$P1004,Trips!$Z5:$Z1004,$R64,Trips!$D5:$D1004,$A64)) | G64: =IF($C64="","",SUMIFS(Trips!$Q5:$Q1004,Trips!$Z5:$Z1004,$R64,Trips!$D5:$D1004,$A64)) | H64: =IF(AND($C64="",$I64="",$J64=""),"",N($E64)+N($F64)+N($G64)) | I64: =IF($A64="","",IFERROR(1/(1/SUMIFS(Expenses!$F5:$F1004,Expenses!$B5:$B1004,"Cash Advance",Expenses!$J5:$J1004,$R64,Expenses!$E5:$E1004,$A64)),"")) | J64: =IF($A64="","",IFERROR(1/(1/SUMIFS(Expenses!$F5:$F1004,Expenses!$B5:$B1004,"Payroll Payout",Expenses!$J5:$J1004,$R64,Expenses!$E5:$E1004,$A64)),"")) | K64: =IF($H64="","",N($H64)-N($I64)-N($J64)) | L64: =IF($K64="","",IF($K64>0.5,"TO PAY",IF($K64<-0.5,"ADVANCE / OWES","SETTLED"))) | R64: 46143
A65: =IF(Setup!$A79="","",Setup!$A79) | B65: =IF($A65="","",Setup!$B79) | C65: =IF($A65="","",IF(COUNTIFS(Trips!$Z5:$Z1004,$R65,Trips!$D5:$D1004,$A65)+COUNTIFS(Trips!$Z5:$Z1004,$R65,Trips!$E5:$E1004,$A65)=0,"",COUNTIFS(Trips!$Z5:$Z1004,$R65,Trips!$D5:$D1004,$A65)+COUNTIFS(Trips!$Z5:$Z1004,$R65,Trips!$E5:$E1004,$A65))) | D65: =IF($C65="","",SUMIFS(Trips!$K5:$K1004,Trips!$Z5:$Z1004,$R65,Trips!$D5:$D1004,$A65)+SUMIFS(Trips!$K5:$K1004,Trips!$Z5:$Z1004,$R65,Trips!$E5:$E1004,$A65)) | E65: =IF($C65="","",SUMIFS(Trips!$N5:$N1004,Trips!$Z5:$Z1004,$R65,Trips!$D5:$D1004,$A65)+SUMIFS(Trips!$O5:$O1004,Trips!$Z5:$Z1004,$R65,Trips!$E5:$E1004,$A65)) | F65: =IF($C65="","",SUMIFS(Trips!$P5:$P1004,Trips!$Z5:$Z1004,$R65,Trips!$D5:$D1004,$A65)) | G65: =IF($C65="","",SUMIFS(Trips!$Q5:$Q1004,Trips!$Z5:$Z1004,$R65,Trips!$D5:$D1004,$A65)) | H65: =IF(AND($C65="",$I65="",$J65=""),"",N($E65)+N($F65)+N($G65)) | I65: =IF($A65="","",IFERROR(1/(1/SUMIFS(Expenses!$F5:$F1004,Expenses!$B5:$B1004,"Cash Advance",Expenses!$J5:$J1004,$R65,Expenses!$E5:$E1004,$A65)),"")) | J65: =IF($A65="","",IFERROR(1/(1/SUMIFS(Expenses!$F5:$F1004,Expenses!$B5:$B1004,"Payroll Payout",Expenses!$J5:$J1004,$R65,Expenses!$E5:$E1004,$A65)),"")) | K65: =IF($H65="","",N($H65)-N($I65)-N($J65)) | L65: =IF($K65="","",IF($K65>0.5,"TO PAY",IF($K65<-0.5,"ADVANCE / OWES","SETTLED"))) | R65: 46143
A66: =IF(Setup!$A80="","",Setup!$A80) | B66: =IF($A66="","",Setup!$B80) | C66: =IF($A66="","",IF(COUNTIFS(Trips!$Z5:$Z1004,$R66,Trips!$D5:$D1004,$A66)+COUNTIFS(Trips!$Z5:$Z1004,$R66,Trips!$E5:$E1004,$A66)=0,"",COUNTIFS(Trips!$Z5:$Z1004,$R66,Trips!$D5:$D1004,$A66)+COUNTIFS(Trips!$Z5:$Z1004,$R66,Trips!$E5:$E1004,$A66))) | D66: =IF($C66="","",SUMIFS(Trips!$K5:$K1004,Trips!$Z5:$Z1004,$R66,Trips!$D5:$D1004,$A66)+SUMIFS(Trips!$K5:$K1004,Trips!$Z5:$Z1004,$R66,Trips!$E5:$E1004,$A66)) | E66: =IF($C66="","",SUMIFS(Trips!$N5:$N1004,Trips!$Z5:$Z1004,$R66,Trips!$D5:$D1004,$A66)+SUMIFS(Trips!$O5:$O1004,Trips!$Z5:$Z1004,$R66,Trips!$E5:$E1004,$A66)) | F66: =IF($C66="","",SUMIFS(Trips!$P5:$P1004,Trips!$Z5:$Z1004,$R66,Trips!$D5:$D1004,$A66)) | G66: =IF($C66="","",SUMIFS(Trips!$Q5:$Q1004,Trips!$Z5:$Z1004,$R66,Trips!$D5:$D1004,$A66)) | H66: =IF(AND($C66="",$I66="",$J66=""),"",N($E66)+N($F66)+N($G66)) | I66: =IF($A66="","",IFERROR(1/(1/SUMIFS(Expenses!$F5:$F1004,Expenses!$B5:$B1004,"Cash Advance",Expenses!$J5:$J1004,$R66,Expenses!$E5:$E1004,$A66)),"")) | J66: =IF($A66="","",IFERROR(1/(1/SUMIFS(Expenses!$F5:$F1004,Expenses!$B5:$B1004,"Payroll Payout",Expenses!$J5:$J1004,$R66,Expenses!$E5:$E1004,$A66)),"")) | K66: =IF($H66="","",N($H66)-N($I66)-N($J66)) | L66: =IF($K66="","",IF($K66>0.5,"TO PAY",IF($K66<-0.5,"ADVANCE / OWES","SETTLED"))) | R66: 46143
A67: =IF(Setup!$A81="","",Setup!$A81) | B67: =IF($A67="","",Setup!$B81) | C67: =IF($A67="","",IF(COUNTIFS(Trips!$Z5:$Z1004,$R67,Trips!$D5:$D1004,$A67)+COUNTIFS(Trips!$Z5:$Z1004,$R67,Trips!$E5:$E1004,$A67)=0,"",COUNTIFS(Trips!$Z5:$Z1004,$R67,Trips!$D5:$D1004,$A67)+COUNTIFS(Trips!$Z5:$Z1004,$R67,Trips!$E5:$E1004,$A67))) | D67: =IF($C67="","",SUMIFS(Trips!$K5:$K1004,Trips!$Z5:$Z1004,$R67,Trips!$D5:$D1004,$A67)+SUMIFS(Trips!$K5:$K1004,Trips!$Z5:$Z1004,$R67,Trips!$E5:$E1004,$A67)) | E67: =IF($C67="","",SUMIFS(Trips!$N5:$N1004,Trips!$Z5:$Z1004,$R67,Trips!$D5:$D1004,$A67)+SUMIFS(Trips!$O5:$O1004,Trips!$Z5:$Z1004,$R67,Trips!$E5:$E1004,$A67)) | F67: =IF($C67="","",SUMIFS(Trips!$P5:$P1004,Trips!$Z5:$Z1004,$R67,Trips!$D5:$D1004,$A67)) | G67: =IF($C67="","",SUMIFS(Trips!$Q5:$Q1004,Trips!$Z5:$Z1004,$R67,Trips!$D5:$D1004,$A67)) | H67: =IF(AND($C67="",$I67="",$J67=""),"",N($E67)+N($F67)+N($G67)) | I67: =IF($A67="","",IFERROR(1/(1/SUMIFS(Expenses!$F5:$F1004,Expenses!$B5:$B1004,"Cash Advance",Expenses!$J5:$J1004,$R67,Expenses!$E5:$E1004,$A67)),"")) | J67: =IF($A67="","",IFERROR(1/(1/SUMIFS(Expenses!$F5:$F1004,Expenses!$B5:$B1004,"Payroll Payout",Expenses!$J5:$J1004,$R67,Expenses!$E5:$E1004,$A67)),"")) | K67: =IF($H67="","",N($H67)-N($I67)-N($J67)) | L67: =IF($K67="","",IF($K67>0.5,"TO PAY",IF($K67<-0.5,"ADVANCE / OWES","SETTLED"))) | R67: 46143
A68: =IF(Setup!$A82="","",Setup!$A82) | B68: =IF($A68="","",Setup!$B82) | C68: =IF($A68="","",IF(COUNTIFS(Trips!$Z5:$Z1004,$R68,Trips!$D5:$D1004,$A68)+COUNTIFS(Trips!$Z5:$Z1004,$R68,Trips!$E5:$E1004,$A68)=0,"",COUNTIFS(Trips!$Z5:$Z1004,$R68,Trips!$D5:$D1004,$A68)+COUNTIFS(Trips!$Z5:$Z1004,$R68,Trips!$E5:$E1004,$A68))) | D68: =IF($C68="","",SUMIFS(Trips!$K5:$K1004,Trips!$Z5:$Z1004,$R68,Trips!$D5:$D1004,$A68)+SUMIFS(Trips!$K5:$K1004,Trips!$Z5:$Z1004,$R68,Trips!$E5:$E1004,$A68)) | E68: =IF($C68="","",SUMIFS(Trips!$N5:$N1004,Trips!$Z5:$Z1004,$R68,Trips!$D5:$D1004,$A68)+SUMIFS(Trips!$O5:$O1004,Trips!$Z5:$Z1004,$R68,Trips!$E5:$E1004,$A68)) | F68: =IF($C68="","",SUMIFS(Trips!$P5:$P1004,Trips!$Z5:$Z1004,$R68,Trips!$D5:$D1004,$A68)) | G68: =IF($C68="","",SUMIFS(Trips!$Q5:$Q1004,Trips!$Z5:$Z1004,$R68,Trips!$D5:$D1004,$A68)) | H68: =IF(AND($C68="",$I68="",$J68=""),"",N($E68)+N($F68)+N($G68)) | I68: =IF($A68="","",IFERROR(1/(1/SUMIFS(Expenses!$F5:$F1004,Expenses!$B5:$B1004,"Cash Advance",Expenses!$J5:$J1004,$R68,Expenses!$E5:$E1004,$A68)),"")) | J68: =IF($A68="","",IFERROR(1/(1/SUMIFS(Expenses!$F5:$F1004,Expenses!$B5:$B1004,"Payroll Payout",Expenses!$J5:$J1004,$R68,Expenses!$E5:$E1004,$A68)),"")) | K68: =IF($H68="","",N($H68)-N($I68)-N($J68)) | L68: =IF($K68="","",IF($K68>0.5,"TO PAY",IF($K68<-0.5,"ADVANCE / OWES","SETTLED"))) | R68: 46143
A69: =IF(Setup!$A83="","",Setup!$A83) | B69: =IF($A69="","",Setup!$B83) | C69: =IF($A69="","",IF(COUNTIFS(Trips!$Z5:$Z1004,$R69,Trips!$D5:$D1004,$A69)+COUNTIFS(Trips!$Z5:$Z1004,$R69,Trips!$E5:$E1004,$A69)=0,"",COUNTIFS(Trips!$Z5:$Z1004,$R69,Trips!$D5:$D1004,$A69)+COUNTIFS(Trips!$Z5:$Z1004,$R69,Trips!$E5:$E1004,$A69))) | D69: =IF($C69="","",SUMIFS(Trips!$K5:$K1004,Trips!$Z5:$Z1004,$R69,Trips!$D5:$D1004,$A69)+SUMIFS(Trips!$K5:$K1004,Trips!$Z5:$Z1004,$R69,Trips!$E5:$E1004,$A69)) | E69: =IF($C69="","",SUMIFS(Trips!$N5:$N1004,Trips!$Z5:$Z1004,$R69,Trips!$D5:$D1004,$A69)+SUMIFS(Trips!$O5:$O1004,Trips!$Z5:$Z1004,$R69,Trips!$E5:$E1004,$A69)) | F69: =IF($C69="","",SUMIFS(Trips!$P5:$P1004,Trips!$Z5:$Z1004,$R69,Trips!$D5:$D1004,$A69)) | G69: =IF($C69="","",SUMIFS(Trips!$Q5:$Q1004,Trips!$Z5:$Z1004,$R69,Trips!$D5:$D1004,$A69)) | H69: =IF(AND($C69="",$I69="",$J69=""),"",N($E69)+N($F69)+N($G69)) | I69: =IF($A69="","",IFERROR(1/(1/SUMIFS(Expenses!$F5:$F1004,Expenses!$B5:$B1004,"Cash Advance",Expenses!$J5:$J1004,$R69,Expenses!$E5:$E1004,$A69)),"")) | J69: =IF($A69="","",IFERROR(1/(1/SUMIFS(Expenses!$F5:$F1004,Expenses!$B5:$B1004,"Payroll Payout",Expenses!$J5:$J1004,$R69,Expenses!$E5:$E1004,$A69)),"")) | K69: =IF($H69="","",N($H69)-N($I69)-N($J69)) | L69: =IF($K69="","",IF($K69>0.5,"TO PAY",IF($K69<-0.5,"ADVANCE / OWES","SETTLED"))) | R69: 46143
A70: =IF(Setup!$A84="","",Setup!$A84) | B70: =IF($A70="","",Setup!$B84) | C70: =IF($A70="","",IF(COUNTIFS(Trips!$Z5:$Z1004,$R70,Trips!$D5:$D1004,$A70)+COUNTIFS(Trips!$Z5:$Z1004,$R70,Trips!$E5:$E1004,$A70)=0,"",COUNTIFS(Trips!$Z5:$Z1004,$R70,Trips!$D5:$D1004,$A70)+COUNTIFS(Trips!$Z5:$Z1004,$R70,Trips!$E5:$E1004,$A70))) | D70: =IF($C70="","",SUMIFS(Trips!$K5:$K1004,Trips!$Z5:$Z1004,$R70,Trips!$D5:$D1004,$A70)+SUMIFS(Trips!$K5:$K1004,Trips!$Z5:$Z1004,$R70,Trips!$E5:$E1004,$A70)) | E70: =IF($C70="","",SUMIFS(Trips!$N5:$N1004,Trips!$Z5:$Z1004,$R70,Trips!$D5:$D1004,$A70)+SUMIFS(Trips!$O5:$O1004,Trips!$Z5:$Z1004,$R70,Trips!$E5:$E1004,$A70)) | F70: =IF($C70="","",SUMIFS(Trips!$P5:$P1004,Trips!$Z5:$Z1004,$R70,Trips!$D5:$D1004,$A70)) | G70: =IF($C70="","",SUMIFS(Trips!$Q5:$Q1004,Trips!$Z5:$Z1004,$R70,Trips!$D5:$D1004,$A70)) | H70: =IF(AND($C70="",$I70="",$J70=""),"",N($E70)+N($F70)+N($G70)) | I70: =IF($A70="","",IFERROR(1/(1/SUMIFS(Expenses!$F5:$F1004,Expenses!$B5:$B1004,"Cash Advance",Expenses!$J5:$J1004,$R70,Expenses!$E5:$E1004,$A70)),"")) | J70: =IF($A70="","",IFERROR(1/(1/SUMIFS(Expenses!$F5:$F1004,Expenses!$B5:$B1004,"Payroll Payout",Expenses!$J5:$J1004,$R70,Expenses!$E5:$E1004,$A70)),"")) | K70: =IF($H70="","",N($H70)-N($I70)-N($J70)) | L70: =IF($K70="","",IF($K70>0.5,"TO PAY",IF($K70<-0.5,"ADVANCE / OWES","SETTLED"))) | R70: 46143
A71: =IF(Setup!$A85="","",Setup!$A85) | B71: =IF($A71="","",Setup!$B85) | C71: =IF($A71="","",IF(COUNTIFS(Trips!$Z5:$Z1004,$R71,Trips!$D5:$D1004,$A71)+COUNTIFS(Trips!$Z5:$Z1004,$R71,Trips!$E5:$E1004,$A71)=0,"",COUNTIFS(Trips!$Z5:$Z1004,$R71,Trips!$D5:$D1004,$A71)+COUNTIFS(Trips!$Z5:$Z1004,$R71,Trips!$E5:$E1004,$A71))) | D71: =IF($C71="","",SUMIFS(Trips!$K5:$K1004,Trips!$Z5:$Z1004,$R71,Trips!$D5:$D1004,$A71)+SUMIFS(Trips!$K5:$K1004,Trips!$Z5:$Z1004,$R71,Trips!$E5:$E1004,$A71)) | E71: =IF($C71="","",SUMIFS(Trips!$N5:$N1004,Trips!$Z5:$Z1004,$R71,Trips!$D5:$D1004,$A71)+SUMIFS(Trips!$O5:$O1004,Trips!$Z5:$Z1004,$R71,Trips!$E5:$E1004,$A71)) | F71: =IF($C71="","",SUMIFS(Trips!$P5:$P1004,Trips!$Z5:$Z1004,$R71,Trips!$D5:$D1004,$A71)) | G71: =IF($C71="","",SUMIFS(Trips!$Q5:$Q1004,Trips!$Z5:$Z1004,$R71,Trips!$D5:$D1004,$A71)) | H71: =IF(AND($C71="",$I71="",$J71=""),"",N($E71)+N($F71)+N($G71)) | I71: =IF($A71="","",IFERROR(1/(1/SUMIFS(Expenses!$F5:$F1004,Expenses!$B5:$B1004,"Cash Advance",Expenses!$J5:$J1004,$R71,Expenses!$E5:$E1004,$A71)),"")) | J71: =IF($A71="","",IFERROR(1/(1/SUMIFS(Expenses!$F5:$F1004,Expenses!$B5:$B1004,"Payroll Payout",Expenses!$J5:$J1004,$R71,Expenses!$E5:$E1004,$A71)),"")) | K71: =IF($H71="","",N($H71)-N($I71)-N($J71)) | L71: =IF($K71="","",IF($K71>0.5,"TO PAY",IF($K71<-0.5,"ADVANCE / OWES","SETTLED"))) | R71: 46143
A72: =IF(Setup!$A86="","",Setup!$A86) | B72: =IF($A72="","",Setup!$B86) | C72: =IF($A72="","",IF(COUNTIFS(Trips!$Z5:$Z1004,$R72,Trips!$D5:$D1004,$A72)+COUNTIFS(Trips!$Z5:$Z1004,$R72,Trips!$E5:$E1004,$A72)=0,"",COUNTIFS(Trips!$Z5:$Z1004,$R72,Trips!$D5:$D1004,$A72)+COUNTIFS(Trips!$Z5:$Z1004,$R72,Trips!$E5:$E1004,$A72))) | D72: =IF($C72="","",SUMIFS(Trips!$K5:$K1004,Trips!$Z5:$Z1004,$R72,Trips!$D5:$D1004,$A72)+SUMIFS(Trips!$K5:$K1004,Trips!$Z5:$Z1004,$R72,Trips!$E5:$E1004,$A72)) | E72: =IF($C72="","",SUMIFS(Trips!$N5:$N1004,Trips!$Z5:$Z1004,$R72,Trips!$D5:$D1004,$A72)+SUMIFS(Trips!$O5:$O1004,Trips!$Z5:$Z1004,$R72,Trips!$E5:$E1004,$A72)) | F72: =IF($C72="","",SUMIFS(Trips!$P5:$P1004,Trips!$Z5:$Z1004,$R72,Trips!$D5:$D1004,$A72)) | G72: =IF($C72="","",SUMIFS(Trips!$Q5:$Q1004,Trips!$Z5:$Z1004,$R72,Trips!$D5:$D1004,$A72)) | H72: =IF(AND($C72="",$I72="",$J72=""),"",N($E72)+N($F72)+N($G72)) | I72: =IF($A72="","",IFERROR(1/(1/SUMIFS(Expenses!$F5:$F1004,Expenses!$B5:$B1004,"Cash Advance",Expenses!$J5:$J1004,$R72,Expenses!$E5:$E1004,$A72)),"")) | J72: =IF($A72="","",IFERROR(1/(1/SUMIFS(Expenses!$F5:$F1004,Expenses!$B5:$B1004,"Payroll Payout",Expenses!$J5:$J1004,$R72,Expenses!$E5:$E1004,$A72)),"")) | K72: =IF($H72="","",N($H72)-N($I72)-N($J72)) | L72: =IF($K72="","",IF($K72>0.5,"TO PAY",IF($K72<-0.5,"ADVANCE / OWES","SETTLED"))) | R72: 46143
A73: =IF(Setup!$A87="","",Setup!$A87) | B73: =IF($A73="","",Setup!$B87) | C73: =IF($A73="","",IF(COUNTIFS(Trips!$Z5:$Z1004,$R73,Trips!$D5:$D1004,$A73)+COUNTIFS(Trips!$Z5:$Z1004,$R73,Trips!$E5:$E1004,$A73)=0,"",COUNTIFS(Trips!$Z5:$Z1004,$R73,Trips!$D5:$D1004,$A73)+COUNTIFS(Trips!$Z5:$Z1004,$R73,Trips!$E5:$E1004,$A73))) | D73: =IF($C73="","",SUMIFS(Trips!$K5:$K1004,Trips!$Z5:$Z1004,$R73,Trips!$D5:$D1004,$A73)+SUMIFS(Trips!$K5:$K1004,Trips!$Z5:$Z1004,$R73,Trips!$E5:$E1004,$A73)) | E73: =IF($C73="","",SUMIFS(Trips!$N5:$N1004,Trips!$Z5:$Z1004,$R73,Trips!$D5:$D1004,$A73)+SUMIFS(Trips!$O5:$O1004,Trips!$Z5:$Z1004,$R73,Trips!$E5:$E1004,$A73)) | F73: =IF($C73="","",SUMIFS(Trips!$P5:$P1004,Trips!$Z5:$Z1004,$R73,Trips!$D5:$D1004,$A73)) | G73: =IF($C73="","",SUMIFS(Trips!$Q5:$Q1004,Trips!$Z5:$Z1004,$R73,Trips!$D5:$D1004,$A73)) | H73: =IF(AND($C73="",$I73="",$J73=""),"",N($E73)+N($F73)+N($G73)) | I73: =IF($A73="","",IFERROR(1/(1/SUMIFS(Expenses!$F5:$F1004,Expenses!$B5:$B1004,"Cash Advance",Expenses!$J5:$J1004,$R73,Expenses!$E5:$E1004,$A73)),"")) | J73: =IF($A73="","",IFERROR(1/(1/SUMIFS(Expenses!$F5:$F1004,Expenses!$B5:$B1004,"Payroll Payout",Expenses!$J5:$J1004,$R73,Expenses!$E5:$E1004,$A73)),"")) | K73: =IF($H73="","",N($H73)-N($I73)-N($J73)) | L73: =IF($K73="","",IF($K73>0.5,"TO PAY",IF($K73<-0.5,"ADVANCE / OWES","SETTLED"))) | R73: 46143
A74: MONTH TOTAL | C74: =IF(COUNT(C62:C73)=0,"",SUM(C62:C73)) | D74: =IF(COUNT(D62:D73)=0,"",SUM(D62:D73)) | E74: =IF(COUNT(E62:E73)=0,"",SUM(E62:E73)) | F74: =IF(COUNT(F62:F73)=0,"",SUM(F62:F73)) | G74: =IF(COUNT(G62:G73)=0,"",SUM(G62:G73)) | H74: =IF(COUNT(H62:H73)=0,"",SUM(H62:H73)) | I74: =IF(COUNT(I62:I73)=0,"",SUM(I62:I73)) | J74: =IF(COUNT(J62:J73)=0,"",SUM(J62:J73)) | K74: =IF(COUNT(K62:K73)=0,"",SUM(K62:K73))
A75: JUNE 2026 · crew earnings & settlement
A76: =IF(Setup!$A76="","",Setup!$A76) | B76: =IF($A76="","",Setup!$B76) | C76: =IF($A76="","",IF(COUNTIFS(Trips!$Z5:$Z1004,$R76,Trips!$D5:$D1004,$A76)+COUNTIFS(Trips!$Z5:$Z1004,$R76,Trips!$E5:$E1004,$A76)=0,"",COUNTIFS(Trips!$Z5:$Z1004,$R76,Trips!$D5:$D1004,$A76)+COUNTIFS(Trips!$Z5:$Z1004,$R76,Trips!$E5:$E1004,$A76))) | D76: =IF($C76="","",SUMIFS(Trips!$K5:$K1004,Trips!$Z5:$Z1004,$R76,Trips!$D5:$D1004,$A76)+SUMIFS(Trips!$K5:$K1004,Trips!$Z5:$Z1004,$R76,Trips!$E5:$E1004,$A76)) | E76: =IF($C76="","",SUMIFS(Trips!$N5:$N1004,Trips!$Z5:$Z1004,$R76,Trips!$D5:$D1004,$A76)+SUMIFS(Trips!$O5:$O1004,Trips!$Z5:$Z1004,$R76,Trips!$E5:$E1004,$A76)) | F76: =IF($C76="","",SUMIFS(Trips!$P5:$P1004,Trips!$Z5:$Z1004,$R76,Trips!$D5:$D1004,$A76)) | G76: =IF($C76="","",SUMIFS(Trips!$Q5:$Q1004,Trips!$Z5:$Z1004,$R76,Trips!$D5:$D1004,$A76)) | H76: =IF(AND($C76="",$I76="",$J76=""),"",N($E76)+N($F76)+N($G76)) | I76: =IF($A76="","",IFERROR(1/(1/SUMIFS(Expenses!$F5:$F1004,Expenses!$B5:$B1004,"Cash Advance",Expenses!$J5:$J1004,$R76,Expenses!$E5:$E1004,$A76)),"")) | J76: =IF($A76="","",IFERROR(1/(1/SUMIFS(Expenses!$F5:$F1004,Expenses!$B5:$B1004,"Payroll Payout",Expenses!$J5:$J1004,$R76,Expenses!$E5:$E1004,$A76)),"")) | K76: =IF($H76="","",N($H76)-N($I76)-N($J76)) | L76: =IF($K76="","",IF($K76>0.5,"TO PAY",IF($K76<-0.5,"ADVANCE / OWES","SETTLED"))) | R76: 46174
A77: =IF(Setup!$A77="","",Setup!$A77) | B77: =IF($A77="","",Setup!$B77) | C77: =IF($A77="","",IF(COUNTIFS(Trips!$Z5:$Z1004,$R77,Trips!$D5:$D1004,$A77)+COUNTIFS(Trips!$Z5:$Z1004,$R77,Trips!$E5:$E1004,$A77)=0,"",COUNTIFS(Trips!$Z5:$Z1004,$R77,Trips!$D5:$D1004,$A77)+COUNTIFS(Trips!$Z5:$Z1004,$R77,Trips!$E5:$E1004,$A77))) | D77: =IF($C77="","",SUMIFS(Trips!$K5:$K1004,Trips!$Z5:$Z1004,$R77,Trips!$D5:$D1004,$A77)+SUMIFS(Trips!$K5:$K1004,Trips!$Z5:$Z1004,$R77,Trips!$E5:$E1004,$A77)) | E77: =IF($C77="","",SUMIFS(Trips!$N5:$N1004,Trips!$Z5:$Z1004,$R77,Trips!$D5:$D1004,$A77)+SUMIFS(Trips!$O5:$O1004,Trips!$Z5:$Z1004,$R77,Trips!$E5:$E1004,$A77)) | F77: =IF($C77="","",SUMIFS(Trips!$P5:$P1004,Trips!$Z5:$Z1004,$R77,Trips!$D5:$D1004,$A77)) | G77: =IF($C77="","",SUMIFS(Trips!$Q5:$Q1004,Trips!$Z5:$Z1004,$R77,Trips!$D5:$D1004,$A77)) | H77: =IF(AND($C77="",$I77="",$J77=""),"",N($E77)+N($F77)+N($G77)) | I77: =IF($A77="","",IFERROR(1/(1/SUMIFS(Expenses!$F5:$F1004,Expenses!$B5:$B1004,"Cash Advance",Expenses!$J5:$J1004,$R77,Expenses!$E5:$E1004,$A77)),"")) | J77: =IF($A77="","",IFERROR(1/(1/SUMIFS(Expenses!$F5:$F1004,Expenses!$B5:$B1004,"Payroll Payout",Expenses!$J5:$J1004,$R77,Expenses!$E5:$E1004,$A77)),"")) | K77: =IF($H77="","",N($H77)-N($I77)-N($J77)) | L77: =IF($K77="","",IF($K77>0.5,"TO PAY",IF($K77<-0.5,"ADVANCE / OWES","SETTLED"))) | R77: 46174
A78: =IF(Setup!$A78="","",Setup!$A78) | B78: =IF($A78="","",Setup!$B78) | C78: =IF($A78="","",IF(COUNTIFS(Trips!$Z5:$Z1004,$R78,Trips!$D5:$D1004,$A78)+COUNTIFS(Trips!$Z5:$Z1004,$R78,Trips!$E5:$E1004,$A78)=0,"",COUNTIFS(Trips!$Z5:$Z1004,$R78,Trips!$D5:$D1004,$A78)+COUNTIFS(Trips!$Z5:$Z1004,$R78,Trips!$E5:$E1004,$A78))) | D78: =IF($C78="","",SUMIFS(Trips!$K5:$K1004,Trips!$Z5:$Z1004,$R78,Trips!$D5:$D1004,$A78)+SUMIFS(Trips!$K5:$K1004,Trips!$Z5:$Z1004,$R78,Trips!$E5:$E1004,$A78)) | E78: =IF($C78="","",SUMIFS(Trips!$N5:$N1004,Trips!$Z5:$Z1004,$R78,Trips!$D5:$D1004,$A78)+SUMIFS(Trips!$O5:$O1004,Trips!$Z5:$Z1004,$R78,Trips!$E5:$E1004,$A78)) | F78: =IF($C78="","",SUMIFS(Trips!$P5:$P1004,Trips!$Z5:$Z1004,$R78,Trips!$D5:$D1004,$A78)) | G78: =IF($C78="","",SUMIFS(Trips!$Q5:$Q1004,Trips!$Z5:$Z1004,$R78,Trips!$D5:$D1004,$A78)) | H78: =IF(AND($C78="",$I78="",$J78=""),"",N($E78)+N($F78)+N($G78)) | I78: =IF($A78="","",IFERROR(1/(1/SUMIFS(Expenses!$F5:$F1004,Expenses!$B5:$B1004,"Cash Advance",Expenses!$J5:$J1004,$R78,Expenses!$E5:$E1004,$A78)),"")) | J78: =IF($A78="","",IFERROR(1/(1/SUMIFS(Expenses!$F5:$F1004,Expenses!$B5:$B1004,"Payroll Payout",Expenses!$J5:$J1004,$R78,Expenses!$E5:$E1004,$A78)),"")) | K78: =IF($H78="","",N($H78)-N($I78)-N($J78)) | L78: =IF($K78="","",IF($K78>0.5,"TO PAY",IF($K78<-0.5,"ADVANCE / OWES","SETTLED"))) | R78: 46174
A79: =IF(Setup!$A79="","",Setup!$A79) | B79: =IF($A79="","",Setup!$B79) | C79: =IF($A79="","",IF(COUNTIFS(Trips!$Z5:$Z1004,$R79,Trips!$D5:$D1004,$A79)+COUNTIFS(Trips!$Z5:$Z1004,$R79,Trips!$E5:$E1004,$A79)=0,"",COUNTIFS(Trips!$Z5:$Z1004,$R79,Trips!$D5:$D1004,$A79)+COUNTIFS(Trips!$Z5:$Z1004,$R79,Trips!$E5:$E1004,$A79))) | D79: =IF($C79="","",SUMIFS(Trips!$K5:$K1004,Trips!$Z5:$Z1004,$R79,Trips!$D5:$D1004,$A79)+SUMIFS(Trips!$K5:$K1004,Trips!$Z5:$Z1004,$R79,Trips!$E5:$E1004,$A79)) | E79: =IF($C79="","",SUMIFS(Trips!$N5:$N1004,Trips!$Z5:$Z1004,$R79,Trips!$D5:$D1004,$A79)+SUMIFS(Trips!$O5:$O1004,Trips!$Z5:$Z1004,$R79,Trips!$E5:$E1004,$A79)) | F79: =IF($C79="","",SUMIFS(Trips!$P5:$P1004,Trips!$Z5:$Z1004,$R79,Trips!$D5:$D1004,$A79)) | G79: =IF($C79="","",SUMIFS(Trips!$Q5:$Q1004,Trips!$Z5:$Z1004,$R79,Trips!$D5:$D1004,$A79)) | H79: =IF(AND($C79="",$I79="",$J79=""),"",N($E79)+N($F79)+N($G79)) | I79: =IF($A79="","",IFERROR(1/(1/SUMIFS(Expenses!$F5:$F1004,Expenses!$B5:$B1004,"Cash Advance",Expenses!$J5:$J1004,$R79,Expenses!$E5:$E1004,$A79)),"")) | J79: =IF($A79="","",IFERROR(1/(1/SUMIFS(Expenses!$F5:$F1004,Expenses!$B5:$B1004,"Payroll Payout",Expenses!$J5:$J1004,$R79,Expenses!$E5:$E1004,$A79)),"")) | K79: =IF($H79="","",N($H79)-N($I79)-N($J79)) | L79: =IF($K79="","",IF($K79>0.5,"TO PAY",IF($K79<-0.5,"ADVANCE / OWES","SETTLED"))) | R79: 46174
A80: =IF(Setup!$A80="","",Setup!$A80) | B80: =IF($A80="","",Setup!$B80) | C80: =IF($A80="","",IF(COUNTIFS(Trips!$Z5:$Z1004,$R80,Trips!$D5:$D1004,$A80)+COUNTIFS(Trips!$Z5:$Z1004,$R80,Trips!$E5:$E1004,$A80)=0,"",COUNTIFS(Trips!$Z5:$Z1004,$R80,Trips!$D5:$D1004,$A80)+COUNTIFS(Trips!$Z5:$Z1004,$R80,Trips!$E5:$E1004,$A80))) | D80: =IF($C80="","",SUMIFS(Trips!$K5:$K1004,Trips!$Z5:$Z1004,$R80,Trips!$D5:$D1004,$A80)+SUMIFS(Trips!$K5:$K1004,Trips!$Z5:$Z1004,$R80,Trips!$E5:$E1004,$A80)) | E80: =IF($C80="","",SUMIFS(Trips!$N5:$N1004,Trips!$Z5:$Z1004,$R80,Trips!$D5:$D1004,$A80)+SUMIFS(Trips!$O5:$O1004,Trips!$Z5:$Z1004,$R80,Trips!$E5:$E1004,$A80)) | F80: =IF($C80="","",SUMIFS(Trips!$P5:$P1004,Trips!$Z5:$Z1004,$R80,Trips!$D5:$D1004,$A80)) | G80: =IF($C80="","",SUMIFS(Trips!$Q5:$Q1004,Trips!$Z5:$Z1004,$R80,Trips!$D5:$D1004,$A80)) | H80: =IF(AND($C80="",$I80="",$J80=""),"",N($E80)+N($F80)+N($G80)) | I80: =IF($A80="","",IFERROR(1/(1/SUMIFS(Expenses!$F5:$F1004,Expenses!$B5:$B1004,"Cash Advance",Expenses!$J5:$J1004,$R80,Expenses!$E5:$E1004,$A80)),"")) | J80: =IF($A80="","",IFERROR(1/(1/SUMIFS(Expenses!$F5:$F1004,Expenses!$B5:$B1004,"Payroll Payout",Expenses!$J5:$J1004,$R80,Expenses!$E5:$E1004,$A80)),"")) | K80: =IF($H80="","",N($H80)-N($I80)-N($J80)) | L80: =IF($K80="","",IF($K80>0.5,"TO PAY",IF($K80<-0.5,"ADVANCE / OWES","SETTLED"))) | R80: 46174
A81: =IF(Setup!$A81="","",Setup!$A81) | B81: =IF($A81="","",Setup!$B81) | C81: =IF($A81="","",IF(COUNTIFS(Trips!$Z5:$Z1004,$R81,Trips!$D5:$D1004,$A81)+COUNTIFS(Trips!$Z5:$Z1004,$R81,Trips!$E5:$E1004,$A81)=0,"",COUNTIFS(Trips!$Z5:$Z1004,$R81,Trips!$D5:$D1004,$A81)+COUNTIFS(Trips!$Z5:$Z1004,$R81,Trips!$E5:$E1004,$A81))) | D81: =IF($C81="","",SUMIFS(Trips!$K5:$K1004,Trips!$Z5:$Z1004,$R81,Trips!$D5:$D1004,$A81)+SUMIFS(Trips!$K5:$K1004,Trips!$Z5:$Z1004,$R81,Trips!$E5:$E1004,$A81)) | E81: =IF($C81="","",SUMIFS(Trips!$N5:$N1004,Trips!$Z5:$Z1004,$R81,Trips!$D5:$D1004,$A81)+SUMIFS(Trips!$O5:$O1004,Trips!$Z5:$Z1004,$R81,Trips!$E5:$E1004,$A81)) | F81: =IF($C81="","",SUMIFS(Trips!$P5:$P1004,Trips!$Z5:$Z1004,$R81,Trips!$D5:$D1004,$A81)) | G81: =IF($C81="","",SUMIFS(Trips!$Q5:$Q1004,Trips!$Z5:$Z1004,$R81,Trips!$D5:$D1004,$A81)) | H81: =IF(AND($C81="",$I81="",$J81=""),"",N($E81)+N($F81)+N($G81)) | I81: =IF($A81="","",IFERROR(1/(1/SUMIFS(Expenses!$F5:$F1004,Expenses!$B5:$B1004,"Cash Advance",Expenses!$J5:$J1004,$R81,Expenses!$E5:$E1004,$A81)),"")) | J81: =IF($A81="","",IFERROR(1/(1/SUMIFS(Expenses!$F5:$F1004,Expenses!$B5:$B1004,"Payroll Payout",Expenses!$J5:$J1004,$R81,Expenses!$E5:$E1004,$A81)),"")) | K81: =IF($H81="","",N($H81)-N($I81)-N($J81)) | L81: =IF($K81="","",IF($K81>0.5,"TO PAY",IF($K81<-0.5,"ADVANCE / OWES","SETTLED"))) | R81: 46174
A82: =IF(Setup!$A82="","",Setup!$A82) | B82: =IF($A82="","",Setup!$B82) | C82: =IF($A82="","",IF(COUNTIFS(Trips!$Z5:$Z1004,$R82,Trips!$D5:$D1004,$A82)+COUNTIFS(Trips!$Z5:$Z1004,$R82,Trips!$E5:$E1004,$A82)=0,"",COUNTIFS(Trips!$Z5:$Z1004,$R82,Trips!$D5:$D1004,$A82)+COUNTIFS(Trips!$Z5:$Z1004,$R82,Trips!$E5:$E1004,$A82))) | D82: =IF($C82="","",SUMIFS(Trips!$K5:$K1004,Trips!$Z5:$Z1004,$R82,Trips!$D5:$D1004,$A82)+SUMIFS(Trips!$K5:$K1004,Trips!$Z5:$Z1004,$R82,Trips!$E5:$E1004,$A82)) | E82: =IF($C82="","",SUMIFS(Trips!$N5:$N1004,Trips!$Z5:$Z1004,$R82,Trips!$D5:$D1004,$A82)+SUMIFS(Trips!$O5:$O1004,Trips!$Z5:$Z1004,$R82,Trips!$E5:$E1004,$A82)) | F82: =IF($C82="","",SUMIFS(Trips!$P5:$P1004,Trips!$Z5:$Z1004,$R82,Trips!$D5:$D1004,$A82)) | G82: =IF($C82="","",SUMIFS(Trips!$Q5:$Q1004,Trips!$Z5:$Z1004,$R82,Trips!$D5:$D1004,$A82)) | H82: =IF(AND($C82="",$I82="",$J82=""),"",N($E82)+N($F82)+N($G82)) | I82: =IF($A82="","",IFERROR(1/(1/SUMIFS(Expenses!$F5:$F1004,Expenses!$B5:$B1004,"Cash Advance",Expenses!$J5:$J1004,$R82,Expenses!$E5:$E1004,$A82)),"")) | J82: =IF($A82="","",IFERROR(1/(1/SUMIFS(Expenses!$F5:$F1004,Expenses!$B5:$B1004,"Payroll Payout",Expenses!$J5:$J1004,$R82,Expenses!$E5:$E1004,$A82)),"")) | K82: =IF($H82="","",N($H82)-N($I82)-N($J82)) | L82: =IF($K82="","",IF($K82>0.5,"TO PAY",IF($K82<-0.5,"ADVANCE / OWES","SETTLED"))) | R82: 46174
A83: =IF(Setup!$A83="","",Setup!$A83) | B83: =IF($A83="","",Setup!$B83) | C83: =IF($A83="","",IF(COUNTIFS(Trips!$Z5:$Z1004,$R83,Trips!$D5:$D1004,$A83)+COUNTIFS(Trips!$Z5:$Z1004,$R83,Trips!$E5:$E1004,$A83)=0,"",COUNTIFS(Trips!$Z5:$Z1004,$R83,Trips!$D5:$D1004,$A83)+COUNTIFS(Trips!$Z5:$Z1004,$R83,Trips!$E5:$E1004,$A83))) | D83: =IF($C83="","",SUMIFS(Trips!$K5:$K1004,Trips!$Z5:$Z1004,$R83,Trips!$D5:$D1004,$A83)+SUMIFS(Trips!$K5:$K1004,Trips!$Z5:$Z1004,$R83,Trips!$E5:$E1004,$A83)) | E83: =IF($C83="","",SUMIFS(Trips!$N5:$N1004,Trips!$Z5:$Z1004,$R83,Trips!$D5:$D1004,$A83)+SUMIFS(Trips!$O5:$O1004,Trips!$Z5:$Z1004,$R83,Trips!$E5:$E1004,$A83)) | F83: =IF($C83="","",SUMIFS(Trips!$P5:$P1004,Trips!$Z5:$Z1004,$R83,Trips!$D5:$D1004,$A83)) | G83: =IF($C83="","",SUMIFS(Trips!$Q5:$Q1004,Trips!$Z5:$Z1004,$R83,Trips!$D5:$D1004,$A83)) | H83: =IF(AND($C83="",$I83="",$J83=""),"",N($E83)+N($F83)+N($G83)) | I83: =IF($A83="","",IFERROR(1/(1/SUMIFS(Expenses!$F5:$F1004,Expenses!$B5:$B1004,"Cash Advance",Expenses!$J5:$J1004,$R83,Expenses!$E5:$E1004,$A83)),"")) | J83: =IF($A83="","",IFERROR(1/(1/SUMIFS(Expenses!$F5:$F1004,Expenses!$B5:$B1004,"Payroll Payout",Expenses!$J5:$J1004,$R83,Expenses!$E5:$E1004,$A83)),"")) | K83: =IF($H83="","",N($H83)-N($I83)-N($J83)) | L83: =IF($K83="","",IF($K83>0.5,"TO PAY",IF($K83<-0.5,"ADVANCE / OWES","SETTLED"))) | R83: 46174
A84: =IF(Setup!$A84="","",Setup!$A84) | B84: =IF($A84="","",Setup!$B84) | C84: =IF($A84="","",IF(COUNTIFS(Trips!$Z5:$Z1004,$R84,Trips!$D5:$D1004,$A84)+COUNTIFS(Trips!$Z5:$Z1004,$R84,Trips!$E5:$E1004,$A84)=0,"",COUNTIFS(Trips!$Z5:$Z1004,$R84,Trips!$D5:$D1004,$A84)+COUNTIFS(Trips!$Z5:$Z1004,$R84,Trips!$E5:$E1004,$A84))) | D84: =IF($C84="","",SUMIFS(Trips!$K5:$K1004,Trips!$Z5:$Z1004,$R84,Trips!$D5:$D1004,$A84)+SUMIFS(Trips!$K5:$K1004,Trips!$Z5:$Z1004,$R84,Trips!$E5:$E1004,$A84)) | E84: =IF($C84="","",SUMIFS(Trips!$N5:$N1004,Trips!$Z5:$Z1004,$R84,Trips!$D5:$D1004,$A84)+SUMIFS(Trips!$O5:$O1004,Trips!$Z5:$Z1004,$R84,Trips!$E5:$E1004,$A84)) | F84: =IF($C84="","",SUMIFS(Trips!$P5:$P1004,Trips!$Z5:$Z1004,$R84,Trips!$D5:$D1004,$A84)) | G84: =IF($C84="","",SUMIFS(Trips!$Q5:$Q1004,Trips!$Z5:$Z1004,$R84,Trips!$D5:$D1004,$A84)) | H84: =IF(AND($C84="",$I84="",$J84=""),"",N($E84)+N($F84)+N($G84)) | I84: =IF($A84="","",IFERROR(1/(1/SUMIFS(Expenses!$F5:$F1004,Expenses!$B5:$B1004,"Cash Advance",Expenses!$J5:$J1004,$R84,Expenses!$E5:$E1004,$A84)),"")) | J84: =IF($A84="","",IFERROR(1/(1/SUMIFS(Expenses!$F5:$F1004,Expenses!$B5:$B1004,"Payroll Payout",Expenses!$J5:$J1004,$R84,Expenses!$E5:$E1004,$A84)),"")) | K84: =IF($H84="","",N($H84)-N($I84)-N($J84)) | L84: =IF($K84="","",IF($K84>0.5,"TO PAY",IF($K84<-0.5,"ADVANCE / OWES","SETTLED"))) | R84: 46174
A85: =IF(Setup!$A85="","",Setup!$A85) | B85: =IF($A85="","",Setup!$B85) | C85: =IF($A85="","",IF(COUNTIFS(Trips!$Z5:$Z1004,$R85,Trips!$D5:$D1004,$A85)+COUNTIFS(Trips!$Z5:$Z1004,$R85,Trips!$E5:$E1004,$A85)=0,"",COUNTIFS(Trips!$Z5:$Z1004,$R85,Trips!$D5:$D1004,$A85)+COUNTIFS(Trips!$Z5:$Z1004,$R85,Trips!$E5:$E1004,$A85))) | D85: =IF($C85="","",SUMIFS(Trips!$K5:$K1004,Trips!$Z5:$Z1004,$R85,Trips!$D5:$D1004,$A85)+SUMIFS(Trips!$K5:$K1004,Trips!$Z5:$Z1004,$R85,Trips!$E5:$E1004,$A85)) | E85: =IF($C85="","",SUMIFS(Trips!$N5:$N1004,Trips!$Z5:$Z1004,$R85,Trips!$D5:$D1004,$A85)+SUMIFS(Trips!$O5:$O1004,Trips!$Z5:$Z1004,$R85,Trips!$E5:$E1004,$A85)) | F85: =IF($C85="","",SUMIFS(Trips!$P5:$P1004,Trips!$Z5:$Z1004,$R85,Trips!$D5:$D1004,$A85)) | G85: =IF($C85="","",SUMIFS(Trips!$Q5:$Q1004,Trips!$Z5:$Z1004,$R85,Trips!$D5:$D1004,$A85)) | H85: =IF(AND($C85="",$I85="",$J85=""),"",N($E85)+N($F85)+N($G85)) | I85: =IF($A85="","",IFERROR(1/(1/SUMIFS(Expenses!$F5:$F1004,Expenses!$B5:$B1004,"Cash Advance",Expenses!$J5:$J1004,$R85,Expenses!$E5:$E1004,$A85)),"")) | J85: =IF($A85="","",IFERROR(1/(1/SUMIFS(Expenses!$F5:$F1004,Expenses!$B5:$B1004,"Payroll Payout",Expenses!$J5:$J1004,$R85,Expenses!$E5:$E1004,$A85)),"")) | K85: =IF($H85="","",N($H85)-N($I85)-N($J85)) | L85: =IF($K85="","",IF($K85>0.5,"TO PAY",IF($K85<-0.5,"ADVANCE / OWES","SETTLED"))) | R85: 46174
A86: =IF(Setup!$A86="","",Setup!$A86) | B86: =IF($A86="","",Setup!$B86) | C86: =IF($A86="","",IF(COUNTIFS(Trips!$Z5:$Z1004,$R86,Trips!$D5:$D1004,$A86)+COUNTIFS(Trips!$Z5:$Z1004,$R86,Trips!$E5:$E1004,$A86)=0,"",COUNTIFS(Trips!$Z5:$Z1004,$R86,Trips!$D5:$D1004,$A86)+COUNTIFS(Trips!$Z5:$Z1004,$R86,Trips!$E5:$E1004,$A86))) | D86: =IF($C86="","",SUMIFS(Trips!$K5:$K1004,Trips!$Z5:$Z1004,$R86,Trips!$D5:$D1004,$A86)+SUMIFS(Trips!$K5:$K1004,Trips!$Z5:$Z1004,$R86,Trips!$E5:$E1004,$A86)) | E86: =IF($C86="","",SUMIFS(Trips!$N5:$N1004,Trips!$Z5:$Z1004,$R86,Trips!$D5:$D1004,$A86)+SUMIFS(Trips!$O5:$O1004,Trips!$Z5:$Z1004,$R86,Trips!$E5:$E1004,$A86)) | F86: =IF($C86="","",SUMIFS(Trips!$P5:$P1004,Trips!$Z5:$Z1004,$R86,Trips!$D5:$D1004,$A86)) | G86: =IF($C86="","",SUMIFS(Trips!$Q5:$Q1004,Trips!$Z5:$Z1004,$R86,Trips!$D5:$D1004,$A86)) | H86: =IF(AND($C86="",$I86="",$J86=""),"",N($E86)+N($F86)+N($G86)) | I86: =IF($A86="","",IFERROR(1/(1/SUMIFS(Expenses!$F5:$F1004,Expenses!$B5:$B1004,"Cash Advance",Expenses!$J5:$J1004,$R86,Expenses!$E5:$E1004,$A86)),"")) | J86: =IF($A86="","",IFERROR(1/(1/SUMIFS(Expenses!$F5:$F1004,Expenses!$B5:$B1004,"Payroll Payout",Expenses!$J5:$J1004,$R86,Expenses!$E5:$E1004,$A86)),"")) | K86: =IF($H86="","",N($H86)-N($I86)-N($J86)) | L86: =IF($K86="","",IF($K86>0.5,"TO PAY",IF($K86<-0.5,"ADVANCE / OWES","SETTLED"))) | R86: 46174
A87: =IF(Setup!$A87="","",Setup!$A87) | B87: =IF($A87="","",Setup!$B87) | C87: =IF($A87="","",IF(COUNTIFS(Trips!$Z5:$Z1004,$R87,Trips!$D5:$D1004,$A87)+COUNTIFS(Trips!$Z5:$Z1004,$R87,Trips!$E5:$E1004,$A87)=0,"",COUNTIFS(Trips!$Z5:$Z1004,$R87,Trips!$D5:$D1004,$A87)+COUNTIFS(Trips!$Z5:$Z1004,$R87,Trips!$E5:$E1004,$A87))) | D87: =IF($C87="","",SUMIFS(Trips!$K5:$K1004,Trips!$Z5:$Z1004,$R87,Trips!$D5:$D1004,$A87)+SUMIFS(Trips!$K5:$K1004,Trips!$Z5:$Z1004,$R87,Trips!$E5:$E1004,$A87)) | E87: =IF($C87="","",SUMIFS(Trips!$N5:$N1004,Trips!$Z5:$Z1004,$R87,Trips!$D5:$D1004,$A87)+SUMIFS(Trips!$O5:$O1004,Trips!$Z5:$Z1004,$R87,Trips!$E5:$E1004,$A87)) | F87: =IF($C87="","",SUMIFS(Trips!$P5:$P1004,Trips!$Z5:$Z1004,$R87,Trips!$D5:$D1004,$A87)) | G87: =IF($C87="","",SUMIFS(Trips!$Q5:$Q1004,Trips!$Z5:$Z1004,$R87,Trips!$D5:$D1004,$A87)) | H87: =IF(AND($C87="",$I87="",$J87=""),"",N($E87)+N($F87)+N($G87)) | I87: =IF($A87="","",IFERROR(1/(1/SUMIFS(Expenses!$F5:$F1004,Expenses!$B5:$B1004,"Cash Advance",Expenses!$J5:$J1004,$R87,Expenses!$E5:$E1004,$A87)),"")) | J87: =IF($A87="","",IFERROR(1/(1/SUMIFS(Expenses!$F5:$F1004,Expenses!$B5:$B1004,"Payroll Payout",Expenses!$J5:$J1004,$R87,Expenses!$E5:$E1004,$A87)),"")) | K87: =IF($H87="","",N($H87)-N($I87)-N($J87)) | L87: =IF($K87="","",IF($K87>0.5,"TO PAY",IF($K87<-0.5,"ADVANCE / OWES","SETTLED"))) | R87: 46174
A88: MONTH TOTAL | C88: =IF(COUNT(C76:C87)=0,"",SUM(C76:C87)) | D88: =IF(COUNT(D76:D87)=0,"",SUM(D76:D87)) | E88: =IF(COUNT(E76:E87)=0,"",SUM(E76:E87)) | F88: =IF(COUNT(F76:F87)=0,"",SUM(F76:F87)) | G88: =IF(COUNT(G76:G87)=0,"",SUM(G76:G87)) | H88: =IF(COUNT(H76:H87)=0,"",SUM(H76:H87)) | I88: =IF(COUNT(I76:I87)=0,"",SUM(I76:I87)) | J88: =IF(COUNT(J76:J87)=0,"",SUM(J76:J87)) | K88: =IF(COUNT(K76:K87)=0,"",SUM(K76:K87))
A89: JULY 2026 · crew earnings & settlement
A90: =IF(Setup!$A76="","",Setup!$A76) | B90: =IF($A90="","",Setup!$B76) | C90: =IF($A90="","",IF(COUNTIFS(Trips!$Z5:$Z1004,$R90,Trips!$D5:$D1004,$A90)+COUNTIFS(Trips!$Z5:$Z1004,$R90,Trips!$E5:$E1004,$A90)=0,"",COUNTIFS(Trips!$Z5:$Z1004,$R90,Trips!$D5:$D1004,$A90)+COUNTIFS(Trips!$Z5:$Z1004,$R90,Trips!$E5:$E1004,$A90))) | D90: =IF($C90="","",SUMIFS(Trips!$K5:$K1004,Trips!$Z5:$Z1004,$R90,Trips!$D5:$D1004,$A90)+SUMIFS(Trips!$K5:$K1004,Trips!$Z5:$Z1004,$R90,Trips!$E5:$E1004,$A90)) | E90: =IF($C90="","",SUMIFS(Trips!$N5:$N1004,Trips!$Z5:$Z1004,$R90,Trips!$D5:$D1004,$A90)+SUMIFS(Trips!$O5:$O1004,Trips!$Z5:$Z1004,$R90,Trips!$E5:$E1004,$A90)) | F90: =IF($C90="","",SUMIFS(Trips!$P5:$P1004,Trips!$Z5:$Z1004,$R90,Trips!$D5:$D1004,$A90)) | G90: =IF($C90="","",SUMIFS(Trips!$Q5:$Q1004,Trips!$Z5:$Z1004,$R90,Trips!$D5:$D1004,$A90)) | H90: =IF(AND($C90="",$I90="",$J90=""),"",N($E90)+N($F90)+N($G90)) | I90: =IF($A90="","",IFERROR(1/(1/SUMIFS(Expenses!$F5:$F1004,Expenses!$B5:$B1004,"Cash Advance",Expenses!$J5:$J1004,$R90,Expenses!$E5:$E1004,$A90)),"")) | J90: =IF($A90="","",IFERROR(1/(1/SUMIFS(Expenses!$F5:$F1004,Expenses!$B5:$B1004,"Payroll Payout",Expenses!$J5:$J1004,$R90,Expenses!$E5:$E1004,$A90)),"")) | K90: =IF($H90="","",N($H90)-N($I90)-N($J90)) | L90: =IF($K90="","",IF($K90>0.5,"TO PAY",IF($K90<-0.5,"ADVANCE / OWES","SETTLED"))) | R90: 46204
A91: =IF(Setup!$A77="","",Setup!$A77) | B91: =IF($A91="","",Setup!$B77) | C91: =IF($A91="","",IF(COUNTIFS(Trips!$Z5:$Z1004,$R91,Trips!$D5:$D1004,$A91)+COUNTIFS(Trips!$Z5:$Z1004,$R91,Trips!$E5:$E1004,$A91)=0,"",COUNTIFS(Trips!$Z5:$Z1004,$R91,Trips!$D5:$D1004,$A91)+COUNTIFS(Trips!$Z5:$Z1004,$R91,Trips!$E5:$E1004,$A91))) | D91: =IF($C91="","",SUMIFS(Trips!$K5:$K1004,Trips!$Z5:$Z1004,$R91,Trips!$D5:$D1004,$A91)+SUMIFS(Trips!$K5:$K1004,Trips!$Z5:$Z1004,$R91,Trips!$E5:$E1004,$A91)) | E91: =IF($C91="","",SUMIFS(Trips!$N5:$N1004,Trips!$Z5:$Z1004,$R91,Trips!$D5:$D1004,$A91)+SUMIFS(Trips!$O5:$O1004,Trips!$Z5:$Z1004,$R91,Trips!$E5:$E1004,$A91)) | F91: =IF($C91="","",SUMIFS(Trips!$P5:$P1004,Trips!$Z5:$Z1004,$R91,Trips!$D5:$D1004,$A91)) | G91: =IF($C91="","",SUMIFS(Trips!$Q5:$Q1004,Trips!$Z5:$Z1004,$R91,Trips!$D5:$D1004,$A91)) | H91: =IF(AND($C91="",$I91="",$J91=""),"",N($E91)+N($F91)+N($G91)) | I91: =IF($A91="","",IFERROR(1/(1/SUMIFS(Expenses!$F5:$F1004,Expenses!$B5:$B1004,"Cash Advance",Expenses!$J5:$J1004,$R91,Expenses!$E5:$E1004,$A91)),"")) | J91: =IF($A91="","",IFERROR(1/(1/SUMIFS(Expenses!$F5:$F1004,Expenses!$B5:$B1004,"Payroll Payout",Expenses!$J5:$J1004,$R91,Expenses!$E5:$E1004,$A91)),"")) | K91: =IF($H91="","",N($H91)-N($I91)-N($J91)) | L91: =IF($K91="","",IF($K91>0.5,"TO PAY",IF($K91<-0.5,"ADVANCE / OWES","SETTLED"))) | R91: 46204
